Workbook

Sheet 01_Capa
B2: FINANCE OPS & ANALYTICS
B3: Modelo Financeiro Gerencial — Empresa Beauty Omnichannel
B5: Período: | C5: Jan/2023 a Dez/2024 (24 meses)
B6: Canais: | C6: E-commerce · Marketplace · Franquia · Loja Própria
B7: Categorias: | C7: Skincare · Maquiagem · Perfumes · Haircare
B8: SKUs: | C8: 58 produtos ativos
B9: Receita líquida 24m: | C9: R$ 3,99 MM (média mensal R$ 166,5 k)
B10: Status do modelo: | C10: Operação em virada — break-even cruzado em Nov-Dez/2024
B12: ÍNDICE DE ABAS
B13: 02_Premissas | C13: Parâmetros editáveis do modelo (tributos, forecast, BPO)
B14: 03_Base_Vendas | C14: Base agregada de vendas: 24m × 4 canais × 4 categorias
B15: 04_Base_Despesas | C15: Base agregada de despesas operacionais por categoria
B16: 05_Base_Apoio | C16: Pagamentos, estoque, clientes e calendário
B17: 06_DRE_Consolidada | C17: DRE gerencial mensal — receita até EBITDA e resultado
B18: 07_DRE_por_Canal | C18: DRE replicada para cada canal de venda
B19: 08_DRE_por_Categoria | C19: DRE replicada para cada categoria de produto
B20: 09_Fluxo_de_Caixa | C20: Fluxo de caixa operacional pelos métodos direto e indireto
B21: 10_Capital_de_Giro | C21: PMR · PMP · PME · NCG · ciclo financeiro
B22: 11_Estoque_e_Giro | C22: Aging, cobertura e giro de estoque por categoria
B23: 12_KPIs | C23: Painel de indicadores financeiros e operacionais
B24: 13_Forecast_6M | C24: Projeção simplificada do 1º semestre de 2025
... B26: 15_Dashboard_Exec | C26: Visão executiva consolidada com gráficos
B29: LEGENDA DE CORES
B30: Texto azul | C30: Input editável (premissa, parâmetro)
B31: Texto preto | C31: Fórmula / cálculo
B32: Texto verde | C32: Link entre abas
B33: Fundo amarelo | C33: Premissa-chave (revisar com frequência)
B34: Fundo verde | C34: Resultado favorável
B35: Fundo vermelho | C35: Resultado desfavorável / alerta
B38: Modelo gerencial. Tributos federais/estaduais não inclusos: receita líquida = receita bruta − devoluções − comissões de canal.

Sheet 02_Premissas
A2: 02 — PREMISSAS DO MODELO
A3: Parâmetros editáveis em azul. Alterações recalculam todas as abas.
A5: Forecast — Crescimento mensal projetado (média móvel × premissa)
B6: Canal | C6: Crescimento (%a.m.) | D6: Janela média (meses) | G6: Observação
B7: E-commerce | C7: 0.025 | D7: 3 | G7: canal com maior elasticidade — alvo de tração
B8: Marketplace | C8: 0.015 | D8: 3 | G8: crescimento moderado, dependente de comissão
B9: Franquia | C9: 0.01 | D9: 3 | G9: expansão controlada, novas unidades em ramp-up
B10: Loja Própria | C10: 0.008 | D10: 3 | G10: footprint físico estável, foco em produtividade
A12: Inflação aplicada às despesas no forecast
B13: Inflação mensal | C13: 0.005 | G13: ≈ 6,2% a.a. — proxy IPCA
A15: Sazonalidade — fatores aplicados ao forecast por mês
B16: Mês | C16: Fator (1.0 = neutro) | G16: Observação
B17: Jan | C17: 0.95 | G17: pós-festas
B18: Fev | C18: 0.9 | G18: mês curto, baixa
B19: Mar | C19: 1 | G19: neutro
B20: Abr | C20: 0.95 | G20: neutro/baixa
B21: Mai | C21: 1.2 | G21: Dia das Mães — alta
B22: Jun | C22: 1.05 | G22: Namorados
A24: Antes vs Depois — premissas do projeto de transformação
B25: Métrica | C25: Antes | D25: Depois | G25: Observação
B26: Prazo de fechamento (dias úteis) | C26: 12 | D26: 5 | G26: Redução de 7 dias por fechamento
B27: Horas/mês — analista financeiro | C27: 200 | D27: 80 | G27: Liberação de capacidade analítica
B28: Custo médio R$/hora analista | C28: 85 | D28: 85 | G28: Custo total (folha + encargos)
B29: Lançamentos retrabalho/mês | C29: 12 | D29: 2 | G29: Erros pós-fechamento que retornam
B30: Tempo médio retrabalho (h) | C30: 4 | D30: 4 | G30: Hora analista por lançamento
B31: Divergências gateway × ERP/mês | C31: 7 | D31: 1 | G31: Captura automática vs revisão manual
B32: Comentários executivos manuais (h) | C32: 16 | D32: 4 | G32: Geração por IA acelera narrativa
A34: Definições contábeis
B35: Definição de Receita Líquida | C35: Receita bruta − devoluções − comissões de canal
B36: Tratamento de tributos | C36: Não inclusos no modelo gerencial (receita líquida ≈ líquida de canal)
B37: Custo dos Produtos Vendidos | C37: Custo médio ponderado por lote × quantidade (proxy contábil)
B38: EBITDA | C38: Margem contribuição − despesas operacionais (excl. depreciação e financeiro)
B39: EBIT | C39: EBITDA − depreciação
B40: Resultado Operacional | C40: EBIT − despesas financeiras

Sheet 03_Base_Vendas
A1: 03 — BASE: VENDAS AGREGADAS
A2: Agregação mensal por canal × categoria. Fonte das fórmulas das DREs.
A4: ano_mes | B4: canal | C4: categoria | D4: qtd_transacoes | E4: unidades | F4: receita_bruta | G4: devolucoes | H4: comissoes | I4: receita_liquida | J4: cmv | K4: margem_contrib | L4: qtd_devolvidas
A5: 2023-01 | B5: ecommerce | C5: haircare | D5: 41 | E5: 69 | F5: 8597.49 | G5: 617.67 | H5: 348.15 | I5: 7631.67 | J5: 4432.72 | K5: 3198.95 | L5: 3
A6: 2023-01 | B6: ecommerce | C6: maquiagem | D6: 70 | E6: 118 | F6: 10380.29 | G6: 172.73 | H6: 419.55 | I6: 9788.01 | J6: 4971.72 | K6: 4816.29 | L6: 1
A7: 2023-01 | B7: ecommerce | C7: perfumes | D7: 45 | E7: 89 | F7: 26995.05 | G7: 222.15 | H7: 1114.33 | I7: 25658.57 | J7: 14398.67 | K7: 11259.9 | L7: 1
A8: 2023-01 | B8: ecommerce | C8: skincare | D8: 68 | E8: 120 | F8: 22663.36 | G8: 929.98 | H8: 924.52 | I8: 20808.86 | J8: 8921.7 | K8: 11887.16 | L8: 3
A9: 2023-01 | B9: franquia | C9: haircare | D9: 14 | E9: 24 | F9: 2876.06 | G9: 0 | H9: 348.81 | I9: 2527.25 | J9: 1428.66 | K9: 1098.59 | L9: 0
A10: 2023-01 | B10: franquia | C10: maquiagem | D10: 36 | E10: 65 | F10: 6919.04 | G10: 302.34 | H10: 824.63 | I10: 5792.07 | J10: 3293.41 | K10: 2498.66 | L10: 3
A11: 2023-01 | B11: franquia | C11: perfumes | D11: 30 | E11: 57 | F11: 17868.8 | G11: 1649.8 | H11: 2160.58 | I11: 14058.42 | J11: 9400.91 | K11: 4657.51 | L11: 3
A12: 2023-01 | B12: franquia | C12: skincare | D12: 36 | E12: 61 | F12: 11997.82 | G12: 687.83 | H12: 1442.28 | I12: 9867.71 | J12: 4717.14 | K12: 5150.57 | L12: 2
A13: 2023-01 | B13: loja_propria | C13: haircare | D13: 10 | E13: 14 | F13: 1619.46 | G13: 0 | H13: 0.37 | I13: 1619.09 | J13: 855.15 | K13: 763.94 | L13: 0
A14: 2023-01 | B14: loja_propria | C14: maquiagem | D14: 24 | E14: 44 | F14: 3703.68 | G14: 0 | H14: 1.04 | I14: 3702.64 | J14: 1779.71 | K14: 1922.93 | L14: 0
A15: 2023-01 | B15: loja_propria | C15: perfumes | D15: 10 | E15: 15 | F15: 3841.65 | G15: 0 | H15: 2.38 | I15: 3839.27 | J15: 2007.8 | K15: 1831.47 | L15: 0
A16: 2023-01 | B16: loja_propria | C16: skincare | D16: 23 | E16: 38 | F16: 6122.39 | G16: 0 | H16: 0.37 | I16: 6122.02 | J16: 2487.69 | K16: 3634.33 | L16: 0
... A388: 2024-12 | B388: marketplace | C388: skincare | D388: 83 | E388: 162 | F388: 31199.98 | G388: 4631.1 | H388: 5322.54 | I388: 21246.34 | J388: 12451.85 | K388: 8794.49 | L388: 9

Sheet 04_Base_Despesas
A1: 04 — BASE: DESPESAS AGREGADAS
A2: Despesas operacionais por categoria, com competência mensal.
A4: ano_mes | B4: categoria | C4: qtd | D4: valor
A5: 2023-01 | B5: administrativo | C5: 4 | D5: 4109.09
A6: 2023-01 | B6: aluguel | C6: 5 | D6: 9500.01
A7: 2023-01 | B7: depreciacao | C7: 3 | D7: 2199.99
A8: 2023-01 | B8: financeiro | C8: 1 | D8: 1365.44
A9: 2023-01 | B9: logistica | C9: 4 | D9: 8993.95
A10: 2023-01 | B10: marketing | C10: 2 | D10: 17846.39
A11: 2023-01 | B11: outros | C11: 2 | D11: 791.43
A12: 2023-01 | B12: pessoal | C12: 5 | D12: 50652.31
A13: 2023-01 | B13: tecnologia | C13: 6 | D13: 6715.05
A14: 2023-02 | B14: administrativo | C14: 1 | D14: 2500
A15: 2023-02 | B15: aluguel | C15: 3 | D15: 9500
A16: 2023-02 | B16: depreciacao | C16: 2 | D16: 2200
... A220: 2024-12 | B220: tecnologia | C220: 3 | D220: 6596.33
A223: Visão alternativa — Despesas por Centro de Custo
A224: ano_mes | B224: centro_custo | C224: qtd | D224: valor
A225: 2023-01 | B225: administrativo | C225: 1 | D225: 27719.13
A226: 2023-01 | B226: armazenagem | C226: 3 | D226: 2907.87
A227: 2023-01 | B227: ativos | C227: 3 | D227: 2199.99
A228: 2023-01 | B228: comercial | C228: 1 | D228: 13995.72
A229: 2023-01 | B229: contabilidade | C229: 3 | D229: 2499.99
A230: 2023-01 | B230: digital | C230: 1 | D230: 14164.74
A231: 2023-01 | B231: erp_gateway | C231: 3 | D231: 2199.99
A232: 2023-01 | B232: estoque | C232: 2 | D232: 3000
A233: 2023-01 | B233: frete_saida | C233: 1 | D233: 6086.08
A234: 2023-01 | B234: juridico | C234: 1 | D234: 1609.1
A235: 2023-01 | B235: logistica | C235: 3 | D235: 8937.46
A236: 2023-01 | B236: operacional | C236: 3 | D236: 6500.01
... A601: 2024-12 | B601: varios | C601: 1 | D601: 648.47

Sheet 05_Base_Apoio
A1: 05 — BASES DE APOIO
A2: Pagamentos, estoque, clientes e calendário consolidados.
A4: Pagamentos por canal × mês (PMR e taxas)
A5: ano_mes | B5: canal | C5: qtd | D5: valor_bruto | E5: valor_erp | F5: taxa_total | G5: divergencia | H5: prazo_gateway_med | I5: prazo_erp_med
A6: 2023-01 | B6: ecommerce | C6: 1 | D6: 63887.11 | E6: 62698.31 | F6: 951.92 | G6: -236.88 | H6: 2 | I6: 14
A7: 2023-01 | B7: franquia | C7: 1 | D7: 32245.45 | E7: 32681.45 | F7: 0 | G7: 436 | H7: 0 | I7: 21
A8: 2023-01 | B8: loja_propria | C8: 1 | D8: 15283.02 | E8: 14978.34 | F8: 349.98 | G8: 45.3 | H8: 1 | I8: 3
A9: 2023-01 | B9: marketplace | C9: 1 | D9: 38606.57 | E9: 37838.3 | F9: 768.27 | G9: 0 | H9: 2 | I9: 30
A10: 2023-02 | B10: ecommerce | C10: 1 | D10: 59873.22 | E10: 59276.02 | F10: 892.11 | G10: 294.91 | H10: 2 | I10: 14
A11: 2023-02 | B11: franquia | C11: 1 | D11: 17813.16 | E11: 17813.16 | F11: 0 | G11: 0 | H11: 0 | I11: 21
A12: 2023-02 | B12: loja_propria | C12: 1 | D12: 16586.45 | E12: 16206.62 | F12: 379.83 | G12: 0 | H12: 1 | I12: 3
A13: 2023-02 | B13: marketplace | C13: 1 | D13: 30438.67 | E13: 29832.94 | F13: 605.73 | G13: 0 | H13: 2 | I13: 30
A14: 2023-03 | B14: ecommerce | C14: 1 | D14: 65382.53 | E14: 64408.33 | F14: 974.2 | G14: 0 | H14: 2 | I14: 14
A15: 2023-03 | B15: franquia | C15: 1 | D15: 22666.4 | E15: 22666.4 | F15: 0 | G15: 0 | H15: 0 | I15: 21
A16: 2023-03 | B16: loja_propria | C16: 1 | D16: 22127.87 | E16: 21621.14 | F16: 506.73 | G16: 0 | H16: 1 | I16: 3
A17: 2023-03 | B17: marketplace | C17: 1 | D17: 41925 | E17: 41090.69 | F17: 834.31 | G17: 0 | H17: 2 | I17: 30
... A101: 2024-12 | B101: marketplace | C101: 1 | D101: 53544.75 | E101: 51783.47 | F101: 1065.54 | G101: -695.74 | H101: 2 | I101: 30
A104: Receita líquida por tipo de compra (recorrente vs pontual)
A105: ano_mes | B105: canal | C105: recorrente | D105: pontual
A106: 2023-01 | B106: ecommerce | C106: 13459.69 | D106: 50427.42
A107: 2023-01 | B107: franquia | C107: 11086.46 | D107: 21158.99
A108: 2023-01 | B108: loja_propria | C108: 4673.91 | D108: 10609.11
A109: 2023-01 | B109: marketplace | C109: 14283.4 | D109: 24323.17
A110: 2023-02 | B110: ecommerce | C110: 14781.29 | D110: 45091.93
A111: 2023-02 | B111: franquia | C111: 3254.25 | D111: 14558.91
A112: 2023-02 | B112: loja_propria | C112: 5465.85 | D112: 11120.6
A113: 2023-02 | B113: marketplace | C113: 10966.61 | D113: 19472.06
A114: 2023-03 | B114: ecommerce | C114: 18029.01 | D114: 47353.52
A115: 2023-03 | B115: franquia | C115: 6158.79 | D115: 16507.61
A116: 2023-03 | B116: loja_propria | C116: 6647.19 | D116: 15480.68
A117: 2023-03 | B117: marketplace | C117: 14649.28 | D117: 27275.72
... A201: 2024-12 | B201: marketplace | C201: 17350.77 | D201: 36193.98
A204: Estoque — aging por categoria × status
A205: categoria | B205: status_aging | C205: qtd_lotes | D205: unidades | E205: valor | F205: aging_med
A206: haircare | B206: alerta | C206: 6 | D206: 725 | E206: 68709.52 | F206: 266.33
A207: haircare | B207: critico | C207: 21 | D207: 2955 | E207: 196907.02 | F207: 538.24
A208: haircare | B208: normal | C208: 4 | D208: 659 | E208: 44088.54 | F208: 146.5
A209: maquiagem | B209: alerta | C209: 6 | D209: 628 | E209: 25048.84 | F209: 278.33
A210: maquiagem | B210: critico | C210: 31 | D210: 4939 | E210: 232641.52 | F210: 538.13
A211: maquiagem | B211: normal | C211: 16 | D211: 2327 | E211: 103523.36 | F211: 88.5
A212: perfumes | B212: alerta | C212: 14 | D212: 1701 | E212: 296164.49 | F212: 282.36
A213: perfumes | B213: critico | C213: 24 | D213: 3428 | E213: 546495.63 | F213: 519.5
A214: perfumes | B214: normal | C214: 8 | D214: 1297 | E214: 236611.44 | F214: 86.12
A215: skincare | B215: alerta | C215: 20 | D215: 2818 | E215: 212317.45 | F215: 269.15
A216: skincare | B216: critico | C216: 35 | D216: 6521 | E216: 508851.86 | F216: 520.26
A217: skincare | B217: normal | C217: 17 | D217: 1923 | E217: 144294.75 | F217: 101
A220: PME ponderado por categoria
A221: categoria | B221: valor_total | C221: unidades_total | D221: pme_ponderado
A222: haircare | B222: 309705.08 | C222: 4339 | D222: 401.44
A223: maquiagem | B223: 361213.72 | C223: 7894 | D223: 391.06
A224: perfumes | B224: 1079271.6 | C224: 6426 | D224: 353.39
A225: skincare | B225: 865464.06 | C225: 11262 | D225: 383.56
A228: Clientes por canal de aquisição (LTV, ticket, frequência)
A229: canal_aquisicao | B229: qtd_clientes | C229: qtd_recorrentes | D229: ltv_medio | E229: ticket_medio | F229: freq_anual
A230: ecommerce | B230: 896 | C230: 423 | D230: 1436.81 | E230: 217.69 | F230: 2.95
A231: franquia | B231: 413 | C231: 176 | D231: 1529.34 | E231: 226.01 | F231: 2.93
A232: loja_propria | B232: 285 | C232: 141 | D232: 1682.4 | E232: 211.82 | F232: 3.46
A233: marketplace | B233: 606 | C233: 280 | D233: 1512.03 | E233: 210.21 | F233: 3.13
A236: Ranking de SKUs por margem de contribuição (24m)
A237: sku_id | B237: categoria | C237: unidades | D237: receita_liquida | E237: cmv | F237: margem
A238: SKU-PER-010 | B238: perfumes | C238: 431 | D238: 154940.07 | E238: 91254.43 | F238: 63685.64
A239: SKU-PER-004 | B239: perfumes | C239: 423 | D239: 135434.29 | E239: 76389.57 | F239: 59044.72
A240: SKU-SKI-007 | B240: skincare | C240: 436 | D240: 103887.33 | E240: 45102.99 | F240: 58784.34
A241: SKU-PER-001 | B241: perfumes | C241: 439 | D241: 140680.99 | E241: 81993.35 | F241: 58687.64
A242: SKU-SKI-018 | B242: skincare | C242: 436 | D242: 112952.44 | E242: 55228.65 | F242: 57723.79
A243: SKU-PER-013 | B243: perfumes | C243: 426 | D243: 142555.26 | E243: 86001.98 | F243: 56553.28
A244: SKU-PER-012 | B244: perfumes | C244: 440 | D244: 140646.15 | E244: 86801.87 | F244: 53844.28
A245: SKU-SKI-016 | B245: skincare | C245: 443 | D245: 89639.51 | E245: 38284.54 | F245: 51354.97
A246: SKU-PER-006 | B246: perfumes | C246: 445 | D246: 149988.28 | E246: 100346.14 | F246: 49642.14
A247: SKU-SKI-002 | B247: skincare | C247: 429 | D247: 92341.79 | E247: 44955.09 | F247: 47386.7
A248: SKU-PER-003 | B248: perfumes | C248: 436 | D248: 132142.48 | E248: 85413.55 | F248: 46728.93
A249: SKU-PER-009 | B249: perfumes | C249: 426 | D249: 130977.54 | E249: 84790.6 | F249: 46186.94
... A295: SKU-MAQ-016 | B295: maquiagem | C295: 423 | D295: 23346.94 | E295: 14297.36 | F295: 9049.58
A298: PMP — prazo médio de pagamento de despesas
A299: metrica | B299: valor
A300: pmp_simples | B300: 7.3
A301: pmp_ponderado | B301: 7.8
A302: lag_min | B302: 0
A303: lag_max | B303: 15
A304: n_desp | B304: 705
A307: PMR consolidado — gateway vs ERP
A308: metrica | B308: valor
A309: pmr_gateway_simples | B309: 1.2
A310: pmr_gateway_ponderado | B310: 1.5
A311: pmr_erp_simples | B311: 17
A312: pmr_erp_ponderado | B312: 17.8
A313: float_dias_medio | B313: 15.8
A316: Dim Calendário
A317: ano_mes | B317: ano | C317: trimestre | D317: mes_num | E317: mes_nome | F317: periodo | G317: is_alta_temporada
A318: 2023-01 | B318: 2023 | C318: 1 | D318: 1 | E318: Jan | F318: 2023-T1 | G318: =FALSE() -> FALSE
A319: 2023-02 | B319: 2023 | C319: 1 | D319: 2 | E319: Feb | F319: 2023-T1 | G319: =FALSE() -> FALSE
A320: 2023-03 | B320: 2023 | C320: 1 | D320: 3 | E320: Mar | F320: 2023-T1 | G320: =FALSE() -> FALSE
A321: 2023-04 | B321: 2023 | C321: 2 | D321: 4 | E321: Apr | F321: 2023-T2 | G321: =FALSE() -> FALSE
A322: 2023-05 | B322: 2023 | C322: 2 | D322: 5 | E322: May | F322: 2023-T2 | G322: =TRUE() -> TRUE
A323: 2023-06 | B323: 2023 | C323: 2 | D323: 6 | E323: Jun | F323: 2023-T2 | G323: =FALSE() -> FALSE
A324: 2023-07 | B324: 2023 | C324: 3 | D324: 7 | E324: Jul | F324: 2023-T3 | G324: =FALSE() -> FALSE
A325: 2023-08 | B325: 2023 | C325: 3 | D325: 8 | E325: Aug | F325: 2023-T3 | G325: =FALSE() -> FALSE
A326: 2023-09 | B326: 2023 | C326: 3 | D326: 9 | E326: Sep | F326: 2023-T3 | G326: =FALSE() -> FALSE
A327: 2023-10 | B327: 2023 | C327: 4 | D327: 10 | E327: Oct | F327: 2023-T4 | G327: =FALSE() -> FALSE
A328: 2023-11 | B328: 2023 | C328: 4 | D328: 11 | E328: Nov | F328: 2023-T4 | G328: =TRUE() -> TRUE
...

Sheet 06_DRE_Consolidada
A1: 06 — DRE GERENCIAL CONSOLIDADA
A2: Demonstrativo mensal completo: receita até resultado operacional. Total acumulado em Z.
A4: DRE Consolidada — toda a operação
A5: Item | B5: 2023-01 | C5: 2023-02 | D5: 2023-03 | E5: 2023-04 | F5: 2023-05 | G5: 2023-06 | H5: 2023-07 | I5: 2023-08 | J5: 2023-09 | K5: 2023-10 | L5: 2023-11 | M5: 2023-12 | N5: 2024-01 | O5: 2024-02 | P5: 2024-03 | Q5: 2024-04 | R5: 2024-05 | S5: 2024-06 | T5: 2024-07 | U5: 2024-08 | V5: 2024-09 | W5: 2024-10 | X5: 2024-11 | Y5: 2024-12 | Z5: Total 24m
A6: Receita Bruta | B6: =SUMIFS('03_Base_Vendas'!$F$4:$F$387, '03_Base_Vendas'!$A$4:$A$387, B$5) -> 171628.88 | C6: =SUMIFS('03_Base_Vendas'!$F$4:$F$387, '03_Base_Vendas'!$A$4:$A$387, C$5) -> 144550.49 | D6: =SUMIFS('03_Base_Vendas'!$F$4:$F$387, '03_Base_Vendas'!$A$4:$A$387, D$5) -> 173089.52 | E6: =SUMIFS('03_Base_Vendas'!$F$4:$F$387, '03_Base_Vendas'!$A$4:$A$387, E$5) -> 159990.02 | F6: =SUMIFS('03_Base_Vendas'!$F$4:$F$387, '03_Base_Vendas'!$A$4:$A$387, F$5) -> 221309.94 | G6: =SUMIFS('03_Base_Vendas'!$F$4:$F$387, '03_Base_Vendas'!$A$4:$A$387, G$5) -> 191441.59 | H6: =SUMIFS('03_Base_Vendas'!$F$4:$F$387, '03_Base_Vendas'!$A$4:$A$387, H$5) -> 145485.14 | I6: =SUMIFS('03_Base_Vendas'!$F$4:$F$387, '03_Base_Vendas'!$A$4:$A$387, I$5) -> 149405.39 | ... Y6: =SUMIFS('03_Base_Vendas'!$F$4:$F$387, '03_Base_Vendas'!$A$4:$A$387, Y$5) -> 216126.54 | Z6: =SUM(B6:Y6) -> 4540779.6
A7: (−) Devoluções | B7: =SUMIFS('03_Base_Vendas'!$G$4:$G$387, '03_Base_Vendas'!$A$4:$A$387, B$5) -> 5827.19 | C7: =SUMIFS('03_Base_Vendas'!$G$4:$G$387, '03_Base_Vendas'!$A$4:$A$387, C$5) -> 8046.66 | D7: =SUMIFS('03_Base_Vendas'!$G$4:$G$387, '03_Base_Vendas'!$A$4:$A$387, D$5) -> 5842.25 | E7: =SUMIFS('03_Base_Vendas'!$G$4:$G$387, '03_Base_Vendas'!$A$4:$A$387, E$5) -> 6773.99 | F7: =SUMIFS('03_Base_Vendas'!$G$4:$G$387, '03_Base_Vendas'!$A$4:$A$387, F$5) -> 7918.41 | G7: =SUMIFS('03_Base_Vendas'!$G$4:$G$387, '03_Base_Vendas'!$A$4:$A$387, G$5) -> 6477.23 | H7: =SUMIFS('03_Base_Vendas'!$G$4:$G$387, '03_Base_Vendas'!$A$4:$A$387, H$5) -> 4353.16 | I7: =SUMIFS('03_Base_Vendas'!$G$4:$G$387, '03_Base_Vendas'!$A$4:$A$387, I$5) -> 8190.88 | ... Y7: =SUMIFS('03_Base_Vendas'!$G$4:$G$387, '03_Base_Vendas'!$A$4:$A$387, Y$5) -> 5236.03 | Z7: =SUM(B7:Y7) -> 176614.95
A8: (−) Comissões de canal | B8: =SUMIFS('03_Base_Vendas'!$H$4:$H$387, '03_Base_Vendas'!$A$4:$A$387, B$5) -> 15779.54 | C8: =SUMIFS('03_Base_Vendas'!$H$4:$H$387, '03_Base_Vendas'!$A$4:$A$387, C$5) -> 11792.33 | D8: =SUMIFS('03_Base_Vendas'!$H$4:$H$387, '03_Base_Vendas'!$A$4:$A$387, D$5) -> 15145.47 | E8: =SUMIFS('03_Base_Vendas'!$H$4:$H$387, '03_Base_Vendas'!$A$4:$A$387, E$5) -> 13399.87 | F8: =SUMIFS('03_Base_Vendas'!$H$4:$H$387, '03_Base_Vendas'!$A$4:$A$387, F$5) -> 18396.28 | G8: =SUMIFS('03_Base_Vendas'!$H$4:$H$387, '03_Base_Vendas'!$A$4:$A$387, G$5) -> 15242.06 | H8: =SUMIFS('03_Base_Vendas'!$H$4:$H$387, '03_Base_Vendas'!$A$4:$A$387, H$5) -> 11923.25 | I8: =SUMIFS('03_Base_Vendas'!$H$4:$H$387, '03_Base_Vendas'!$A$4:$A$387, I$5) -> 12269.8 | ... Y8: =SUMIFS('03_Base_Vendas'!$H$4:$H$387, '03_Base_Vendas'!$A$4:$A$387, Y$5) -> 16615.29 | Z8: =SUM(B8:Y8) -> 389110.95
A9: Receita Líquida | B9: =B6-B7-B8 -> 150022.15 | C9: =C6-C7-C8 -> 124711.5 | D9: =D6-D7-D8 -> 152101.8 | E9: =E6-E7-E8 -> 139816.16 | F9: =F6-F7-F8 -> 194995.25 | G9: =G6-G7-G8 -> 169722.3 | H9: =H6-H7-H8 -> 129208.73 | I9: =I6-I7-I8 -> 128944.71 | ... Y9: =Y6-Y7-Y8 -> 194275.22 | Z9: =SUM(B9:Y9) -> 3975053.7
A10: (−) CMV | B10: =SUMIFS('03_Base_Vendas'!$J$4:$J$387, '03_Base_Vendas'!$A$4:$A$387, B$5) -> 81211.09 | C10: =SUMIFS('03_Base_Vendas'!$J$4:$J$387, '03_Base_Vendas'!$A$4:$A$387, C$5) -> 68953.1 | D10: =SUMIFS('03_Base_Vendas'!$J$4:$J$387, '03_Base_Vendas'!$A$4:$A$387, D$5) -> 83570.01 | E10: =SUMIFS('03_Base_Vendas'!$J$4:$J$387, '03_Base_Vendas'!$A$4:$A$387, E$5) -> 75794.19 | F10: =SUMIFS('03_Base_Vendas'!$J$4:$J$387, '03_Base_Vendas'!$A$4:$A$387, F$5) -> 104404.86 | G10: =SUMIFS('03_Base_Vendas'!$J$4:$J$387, '03_Base_Vendas'!$A$4:$A$387, G$5) -> 93680.99 | H10: =SUMIFS('03_Base_Vendas'!$J$4:$J$387, '03_Base_Vendas'!$A$4:$A$387, H$5) -> 70276.95 | I10: =SUMIFS('03_Base_Vendas'!$J$4:$J$387, '03_Base_Vendas'!$A$4:$A$387, I$5) -> 70294.68 | ... Y10: =SUMIFS('03_Base_Vendas'!$J$4:$J$387, '03_Base_Vendas'!$A$4:$A$387, Y$5) -> 105108.86 | Z10: =SUM(B10:Y10) -> 2178990.1
A11: Margem de Contribuição | B11: =B9-B10 -> 68811.06 | C11: =C9-C10 -> 55758.4 | D11: =D9-D10 -> 68531.79 | E11: =E9-E10 -> 64021.97 | F11: =F9-F10 -> 90590.39 | G11: =G9-G10 -> 76041.31 | H11: =H9-H10 -> 58931.78 | I11: =I9-I10 -> 58650.03 | ... Y11: =Y9-Y10 -> 89166.36 | Z11: =SUM(B11:Y11) -> 1796063.6
A12: % Margem de Contribuição | B12: =IFERROR(B11/B9,0) -> 0.45867267 | C12: =IFERROR(C11/C9,0) -> 0.4470991 | D12: =IFERROR(D11/D9,0) -> 0.45056528 | E12: =IFERROR(E11/E9,0) -> 0.45790108 | F12: =IFERROR(F11/F9,0) -> 0.46457742 | G12: =IFERROR(G11/G9,0) -> 0.4480337 | H12: =IFERROR(H11/H9,0) -> 0.45609751 | I12: =IFERROR(I11/I9,0) -> 0.45484634 | ... Y12: =IFERROR(Y11/Y9,0) -> 0.45896929 | Z12: =IFERROR($Z$11/$Z$9,0) -> 0.4518338
A13: (−) Pessoal | B13: =SUMIFS('04_Base_Despesas'!$D$4:$D$219, '04_Base_Despesas'!$A$4:$A$219, B$5, '04_Base_Despesas'!$B$4:$B$219, "pessoal") -> 50652.31 | C13: =SUMIFS('04_Base_Despesas'!$D$4:$D$219, '04_Base_Despesas'!$A$4:$A$219, C$5, '04_Base_Despesas'!$B$4:$B$219, "pessoal") -> 52124.12 | D13: =SUMIFS('04_Base_Despesas'!$D$4:$D$219, '04_Base_Despesas'!$A$4:$A$219, D$5, '04_Base_Despesas'!$B$4:$B$219, "pessoal") -> 50124.75 | E13: =SUMIFS('04_Base_Despesas'!$D$4:$D$219, '04_Base_Despesas'!$A$4:$A$219, E$5, '04_Base_Despesas'!$B$4:$B$219, "pessoal") -> 49472.83 | F13: =SUMIFS('04_Base_Despesas'!$D$4:$D$219, '04_Base_Despesas'!$A$4:$A$219, F$5, '04_Base_Despesas'!$B$4:$B$219, "pessoal") -> 51984.88 | G13: =SUMIFS('04_Base_Despesas'!$D$4:$D$219, '04_Base_Despesas'!$A$4:$A$219, G$5, '04_Base_Despesas'!$B$4:$B$219, "pessoal") -> 50582.85 | H13: =SUMIFS('04_Base_Despesas'!$D$4:$D$219, '04_Base_Despesas'!$A$4:$A$219, H$5, '04_Base_Despesas'!$B$4:$B$219, "pessoal") -> 51882.99 | I13: =SUMIFS('04_Base_Despesas'!$D$4:$D$219, '04_Base_Despesas'!$A$4:$A$219, I$5, '04_Base_Despesas'!$B$4:$B$219, "pessoal") -> 51904.5 | ... Y13: =SUMIFS('04_Base_Despesas'!$D$4:$D$219, '04_Base_Despesas'!$A$4:$A$219, Y$5, '04_Base_Despesas'!$B$4:$B$219, "pessoal") -> 51109.32 | Z13: =SUM(B13:Y13) -> 1232369.6
A14: (−) Aluguel | B14: =SUMIFS('04_Base_Despesas'!$D$4:$D$219, '04_Base_Despesas'!$A$4:$A$219, B$5, '04_Base_Despesas'!$B$4:$B$219, "aluguel") -> 9500.01 | C14: =SUMIFS('04_Base_Despesas'!$D$4:$D$219, '04_Base_Despesas'!$A$4:$A$219, C$5, '04_Base_Despesas'!$B$4:$B$219, "aluguel") -> 9500 | D14: =SUMIFS('04_Base_Despesas'!$D$4:$D$219, '04_Base_Despesas'!$A$4:$A$219, D$5, '04_Base_Despesas'!$B$4:$B$219, "aluguel") -> 9500 | E14: =SUMIFS('04_Base_Despesas'!$D$4:$D$219, '04_Base_Despesas'!$A$4:$A$219, E$5, '04_Base_Despesas'!$B$4:$B$219, "aluguel") -> 9500 | F14: =SUMIFS('04_Base_Despesas'!$D$4:$D$219, '04_Base_Despesas'!$A$4:$A$219, F$5, '04_Base_Despesas'!$B$4:$B$219, "aluguel") -> 9500 | G14: =SUMIFS('04_Base_Despesas'!$D$4:$D$219, '04_Base_Despesas'!$A$4:$A$219, G$5, '04_Base_Despesas'!$B$4:$B$219, "aluguel") -> 9500 | H14: =SUMIFS('04_Base_Despesas'!$D$4:$D$219, '04_Base_Despesas'!$A$4:$A$219, H$5, '04_Base_Despesas'!$B$4:$B$219, "aluguel") -> 9500 | I14: =SUMIFS('04_Base_Despesas'!$D$4:$D$219, '04_Base_Despesas'!$A$4:$A$219, I$5, '04_Base_Despesas'!$B$4:$B$219, "aluguel") -> 9500 | ... Y14: =SUMIFS('04_Base_Despesas'!$D$4:$D$219, '04_Base_Despesas'!$A$4:$A$219, Y$5, '04_Base_Despesas'!$B$4:$B$219, "aluguel") -> 9500.01 | Z14: =SUM(B14:Y14) -> 228000.06
A15: (−) Marketing | B15: =SUMIFS('04_Base_Despesas'!$D$4:$D$219, '04_Base_Despesas'!$A$4:$A$219, B$5, '04_Base_Despesas'!$B$4:$B$219, "marketing") -> 17846.39 | C15: =SUMIFS('04_Base_Despesas'!$D$4:$D$219, '04_Base_Despesas'!$A$4:$A$219, C$5, '04_Base_Despesas'!$B$4:$B$219, "marketing") -> 12148.23 | D15: =SUMIFS('04_Base_Despesas'!$D$4:$D$219, '04_Base_Despesas'!$A$4:$A$219, D$5, '04_Base_Despesas'!$B$4:$B$219, "marketing") -> 10991.08 | E15: =SUMIFS('04_Base_Despesas'!$D$4:$D$219, '04_Base_Despesas'!$A$4:$A$219, E$5, '04_Base_Despesas'!$B$4:$B$219, "marketing") -> 12370.69 | F15: =SUMIFS('04_Base_Despesas'!$D$4:$D$219, '04_Base_Despesas'!$A$4:$A$219, F$5, '04_Base_Despesas'!$B$4:$B$219, "marketing") -> 17102.54 | G15: =SUMIFS('04_Base_Despesas'!$D$4:$D$219, '04_Base_Despesas'!$A$4:$A$219, G$5, '04_Base_Despesas'!$B$4:$B$219, "marketing") -> 17727.79 | H15: =SUMIFS('04_Base_Despesas'!$D$4:$D$219, '04_Base_Despesas'!$A$4:$A$219, H$5, '04_Base_Despesas'!$B$4:$B$219, "marketing") -> 9948.49 | I15: =SUMIFS('04_Base_Despesas'!$D$4:$D$219, '04_Base_Despesas'!$A$4:$A$219, I$5, '04_Base_Despesas'!$B$4:$B$219, "marketing") -> 12849.46 | ... Y15: =SUMIFS('04_Base_Despesas'!$D$4:$D$219, '04_Base_Despesas'!$A$4:$A$219, Y$5, '04_Base_Despesas'!$B$4:$B$219, "marketing") -> 14130.97 | Z15: =SUM(B15:Y15) -> 350191.86
A16: (−) Logística | B16: =SUMIFS('04_Base_Despesas'!$D$4:$D$219, '04_Base_Despesas'!$A$4:$A$219, B$5, '04_Base_Despesas'!$B$4:$B$219, "logistica") -> 8993.95 | C16: =SUMIFS('04_Base_Despesas'!$D$4:$D$219, '04_Base_Despesas'!$A$4:$A$219, C$5, '04_Base_Despesas'!$B$4:$B$219, "logistica") -> 9160.58 | D16: =SUMIFS('04_Base_Despesas'!$D$4:$D$219, '04_Base_Despesas'!$A$4:$A$219, D$5, '04_Base_Despesas'!$B$4:$B$219, "logistica") -> 9764.07 | E16: =SUMIFS('04_Base_Despesas'!$D$4:$D$219, '04_Base_Despesas'!$A$4:$A$219, E$5, '04_Base_Despesas'!$B$4:$B$219, "logistica") -> 10858.12 | F16: =SUMIFS('04_Base_Despesas'!$D$4:$D$219, '04_Base_Despesas'!$A$4:$A$219, F$5, '04_Base_Despesas'!$B$4:$B$219, "logistica") -> 9866.92 | G16: =SUMIFS('04_Base_Despesas'!$D$4:$D$219, '04_Base_Despesas'!$A$4:$A$219, G$5, '04_Base_Despesas'!$B$4:$B$219, "logistica") -> 9425.93 | H16: =SUMIFS('04_Base_Despesas'!$D$4:$D$219, '04_Base_Despesas'!$A$4:$A$219, H$5, '04_Base_Despesas'!$B$4:$B$219, "logistica") -> 10739.52 | I16: =SUMIFS('04_Base_Despesas'!$D$4:$D$219, '04_Base_Despesas'!$A$4:$A$219, I$5, '04_Base_Despesas'!$B$4:$B$219, "logistica") -> 10757.29 | ... Y16: =SUMIFS('04_Base_Despesas'!$D$4:$D$219, '04_Base_Despesas'!$A$4:$A$219, Y$5, '04_Base_Despesas'!$B$4:$B$219, "logistica") -> 9303.17 | Z16: =SUM(B16:Y16) -> 238776.73
A17: (−) Tecnologia | B17: =SUMIFS('04_Base_Despesas'!$D$4:$D$219, '04_Base_Despesas'!$A$4:$A$219, B$5, '04_Base_Despesas'!$B$4:$B$219, "tecnologia") -> 6715.05 | C17: =SUMIFS('04_Base_Despesas'!$D$4:$D$219, '04_Base_Despesas'!$A$4:$A$219, C$5, '04_Base_Despesas'!$B$4:$B$219, "tecnologia") -> 6617.13 | D17: =SUMIFS('04_Base_Despesas'!$D$4:$D$219, '04_Base_Despesas'!$A$4:$A$219, D$5, '04_Base_Despesas'!$B$4:$B$219, "tecnologia") -> 6653.07 | E17: =SUMIFS('04_Base_Despesas'!$D$4:$D$219, '04_Base_Despesas'!$A$4:$A$219, E$5, '04_Base_Despesas'!$B$4:$B$219, "tecnologia") -> 6588.75 | F17: =SUMIFS('04_Base_Despesas'!$D$4:$D$219, '04_Base_Despesas'!$A$4:$A$219, F$5, '04_Base_Despesas'!$B$4:$B$219, "tecnologia") -> 6590.3 | G17: =SUMIFS('04_Base_Despesas'!$D$4:$D$219, '04_Base_Despesas'!$A$4:$A$219, G$5, '04_Base_Despesas'!$B$4:$B$219, "tecnologia") -> 6700.43 | H17: =SUMIFS('04_Base_Despesas'!$D$4:$D$219, '04_Base_Despesas'!$A$4:$A$219, H$5, '04_Base_Despesas'!$B$4:$B$219, "tecnologia") -> 6624.29 | I17: =SUMIFS('04_Base_Despesas'!$D$4:$D$219, '04_Base_Despesas'!$A$4:$A$219, I$5, '04_Base_Despesas'!$B$4:$B$219, "tecnologia") -> 6794.75 | ... Y17: =SUMIFS('04_Base_Despesas'!$D$4:$D$219, '04_Base_Despesas'!$A$4:$A$219, Y$5, '04_Base_Despesas'!$B$4:$B$219, "tecnologia") -> 0 | Z17: =SUM(B17:Y17) -> 153669.48
A18: (−) Administrativo | B18: =SUMIFS('04_Base_Despesas'!$D$4:$D$219, '04_Base_Despesas'!$A$4:$A$219, B$5, '04_Base_Despesas'!$B$4:$B$219, "administrativo") -> 4109.09 | C18: =SUMIFS('04_Base_Despesas'!$D$4:$D$219, '04_Base_Despesas'!$A$4:$A$219, C$5, '04_Base_Despesas'!$B$4:$B$219, "administrativo") -> 2500 | D18: =SUMIFS('04_Base_Despesas'!$D$4:$D$219, '04_Base_Despesas'!$A$4:$A$219, D$5, '04_Base_Despesas'!$B$4:$B$219, "administrativo") -> 2500 | E18: =SUMIFS('04_Base_Despesas'!$D$4:$D$219, '04_Base_Despesas'!$A$4:$A$219, E$5, '04_Base_Despesas'!$B$4:$B$219, "administrativo") -> 4557.28 | F18: =SUMIFS('04_Base_Despesas'!$D$4:$D$219, '04_Base_Despesas'!$A$4:$A$219, F$5, '04_Base_Despesas'!$B$4:$B$219, "administrativo") -> 2500 | G18: =SUMIFS('04_Base_Despesas'!$D$4:$D$219, '04_Base_Despesas'!$A$4:$A$219, G$5, '04_Base_Despesas'!$B$4:$B$219, "administrativo") -> 2500 | H18: =SUMIFS('04_Base_Despesas'!$D$4:$D$219, '04_Base_Despesas'!$A$4:$A$219, H$5, '04_Base_Despesas'!$B$4:$B$219, "administrativo") -> 4252.75 | I18: =SUMIFS('04_Base_Despesas'!$D$4:$D$219, '04_Base_Despesas'!$A$4:$A$219, I$5, '04_Base_Despesas'!$B$4:$B$219, "administrativo") -> 2500 | ... Y18: =SUMIFS('04_Base_Despesas'!$D$4:$D$219, '04_Base_Despesas'!$A$4:$A$219, Y$5, '04_Base_Despesas'!$B$4:$B$219, "administrativo") -> 2500 | Z18: =SUM(B18:Y18) -> 75132.22
A19: (−) Outros | B19: =SUMIFS('04_Base_Despesas'!$D$4:$D$219, '04_Base_Despesas'!$A$4:$A$219, B$5, '04_Base_Despesas'!$B$4:$B$219, "outros") -> 791.43 | C19: =SUMIFS('04_Base_Despesas'!$D$4:$D$219, '04_Base_Despesas'!$A$4:$A$219, C$5, '04_Base_Despesas'!$B$4:$B$219, "outros") -> 878.67 | D19: =SUMIFS('04_Base_Despesas'!$D$4:$D$219, '04_Base_Despesas'!$A$4:$A$219, D$5, '04_Base_Despesas'!$B$4:$B$219, "outros") -> 864.81 | E19: =SUMIFS('04_Base_Despesas'!$D$4:$D$219, '04_Base_Despesas'!$A$4:$A$219, E$5, '04_Base_Despesas'!$B$4:$B$219, "outros") -> 688.55 | F19: =SUMIFS('04_Base_Despesas'!$D$4:$D$219, '04_Base_Despesas'!$A$4:$A$219, F$5, '04_Base_Despesas'!$B$4:$B$219, "outros") -> 773.72 | G19: =SUMIFS('04_Base_Despesas'!$D$4:$D$219, '04_Base_Despesas'!$A$4:$A$219, G$5, '04_Base_Despesas'!$B$4:$B$219, "outros") -> 770.82 | H19: =SUMIFS('04_Base_Despesas'!$D$4:$D$219, '04_Base_Despesas'!$A$4:$A$219, H$5, '04_Base_Despesas'!$B$4:$B$219, "outros") -> 984.56 | I19: =SUMIFS('04_Base_Despesas'!$D$4:$D$219, '04_Base_Despesas'!$A$4:$A$219, I$5, '04_Base_Despesas'!$B$4:$B$219, "outros") -> 873.81 | ... Y19: =SUMIFS('04_Base_Despesas'!$D$4:$D$219, '04_Base_Despesas'!$A$4:$A$219, Y$5, '04_Base_Despesas'!$B$4:$B$219, "outros") -> 648.47 | Z19: =SUM(B19:Y19) -> 20427.8
A20: Total Despesas Operac. | B20: =B13+B14+B15+B16+B17+B18+B19 -> 98608.23 | C20: =C13+C14+C15+C16+C17+C18+C19 -> 92928.73 | D20: =D13+D14+D15+D16+D17+D18+D19 -> 90397.78 | E20: =E13+E14+E15+E16+E17+E18+E19 -> 94036.22 | F20: =F13+F14+F15+F16+F17+F18+F19 -> 98318.36 | G20: =G13+G14+G15+G16+G17+G18+G19 -> 97207.82 | H20: =H13+H14+H15+H16+H17+H18+H19 -> 93932.6 | I20: =I13+I14+I15+I16+I17+I18+I19 -> 95179.81 | ... Y20: =Y13+Y14+Y15+Y16+Y17+Y18+Y19 -> 87191.94 | Z20: =SUM(B20:Y20) -> 2298567.7
A21: EBITDA | B21: =B11-B20 -> -29797.17 | C21: =C11-C20 -> -37170.33 | D21: =D11-D20 -> -21865.99 | E21: =E11-E20 -> -30014.25 | F21: =F11-F20 -> -7727.97 | G21: =G11-G20 -> -21166.51 | H21: =H11-H20 -> -35000.82 | I21: =I11-I20 -> -36529.78 | ... Y21: =Y11-Y20 -> 1974.42 | Z21: =SUM(B21:Y21) -> -502504.1
A22: % Margem EBITDA | B22: =IFERROR(B21/B9,0) -> -0.19861847 | C22: =IFERROR(C21/C9,0) -> -0.29805054 | D22: =IFERROR(D21/D9,0) -> -0.14375892 | E22: =IFERROR(E21/E9,0) -> -0.21466939 | F22: =IFERROR(F21/F9,0) -> -0.039631581 | G22: =IFERROR(G21/G9,0) -> -0.1247126 | H22: =IFERROR(H21/H9,0) -> -0.27088588 | I22: =IFERROR(I21/I9,0) -> -0.28329801 | ... Y22: =IFERROR(Y21/Y9,0) -> 0.010163005 | Z22: =IFERROR($Z$21/$Z$9,0) -> -0.12641442
A23: (−) Depreciação | B23: =SUMIFS('04_Base_Despesas'!$D$4:$D$219, '04_Base_Despesas'!$A$4:$A$219, B$5, '04_Base_Despesas'!$B$4:$B$219, "depreciacao") -> 2199.99 | C23: =SUMIFS('04_Base_Despesas'!$D$4:$D$219, '04_Base_Despesas'!$A$4:$A$219, C$5, '04_Base_Despesas'!$B$4:$B$219, "depreciacao") -> 2200 | D23: =SUMIFS('04_Base_Despesas'!$D$4:$D$219, '04_Base_Despesas'!$A$4:$A$219, D$5, '04_Base_Despesas'!$B$4:$B$219, "depreciacao") -> 2199.99 | E23: =SUMIFS('04_Base_Despesas'!$D$4:$D$219, '04_Base_Despesas'!$A$4:$A$219, E$5, '04_Base_Despesas'!$B$4:$B$219, "depreciacao") -> 2199.99 | F23: =SUMIFS('04_Base_Despesas'!$D$4:$D$219, '04_Base_Despesas'!$A$4:$A$219, F$5, '04_Base_Despesas'!$B$4:$B$219, "depreciacao") -> 2199.99 | G23: =SUMIFS('04_Base_Despesas'!$D$4:$D$219, '04_Base_Despesas'!$A$4:$A$219, G$5, '04_Base_Despesas'!$B$4:$B$219, "depreciacao") -> 2199.99 | H23: =SUMIFS('04_Base_Despesas'!$D$4:$D$219, '04_Base_Despesas'!$A$4:$A$219, H$5, '04_Base_Despesas'!$B$4:$B$219, "depreciacao") -> 2199.99 | I23: =SUMIFS('04_Base_Despesas'!$D$4:$D$219, '04_Base_Despesas'!$A$4:$A$219, I$5, '04_Base_Despesas'!$B$4:$B$219, "depreciacao") -> 2200 | ... Y23: =SUMIFS('04_Base_Despesas'!$D$4:$D$219, '04_Base_Despesas'!$A$4:$A$219, Y$5, '04_Base_Despesas'!$B$4:$B$219, "depreciacao") -> 2200 | Z23: =SUM(B23:Y23) -> 52799.91
A24: EBIT | B24: =B21-B23 -> -31997.16 | C24: =C21-C23 -> -39370.33 | D24: =D21-D23 -> -24065.98 | E24: =E21-E23 -> -32214.24 | F24: =F21-F23 -> -9927.96 | G24: =G21-G23 -> -23366.5 | H24: =H21-H23 -> -37200.81 | I24: =I21-I23 -> -38729.78 | ... Y24: =Y21-Y23 -> -225.58 | Z24: =SUM(B24:Y24) -> -555304.01
A25: (−) Despesas Financeiras | B25: =SUMIFS('04_Base_Despesas'!$D$4:$D$219, '04_Base_Despesas'!$A$4:$A$219, B$5, '04_Base_Despesas'!$B$4:$B$219, "financeiro") -> 1365.44 | C25: =SUMIFS('04_Base_Despesas'!$D$4:$D$219, '04_Base_Despesas'!$A$4:$A$219, C$5, '04_Base_Despesas'!$B$4:$B$219, "financeiro") -> 1351.57 | D25: =SUMIFS('04_Base_Despesas'!$D$4:$D$219, '04_Base_Despesas'!$A$4:$A$219, D$5, '04_Base_Despesas'!$B$4:$B$219, "financeiro") -> 1345.81 | E25: =SUMIFS('04_Base_Despesas'!$D$4:$D$219, '04_Base_Despesas'!$A$4:$A$219, E$5, '04_Base_Despesas'!$B$4:$B$219, "financeiro") -> 1298.1 | F25: =SUMIFS('04_Base_Despesas'!$D$4:$D$219, '04_Base_Despesas'!$A$4:$A$219, F$5, '04_Base_Despesas'!$B$4:$B$219, "financeiro") -> 1353.03 | G25: =SUMIFS('04_Base_Despesas'!$D$4:$D$219, '04_Base_Despesas'!$A$4:$A$219, G$5, '04_Base_Despesas'!$B$4:$B$219, "financeiro") -> 1278.47 | H25: =SUMIFS('04_Base_Despesas'!$D$4:$D$219, '04_Base_Despesas'!$A$4:$A$219, H$5, '04_Base_Despesas'!$B$4:$B$219, "financeiro") -> 5445.99 | I25: =SUMIFS('04_Base_Despesas'!$D$4:$D$219, '04_Base_Despesas'!$A$4:$A$219, I$5, '04_Base_Despesas'!$B$4:$B$219, "financeiro") -> 1313.68 | ... Y25: =SUMIFS('04_Base_Despesas'!$D$4:$D$219, '04_Base_Despesas'!$A$4:$A$219, Y$5, '04_Base_Despesas'!$B$4:$B$219, "financeiro") -> 1383.86 | Z25: =SUM(B25:Y25) -> 35628.56
A26: Resultado Operacional | B26: =B24-B25 -> -33362.6 | C26: =C24-C25 -> -40721.9 | D26: =D24-D25 -> -25411.79 | E26: =E24-E25 -> -33512.34 | F26: =F24-F25 -> -11280.99 | G26: =G24-G25 -> -24644.97 | H26: =H24-H25 -> -42646.8 | I26: =I24-I25 -> -40043.46 | ... Y26: =Y24-Y25 -> -1609.44 | Z26: =SUM(B26:Y26) -> -590932.57
A27: % Margem Operacional | B27: =IFERROR(B26/B9,0) -> -0.22238449 | C27: =IFERROR(C26/C9,0) -> -0.32652883 | D27: =IFERROR(D26/D9,0) -> -0.16707094 | E27: =IFERROR(E26/E9,0) -> -0.2396886 | F27: =IFERROR(F26/F9,0) -> -0.05785264 | G27: =IFERROR(G26/G9,0) -> -0.14520761 | H27: =IFERROR(H26/H9,0) -> -0.33006129 | I27: =IFERROR(I26/I9,0) -> -0.31054752 | ... Y27: =IFERROR(Y26/Y9,0) -> -0.0082843298 | Z27: =IFERROR($Z$26/$Z$9,0) -> -0.14866027

Sheet 07_DRE_por_Canal
A1: 07 — DRE POR CANAL
A2: DREs replicadas por canal. Despesas operacionais e financeiras são rateadas pelo share de receita líquida do canal no mês.
A4: Rateio: as despesas centrais (pessoal, aluguel, marketing, logística, etc.) são distribuídas pelo canal proporcionalmente à sua receita líquida no mês. Linhas de receita, devoluções, comissões, CMV e margem de contribuição são alocação direta por canal.
A6: Canal: E-commerce
A7: Item | B7: 2023-01 | C7: 2023-02 | D7: 2023-03 | E7: 2023-04 | F7: 2023-05 | G7: 2023-06 | H7: 2023-07 | I7: 2023-08 | J7: 2023-09 | K7: 2023-10 | L7: 2023-11 | M7: 2023-12 | N7: 2024-01 | O7: 2024-02 | P7: 2024-03 | Q7: 2024-04 | R7: 2024-05 | S7: 2024-06 | T7: 2024-07 | U7: 2024-08 | V7: 2024-09 | W7: 2024-10 | X7: 2024-11 | Y7: 2024-12 | Z7: Total 24m
A8: Receita Bruta | B8: =SUMIFS('03_Base_Vendas'!$F$4:$F$387, '03_Base_Vendas'!$A$4:$A$387, B$7, '03_Base_Vendas'!$B$4:$B$387, "ecommerce") -> 68636.19 | C8: =SUMIFS('03_Base_Vendas'!$F$4:$F$387, '03_Base_Vendas'!$A$4:$A$387, C$7, '03_Base_Vendas'!$B$4:$B$387, "ecommerce") -> 66148.95 | D8: =SUMIFS('03_Base_Vendas'!$F$4:$F$387, '03_Base_Vendas'!$A$4:$A$387, D$7, '03_Base_Vendas'!$B$4:$B$387, "ecommerce") -> 70357.55 | E8: =SUMIFS('03_Base_Vendas'!$F$4:$F$387, '03_Base_Vendas'!$A$4:$A$387, E$7, '03_Base_Vendas'!$B$4:$B$387, "ecommerce") -> 65336.91 | F8: =SUMIFS('03_Base_Vendas'!$F$4:$F$387, '03_Base_Vendas'!$A$4:$A$387, F$7, '03_Base_Vendas'!$B$4:$B$387, "ecommerce") -> 101416.68 | G8: =SUMIFS('03_Base_Vendas'!$F$4:$F$387, '03_Base_Vendas'!$A$4:$A$387, G$7, '03_Base_Vendas'!$B$4:$B$387, "ecommerce") -> 87766.93 | H8: =SUMIFS('03_Base_Vendas'!$F$4:$F$387, '03_Base_Vendas'!$A$4:$A$387, H$7, '03_Base_Vendas'!$B$4:$B$387, "ecommerce") -> 66646.31 | I8: =SUMIFS('03_Base_Vendas'!$F$4:$F$387, '03_Base_Vendas'!$A$4:$A$387, I$7, '03_Base_Vendas'!$B$4:$B$387, "ecommerce") -> 64204.01 | ... Y8: =SUMIFS('03_Base_Vendas'!$F$4:$F$387, '03_Base_Vendas'!$A$4:$A$387, Y$7, '03_Base_Vendas'!$B$4:$B$387, "ecommerce") -> 105016.31 | Z8: =SUM(B8:Y8) -> 1943188.9
A9: (−) Devoluções | B9: =SUMIFS('03_Base_Vendas'!$G$4:$G$387, '03_Base_Vendas'!$A$4:$A$387, B$7, '03_Base_Vendas'!$B$4:$B$387, "ecommerce") -> 1942.53 | C9: =SUMIFS('03_Base_Vendas'!$G$4:$G$387, '03_Base_Vendas'!$A$4:$A$387, C$7, '03_Base_Vendas'!$B$4:$B$387, "ecommerce") -> 3660.31 | D9: =SUMIFS('03_Base_Vendas'!$G$4:$G$387, '03_Base_Vendas'!$A$4:$A$387, D$7, '03_Base_Vendas'!$B$4:$B$387, "ecommerce") -> 2128.42 | E9: =SUMIFS('03_Base_Vendas'!$G$4:$G$387, '03_Base_Vendas'!$A$4:$A$387, E$7, '03_Base_Vendas'!$B$4:$B$387, "ecommerce") -> 2640.31 | F9: =SUMIFS('03_Base_Vendas'!$G$4:$G$387, '03_Base_Vendas'!$A$4:$A$387, F$7, '03_Base_Vendas'!$B$4:$B$387, "ecommerce") -> 2478.76 | G9: =SUMIFS('03_Base_Vendas'!$G$4:$G$387, '03_Base_Vendas'!$A$4:$A$387, G$7, '03_Base_Vendas'!$B$4:$B$387, "ecommerce") -> 3237.31 | H9: =SUMIFS('03_Base_Vendas'!$G$4:$G$387, '03_Base_Vendas'!$A$4:$A$387, H$7, '03_Base_Vendas'!$B$4:$B$387, "ecommerce") -> 790.33 | I9: =SUMIFS('03_Base_Vendas'!$G$4:$G$387, '03_Base_Vendas'!$A$4:$A$387, I$7, '03_Base_Vendas'!$B$4:$B$387, "ecommerce") -> 2014.64 | ... Y9: =SUMIFS('03_Base_Vendas'!$G$4:$G$387, '03_Base_Vendas'!$A$4:$A$387, Y$7, '03_Base_Vendas'!$B$4:$B$387, "ecommerce") -> 1827.61 | Z9: =SUM(B9:Y9) -> 57894.53
A10: (−) Comissões de canal | B10: =SUMIFS('03_Base_Vendas'!$H$4:$H$387, '03_Base_Vendas'!$A$4:$A$387, B$7, '03_Base_Vendas'!$B$4:$B$387, "ecommerce") -> 2806.55 | C10: =SUMIFS('03_Base_Vendas'!$H$4:$H$387, '03_Base_Vendas'!$A$4:$A$387, C$7, '03_Base_Vendas'!$B$4:$B$387, "ecommerce") -> 2615.42 | D10: =SUMIFS('03_Base_Vendas'!$H$4:$H$387, '03_Base_Vendas'!$A$4:$A$387, D$7, '03_Base_Vendas'!$B$4:$B$387, "ecommerce") -> 2846.6 | E10: =SUMIFS('03_Base_Vendas'!$H$4:$H$387, '03_Base_Vendas'!$A$4:$A$387, E$7, '03_Base_Vendas'!$B$4:$B$387, "ecommerce") -> 2656.28 | F10: =SUMIFS('03_Base_Vendas'!$H$4:$H$387, '03_Base_Vendas'!$A$4:$A$387, F$7, '03_Base_Vendas'!$B$4:$B$387, "ecommerce") -> 3975.57 | G10: =SUMIFS('03_Base_Vendas'!$H$4:$H$387, '03_Base_Vendas'!$A$4:$A$387, G$7, '03_Base_Vendas'!$B$4:$B$387, "ecommerce") -> 3480.01 | H10: =SUMIFS('03_Base_Vendas'!$H$4:$H$387, '03_Base_Vendas'!$A$4:$A$387, H$7, '03_Base_Vendas'!$B$4:$B$387, "ecommerce") -> 2639.68 | I10: =SUMIFS('03_Base_Vendas'!$H$4:$H$387, '03_Base_Vendas'!$A$4:$A$387, I$7, '03_Base_Vendas'!$B$4:$B$387, "ecommerce") -> 2523.04 | ... Y10: =SUMIFS('03_Base_Vendas'!$H$4:$H$387, '03_Base_Vendas'!$A$4:$A$387, Y$7, '03_Base_Vendas'!$B$4:$B$387, "ecommerce") -> 4244.96 | Z10: =SUM(B10:Y10) -> 77414.93
A11: Receita Líquida | B11: =B8-B9-B10 -> 63887.11 | C11: =C8-C9-C10 -> 59873.22 | D11: =D8-D9-D10 -> 65382.53 | E11: =E8-E9-E10 -> 60040.32 | F11: =F8-F9-F10 -> 94962.35 | G11: =G8-G9-G10 -> 81049.61 | H11: =H8-H9-H10 -> 63216.3 | I11: =I8-I9-I10 -> 59666.33 | ... Y11: =Y8-Y9-Y10 -> 98943.74 | Z11: =SUM(B11:Y11) -> 1807879.5
A12: (−) CMV | B12: =SUMIFS('03_Base_Vendas'!$J$4:$J$387, '03_Base_Vendas'!$A$4:$A$387, B$7, '03_Base_Vendas'!$B$4:$B$387, "ecommerce") -> 32724.81 | C12: =SUMIFS('03_Base_Vendas'!$J$4:$J$387, '03_Base_Vendas'!$A$4:$A$387, C$7, '03_Base_Vendas'!$B$4:$B$387, "ecommerce") -> 31609.47 | D12: =SUMIFS('03_Base_Vendas'!$J$4:$J$387, '03_Base_Vendas'!$A$4:$A$387, D$7, '03_Base_Vendas'!$B$4:$B$387, "ecommerce") -> 34083.99 | E12: =SUMIFS('03_Base_Vendas'!$J$4:$J$387, '03_Base_Vendas'!$A$4:$A$387, E$7, '03_Base_Vendas'!$B$4:$B$387, "ecommerce") -> 30620.35 | F12: =SUMIFS('03_Base_Vendas'!$J$4:$J$387, '03_Base_Vendas'!$A$4:$A$387, F$7, '03_Base_Vendas'!$B$4:$B$387, "ecommerce") -> 48888.53 | G12: =SUMIFS('03_Base_Vendas'!$J$4:$J$387, '03_Base_Vendas'!$A$4:$A$387, G$7, '03_Base_Vendas'!$B$4:$B$387, "ecommerce") -> 43155.15 | H12: =SUMIFS('03_Base_Vendas'!$J$4:$J$387, '03_Base_Vendas'!$A$4:$A$387, H$7, '03_Base_Vendas'!$B$4:$B$387, "ecommerce") -> 32083.03 | I12: =SUMIFS('03_Base_Vendas'!$J$4:$J$387, '03_Base_Vendas'!$A$4:$A$387, I$7, '03_Base_Vendas'!$B$4:$B$387, "ecommerce") -> 30738 | ... Y12: =SUMIFS('03_Base_Vendas'!$J$4:$J$387, '03_Base_Vendas'!$A$4:$A$387, Y$7, '03_Base_Vendas'!$B$4:$B$387, "ecommerce") -> 50354.61 | Z12: =SUM(B12:Y12) -> 931100.49
A13: Margem de Contribuição | B13: =B11-B12 -> 31162.3 | C13: =C11-C12 -> 28263.75 | D13: =D11-D12 -> 31298.54 | E13: =E11-E12 -> 29419.97 | F13: =F11-F12 -> 46073.82 | G13: =G11-G12 -> 37894.46 | H13: =H11-H12 -> 31133.27 | I13: =I11-I12 -> 28928.33 | ... Y13: =Y11-Y12 -> 48589.13 | Z13: =SUM(B13:Y13) -> 876778.97
A14: % Margem de Contribuição | B14: =IFERROR(B13/B11,0) -> 0.48777132 | C14: =IFERROR(C13/C11,0) -> 0.47205996 | D14: =IFERROR(D13/D11,0) -> 0.47869882 | E14: =IFERROR(E13/E11,0) -> 0.49000355 | F14: =IFERROR(F13/F11,0) -> 0.48517986 | G14: =IFERROR(G13/G11,0) -> 0.46754648 | H14: =IFERROR(H13/H11,0) -> 0.49248801 | I14: =IFERROR(I13/I11,0) -> 0.48483508 | ... Y14: =IFERROR(Y13/Y11,0) -> 0.49107836 | Z14: =IFERROR($Z$13/$Z$11,0) -> 0.48497645
A15: (−) Pessoal | B15: =(SUMIFS('04_Base_Despesas'!$D$4:$D$219, '04_Base_Despesas'!$A$4:$A$219, B$7, '04_Base_Despesas'!$B$4:$B$219, "pessoal"))*(IFERROR(SUMIFS('03_Base_Vendas'!$I$4:$I$387, '03_Base_Vendas'!$A$4:$A$387, B$7, '03_Base_Vendas'!$B$4:$B$387, "ecommerce")/SUMIFS('03_Base_Vendas'!$I$4:$I$387, '03_Base_Vendas'!$A$4:$A$387, B$7),0)) -> 21570.346 | C15: =(SUMIFS('04_Base_Despesas'!$D$4:$D$219, '04_Base_Despesas'!$A$4:$A$219, C$7, '04_Base_Despesas'!$B$4:$B$219, "pessoal"))*(IFERROR(SUMIFS('03_Base_Vendas'!$I$4:$I$387, '03_Base_Vendas'!$A$4:$A$387, C$7, '03_Base_Vendas'!$B$4:$B$387, "ecommerce")/SUMIFS('03_Base_Vendas'!$I$4:$I$387, '03_Base_Vendas'!$A$4:$A$387, C$7),0)) -> 25024.468 | D15: =(SUMIFS('04_Base_Despesas'!$D$4:$D$219, '04_Base_Despesas'!$A$4:$A$219, D$7, '04_Base_Despesas'!$B$4:$B$219, "pessoal"))*(IFERROR(SUMIFS('03_Base_Vendas'!$I$4:$I$387, '03_Base_Vendas'!$A$4:$A$387, D$7, '03_Base_Vendas'!$B$4:$B$387, "ecommerce")/SUMIFS('03_Base_Vendas'!$I$4:$I$387, '03_Base_Vendas'!$A$4:$A$387, D$7),0)) -> 21546.642 | E15: =(SUMIFS('04_Base_Despesas'!$D$4:$D$219, '04_Base_Despesas'!$A$4:$A$219, E$7, '04_Base_Despesas'!$B$4:$B$219, "pessoal"))*(IFERROR(SUMIFS('03_Base_Vendas'!$I$4:$I$387, '03_Base_Vendas'!$A$4:$A$387, E$7, '03_Base_Vendas'!$B$4:$B$387, "ecommerce")/SUMIFS('03_Base_Vendas'!$I$4:$I$387, '03_Base_Vendas'!$A$4:$A$387, E$7),0)) -> 21244.787 | F15: =(SUMIFS('04_Base_Despesas'!$D$4:$D$219, '04_Base_Despesas'!$A$4:$A$219, F$7, '04_Base_Despesas'!$B$4:$B$219, "pessoal"))*(IFERROR(SUMIFS('03_Base_Vendas'!$I$4:$I$387, '03_Base_Vendas'!$A$4:$A$387, F$7, '03_Base_Vendas'!$B$4:$B$387, "ecommerce")/SUMIFS('03_Base_Vendas'!$I$4:$I$387, '03_Base_Vendas'!$A$4:$A$387, F$7),0)) -> 25316.547 | G15: =(SUMIFS('04_Base_Despesas'!$D$4:$D$219, '04_Base_Despesas'!$A$4:$A$219, G$7, '04_Base_Despesas'!$B$4:$B$219, "pessoal"))*(IFERROR(SUMIFS('03_Base_Vendas'!$I$4:$I$387, '03_Base_Vendas'!$A$4:$A$387, G$7, '03_Base_Vendas'!$B$4:$B$387, "ecommerce")/SUMIFS('03_Base_Vendas'!$I$4:$I$387, '03_Base_Vendas'!$A$4:$A$387, G$7),0)) -> 24155.46 | H15: =(SUMIFS('04_Base_Despesas'!$D$4:$D$219, '04_Base_Despesas'!$A$4:$A$219, H$7, '04_Base_Despesas'!$B$4:$B$219, "pessoal"))*(IFERROR(SUMIFS('03_Base_Vendas'!$I$4:$I$387, '03_Base_Vendas'!$A$4:$A$387, H$7, '03_Base_Vendas'!$B$4:$B$387, "ecommerce")/SUMIFS('03_Base_Vendas'!$I$4:$I$387, '03_Base_Vendas'!$A$4:$A$387, H$7),0)) -> 25384.126 | I15: =(SUMIFS('04_Base_Despesas'!$D$4:$D$219, '04_Base_Despesas'!$A$4:$A$219, I$7, '04_Base_Despesas'!$B$4:$B$219, "pessoal"))*(IFERROR(SUMIFS('03_Base_Vendas'!$I$4:$I$387, '03_Base_Vendas'!$A$4:$A$387, I$7, '03_Base_Vendas'!$B$4:$B$387, "ecommerce")/SUMIFS('03_Base_Vendas'!$I$4:$I$387, '03_Base_Vendas'!$A$4:$A$387, I$7),0)) -> 24017.666 | ... Y15: =(SUMIFS('04_Base_Despesas'!$D$4:$D$219, '04_Base_Despesas'!$A$4:$A$219, Y$7, '04_Base_Despesas'!$B$4:$B$219, "pessoal"))*(IFERROR(SUMIFS('03_Base_Vendas'!$I$4:$I$387, '03_Base_Vendas'!$A$4:$A$387, Y$7, '03_Base_Vendas'!$B$4:$B$387, "ecommerce")/SUMIFS('03_Base_Vendas'!$I$4:$I$387, '03_Base_Vendas'!$A$4:$A$387, Y$7),0)) -> 26029.811 | Z15: =SUM(B15:Y15) -> 561117.29
A16: (−) Aluguel | B16: =(SUMIFS('04_Base_Despesas'!$D$4:$D$219, '04_Base_Despesas'!$A$4:$A$219, B$7, '04_Base_Despesas'!$B$4:$B$219, "aluguel"))*(IFERROR(SUMIFS('03_Base_Vendas'!$I$4:$I$387, '03_Base_Vendas'!$A$4:$A$387, B$7, '03_Base_Vendas'!$B$4:$B$387, "ecommerce")/SUMIFS('03_Base_Vendas'!$I$4:$I$387, '03_Base_Vendas'!$A$4:$A$387, B$7),0)) -> 4045.5905 | C16: =(SUMIFS('04_Base_Despesas'!$D$4:$D$219, '04_Base_Despesas'!$A$4:$A$219, C$7, '04_Base_Despesas'!$B$4:$B$219, "aluguel"))*(IFERROR(SUMIFS('03_Base_Vendas'!$I$4:$I$387, '03_Base_Vendas'!$A$4:$A$387, C$7, '03_Base_Vendas'!$B$4:$B$387, "ecommerce")/SUMIFS('03_Base_Vendas'!$I$4:$I$387, '03_Base_Vendas'!$A$4:$A$387, C$7),0)) -> 4560.8913 | D16: =(SUMIFS('04_Base_Despesas'!$D$4:$D$219, '04_Base_Despesas'!$A$4:$A$219, D$7, '04_Base_Despesas'!$B$4:$B$219, "aluguel"))*(IFERROR(SUMIFS('03_Base_Vendas'!$I$4:$I$387, '03_Base_Vendas'!$A$4:$A$387, D$7, '03_Base_Vendas'!$B$4:$B$387, "ecommerce")/SUMIFS('03_Base_Vendas'!$I$4:$I$387, '03_Base_Vendas'!$A$4:$A$387, D$7),0)) -> 4083.6731 | E16: =(SUMIFS('04_Base_Despesas'!$D$4:$D$219, '04_Base_Despesas'!$A$4:$A$219, E$7, '04_Base_Despesas'!$B$4:$B$219, "aluguel"))*(IFERROR(SUMIFS('03_Base_Vendas'!$I$4:$I$387, '03_Base_Vendas'!$A$4:$A$387, E$7, '03_Base_Vendas'!$B$4:$B$387, "ecommerce")/SUMIFS('03_Base_Vendas'!$I$4:$I$387, '03_Base_Vendas'!$A$4:$A$387, E$7),0)) -> 4079.5216 | F16: =(SUMIFS('04_Base_Despesas'!$D$4:$D$219, '04_Base_Despesas'!$A$4:$A$219, F$7, '04_Base_Despesas'!$B$4:$B$219, "aluguel"))*(IFERROR(SUMIFS('03_Base_Vendas'!$I$4:$I$387, '03_Base_Vendas'!$A$4:$A$387, F$7, '03_Base_Vendas'!$B$4:$B$387, "ecommerce")/SUMIFS('03_Base_Vendas'!$I$4:$I$387, '03_Base_Vendas'!$A$4:$A$387, F$7),0)) -> 4626.4836 | G16: =(SUMIFS('04_Base_Despesas'!$D$4:$D$219, '04_Base_Despesas'!$A$4:$A$219, G$7, '04_Base_Despesas'!$B$4:$B$219, "aluguel"))*(IFERROR(SUMIFS('03_Base_Vendas'!$I$4:$I$387, '03_Base_Vendas'!$A$4:$A$387, G$7, '03_Base_Vendas'!$B$4:$B$387, "ecommerce")/SUMIFS('03_Base_Vendas'!$I$4:$I$387, '03_Base_Vendas'!$A$4:$A$387, G$7),0)) -> 4536.6537 | H16: =(SUMIFS('04_Base_Despesas'!$D$4:$D$219, '04_Base_Despesas'!$A$4:$A$219, H$7, '04_Base_Despesas'!$B$4:$B$219, "aluguel"))*(IFERROR(SUMIFS('03_Base_Vendas'!$I$4:$I$387, '03_Base_Vendas'!$A$4:$A$387, H$7, '03_Base_Vendas'!$B$4:$B$387, "ecommerce")/SUMIFS('03_Base_Vendas'!$I$4:$I$387, '03_Base_Vendas'!$A$4:$A$387, H$7),0)) -> 4647.9433 | I16: =(SUMIFS('04_Base_Despesas'!$D$4:$D$219, '04_Base_Despesas'!$A$4:$A$219, I$7, '04_Base_Despesas'!$B$4:$B$219, "aluguel"))*(IFERROR(SUMIFS('03_Base_Vendas'!$I$4:$I$387, '03_Base_Vendas'!$A$4:$A$387, I$7, '03_Base_Vendas'!$B$4:$B$387, "ecommerce")/SUMIFS('03_Base_Vendas'!$I$4:$I$387, '03_Base_Vendas'!$A$4:$A$387, I$7),0)) -> 4395.9162 | ... Y16: =(SUMIFS('04_Base_Despesas'!$D$4:$D$219, '04_Base_Despesas'!$A$4:$A$219, Y$7, '04_Base_Despesas'!$B$4:$B$219, "aluguel"))*(IFERROR(SUMIFS('03_Base_Vendas'!$I$4:$I$387, '03_Base_Vendas'!$A$4:$A$387, Y$7, '03_Base_Vendas'!$B$4:$B$387, "ecommerce")/SUMIFS('03_Base_Vendas'!$I$4:$I$387, '03_Base_Vendas'!$A$4:$A$387, Y$7),0)) -> 4838.3243 | Z16: =SUM(B16:Y16) -> 103774.22
A17: (−) Marketing | B17: =(SUMIFS('04_Base_Despesas'!$D$4:$D$219, '04_Base_Despesas'!$A$4:$A$219, B$7, '04_Base_Despesas'!$B$4:$B$219, "marketing"))*(IFERROR(SUMIFS('03_Base_Vendas'!$I$4:$I$387, '03_Base_Vendas'!$A$4:$A$387, B$7, '03_Base_Vendas'!$B$4:$B$387, "ecommerce")/SUMIFS('03_Base_Vendas'!$I$4:$I$387, '03_Base_Vendas'!$A$4:$A$387, B$7),0)) -> 7599.9063 | C17: =(SUMIFS('04_Base_Despesas'!$D$4:$D$219, '04_Base_Despesas'!$A$4:$A$219, C$7, '04_Base_Despesas'!$B$4:$B$219, "marketing"))*(IFERROR(SUMIFS('03_Base_Vendas'!$I$4:$I$387, '03_Base_Vendas'!$A$4:$A$387, C$7, '03_Base_Vendas'!$B$4:$B$387, "ecommerce")/SUMIFS('03_Base_Vendas'!$I$4:$I$387, '03_Base_Vendas'!$A$4:$A$387, C$7),0)) -> 5832.2901 | D17: =(SUMIFS('04_Base_Despesas'!$D$4:$D$219, '04_Base_Despesas'!$A$4:$A$219, D$7, '04_Base_Despesas'!$B$4:$B$219, "marketing"))*(IFERROR(SUMIFS('03_Base_Vendas'!$I$4:$I$387, '03_Base_Vendas'!$A$4:$A$387, D$7, '03_Base_Vendas'!$B$4:$B$387, "ecommerce")/SUMIFS('03_Base_Vendas'!$I$4:$I$387, '03_Base_Vendas'!$A$4:$A$387, D$7),0)) -> 4724.6293 | E17: =(SUMIFS('04_Base_Despesas'!$D$4:$D$219, '04_Base_Despesas'!$A$4:$A$219, E$7, '04_Base_Despesas'!$B$4:$B$219, "marketing"))*(IFERROR(SUMIFS('03_Base_Vendas'!$I$4:$I$387, '03_Base_Vendas'!$A$4:$A$387, E$7, '03_Base_Vendas'!$B$4:$B$387, "ecommerce")/SUMIFS('03_Base_Vendas'!$I$4:$I$387, '03_Base_Vendas'!$A$4:$A$387, E$7),0)) -> 5312.2628 | F17: =(SUMIFS('04_Base_Despesas'!$D$4:$D$219, '04_Base_Despesas'!$A$4:$A$219, F$7, '04_Base_Despesas'!$B$4:$B$219, "marketing"))*(IFERROR(SUMIFS('03_Base_Vendas'!$I$4:$I$387, '03_Base_Vendas'!$A$4:$A$387, F$7, '03_Base_Vendas'!$B$4:$B$387, "ecommerce")/SUMIFS('03_Base_Vendas'!$I$4:$I$387, '03_Base_Vendas'!$A$4:$A$387, F$7),0)) -> 8328.9074 | G17: =(SUMIFS('04_Base_Despesas'!$D$4:$D$219, '04_Base_Despesas'!$A$4:$A$219, G$7, '04_Base_Despesas'!$B$4:$B$219, "marketing"))*(IFERROR(SUMIFS('03_Base_Vendas'!$I$4:$I$387, '03_Base_Vendas'!$A$4:$A$387, G$7, '03_Base_Vendas'!$B$4:$B$387, "ecommerce")/SUMIFS('03_Base_Vendas'!$I$4:$I$387, '03_Base_Vendas'!$A$4:$A$387, G$7),0)) -> 8465.773 | H17: =(SUMIFS('04_Base_Despesas'!$D$4:$D$219, '04_Base_Despesas'!$A$4:$A$219, H$7, '04_Base_Despesas'!$B$4:$B$219, "marketing"))*(IFERROR(SUMIFS('03_Base_Vendas'!$I$4:$I$387, '03_Base_Vendas'!$A$4:$A$387, H$7, '03_Base_Vendas'!$B$4:$B$387, "ecommerce")/SUMIFS('03_Base_Vendas'!$I$4:$I$387, '03_Base_Vendas'!$A$4:$A$387, H$7),0)) -> 4867.3702 | I17: =(SUMIFS('04_Base_Despesas'!$D$4:$D$219, '04_Base_Despesas'!$A$4:$A$219, I$7, '04_Base_Despesas'!$B$4:$B$219, "marketing"))*(IFERROR(SUMIFS('03_Base_Vendas'!$I$4:$I$387, '03_Base_Vendas'!$A$4:$A$387, I$7, '03_Base_Vendas'!$B$4:$B$387, "ecommerce")/SUMIFS('03_Base_Vendas'!$I$4:$I$387, '03_Base_Vendas'!$A$4:$A$387, I$7),0)) -> 5945.8051 | ... Y17: =(SUMIFS('04_Base_Despesas'!$D$4:$D$219, '04_Base_Despesas'!$A$4:$A$219, Y$7, '04_Base_Despesas'!$B$4:$B$219, "marketing"))*(IFERROR(SUMIFS('03_Base_Vendas'!$I$4:$I$387, '03_Base_Vendas'!$A$4:$A$387, Y$7, '03_Base_Vendas'!$B$4:$B$387, "ecommerce")/SUMIFS('03_Base_Vendas'!$I$4:$I$387, '03_Base_Vendas'!$A$4:$A$387, Y$7),0)) -> 7196.8572 | Z17: =SUM(B17:Y17) -> 159187.75
A18: (−) Logística | B18: =(SUMIFS('04_Base_Despesas'!$D$4:$D$219, '04_Base_Despesas'!$A$4:$A$219, B$7, '04_Base_Despesas'!$B$4:$B$219, "logistica"))*(IFERROR(SUMIFS('03_Base_Vendas'!$I$4:$I$387, '03_Base_Vendas'!$A$4:$A$387, B$7, '03_Base_Vendas'!$B$4:$B$387, "ecommerce")/SUMIFS('03_Base_Vendas'!$I$4:$I$387, '03_Base_Vendas'!$A$4:$A$387, B$7),0)) -> 3830.0842 | C18: =(SUMIFS('04_Base_Despesas'!$D$4:$D$219, '04_Base_Despesas'!$A$4:$A$219, C$7, '04_Base_Despesas'!$B$4:$B$219, "logistica"))*(IFERROR(SUMIFS('03_Base_Vendas'!$I$4:$I$387, '03_Base_Vendas'!$A$4:$A$387, C$7, '03_Base_Vendas'!$B$4:$B$387, "ecommerce")/SUMIFS('03_Base_Vendas'!$I$4:$I$387, '03_Base_Vendas'!$A$4:$A$387, C$7),0)) -> 4397.9378 | D18: =(SUMIFS('04_Base_Despesas'!$D$4:$D$219, '04_Base_Despesas'!$A$4:$A$219, D$7, '04_Base_Despesas'!$B$4:$B$219, "logistica"))*(IFERROR(SUMIFS('03_Base_Vendas'!$I$4:$I$387, '03_Base_Vendas'!$A$4:$A$387, D$7, '03_Base_Vendas'!$B$4:$B$387, "ecommerce")/SUMIFS('03_Base_Vendas'!$I$4:$I$387, '03_Base_Vendas'!$A$4:$A$387, D$7),0)) -> 4197.1864 | E18: =(SUMIFS('04_Base_Despesas'!$D$4:$D$219, '04_Base_Despesas'!$A$4:$A$219, E$7, '04_Base_Despesas'!$B$4:$B$219, "logistica"))*(IFERROR(SUMIFS('03_Base_Vendas'!$I$4:$I$387, '03_Base_Vendas'!$A$4:$A$387, E$7, '03_Base_Vendas'!$B$4:$B$387, "ecommerce")/SUMIFS('03_Base_Vendas'!$I$4:$I$387, '03_Base_Vendas'!$A$4:$A$387, E$7),0)) -> 4662.73 | F18: =(SUMIFS('04_Base_Despesas'!$D$4:$D$219, '04_Base_Despesas'!$A$4:$A$219, F$7, '04_Base_Despesas'!$B$4:$B$219, "logistica"))*(IFERROR(SUMIFS('03_Base_Vendas'!$I$4:$I$387, '03_Base_Vendas'!$A$4:$A$387, F$7, '03_Base_Vendas'!$B$4:$B$387, "ecommerce")/SUMIFS('03_Base_Vendas'!$I$4:$I$387, '03_Base_Vendas'!$A$4:$A$387, F$7),0)) -> 4805.173 | G18: =(SUMIFS('04_Base_Despesas'!$D$4:$D$219, '04_Base_Despesas'!$A$4:$A$219, G$7, '04_Base_Despesas'!$B$4:$B$219, "logistica"))*(IFERROR(SUMIFS('03_Base_Vendas'!$I$4:$I$387, '03_Base_Vendas'!$A$4:$A$387, G$7, '03_Base_Vendas'!$B$4:$B$387, "ecommerce")/SUMIFS('03_Base_Vendas'!$I$4:$I$387, '03_Base_Vendas'!$A$4:$A$387, G$7),0)) -> 4501.2821 | H18: =(SUMIFS('04_Base_Despesas'!$D$4:$D$219, '04_Base_Despesas'!$A$4:$A$219, H$7, '04_Base_Despesas'!$B$4:$B$219, "logistica"))*(IFERROR(SUMIFS('03_Base_Vendas'!$I$4:$I$387, '03_Base_Vendas'!$A$4:$A$387, H$7, '03_Base_Vendas'!$B$4:$B$387, "ecommerce")/SUMIFS('03_Base_Vendas'!$I$4:$I$387, '03_Base_Vendas'!$A$4:$A$387, H$7),0)) -> 5254.3874 | I18: =(SUMIFS('04_Base_Despesas'!$D$4:$D$219, '04_Base_Despesas'!$A$4:$A$219, I$7, '04_Base_Despesas'!$B$4:$B$219, "logistica"))*(IFERROR(SUMIFS('03_Base_Vendas'!$I$4:$I$387, '03_Base_Vendas'!$A$4:$A$387, I$7, '03_Base_Vendas'!$B$4:$B$387, "ecommerce")/SUMIFS('03_Base_Vendas'!$I$4:$I$387, '03_Base_Vendas'!$A$4:$A$387, I$7),0)) -> 4977.6995 | ... Y18: =(SUMIFS('04_Base_Despesas'!$D$4:$D$219, '04_Base_Despesas'!$A$4:$A$219, Y$7, '04_Base_Despesas'!$B$4:$B$219, "logistica"))*(IFERROR(SUMIFS('03_Base_Vendas'!$I$4:$I$387, '03_Base_Vendas'!$A$4:$A$387, Y$7, '03_Base_Vendas'!$B$4:$B$387, "ecommerce")/SUMIFS('03_Base_Vendas'!$I$4:$I$387, '03_Base_Vendas'!$A$4:$A$387, Y$7),0)) -> 4738.0743 | Z18: =SUM(B18:Y18) -> 108665.01
A19: (−) Tecnologia | B19: =(SUMIFS('04_Base_Despesas'!$D$4:$D$219, '04_Base_Despesas'!$A$4:$A$219, B$7, '04_Base_Despesas'!$B$4:$B$219, "tecnologia"))*(IFERROR(SUMIFS('03_Base_Vendas'!$I$4:$I$387, '03_Base_Vendas'!$A$4:$A$387, B$7, '03_Base_Vendas'!$B$4:$B$387, "ecommerce")/SUMIFS('03_Base_Vendas'!$I$4:$I$387, '03_Base_Vendas'!$A$4:$A$387, B$7),0)) -> 2859.612 | C19: =(SUMIFS('04_Base_Despesas'!$D$4:$D$219, '04_Base_Despesas'!$A$4:$A$219, C$7, '04_Base_Despesas'!$B$4:$B$219, "tecnologia"))*(IFERROR(SUMIFS('03_Base_Vendas'!$I$4:$I$387, '03_Base_Vendas'!$A$4:$A$387, C$7, '03_Base_Vendas'!$B$4:$B$387, "ecommerce")/SUMIFS('03_Base_Vendas'!$I$4:$I$387, '03_Base_Vendas'!$A$4:$A$387, C$7),0)) -> 3176.8432 | D19: =(SUMIFS('04_Base_Despesas'!$D$4:$D$219, '04_Base_Despesas'!$A$4:$A$219, D$7, '04_Base_Despesas'!$B$4:$B$219, "tecnologia"))*(IFERROR(SUMIFS('03_Base_Vendas'!$I$4:$I$387, '03_Base_Vendas'!$A$4:$A$387, D$7, '03_Base_Vendas'!$B$4:$B$387, "ecommerce")/SUMIFS('03_Base_Vendas'!$I$4:$I$387, '03_Base_Vendas'!$A$4:$A$387, D$7),0)) -> 2859.8909 | E19: =(SUMIFS('04_Base_Despesas'!$D$4:$D$219, '04_Base_Despesas'!$A$4:$A$219, E$7, '04_Base_Despesas'!$B$4:$B$219, "tecnologia"))*(IFERROR(SUMIFS('03_Base_Vendas'!$I$4:$I$387, '03_Base_Vendas'!$A$4:$A$387, E$7, '03_Base_Vendas'!$B$4:$B$387, "ecommerce")/SUMIFS('03_Base_Vendas'!$I$4:$I$387, '03_Base_Vendas'!$A$4:$A$387, E$7),0)) -> 2829.3629 | F19: =(SUMIFS('04_Base_Despesas'!$D$4:$D$219, '04_Base_Despesas'!$A$4:$A$219, F$7, '04_Base_Despesas'!$B$4:$B$219, "tecnologia"))*(IFERROR(SUMIFS('03_Base_Vendas'!$I$4:$I$387, '03_Base_Vendas'!$A$4:$A$387, F$7, '03_Base_Vendas'!$B$4:$B$387, "ecommerce")/SUMIFS('03_Base_Vendas'!$I$4:$I$387, '03_Base_Vendas'!$A$4:$A$387, F$7),0)) -> 3209.4647 | G19: =(SUMIFS('04_Base_Despesas'!$D$4:$D$219, '04_Base_Despesas'!$A$4:$A$219, G$7, '04_Base_Despesas'!$B$4:$B$219, "tecnologia"))*(IFERROR(SUMIFS('03_Base_Vendas'!$I$4:$I$387, '03_Base_Vendas'!$A$4:$A$387, G$7, '03_Base_Vendas'!$B$4:$B$387, "ecommerce")/SUMIFS('03_Base_Vendas'!$I$4:$I$387, '03_Base_Vendas'!$A$4:$A$387, G$7),0)) -> 3199.74 | H19: =(SUMIFS('04_Base_Despesas'!$D$4:$D$219, '04_Base_Despesas'!$A$4:$A$219, H$7, '04_Base_Despesas'!$B$4:$B$219, "tecnologia"))*(IFERROR(SUMIFS('03_Base_Vendas'!$I$4:$I$387, '03_Base_Vendas'!$A$4:$A$387, H$7, '03_Base_Vendas'!$B$4:$B$387, "ecommerce")/SUMIFS('03_Base_Vendas'!$I$4:$I$387, '03_Base_Vendas'!$A$4:$A$387, H$7),0)) -> 3240.9815 | I19: =(SUMIFS('04_Base_Despesas'!$D$4:$D$219, '04_Base_Despesas'!$A$4:$A$219, I$7, '04_Base_Despesas'!$B$4:$B$219, "tecnologia"))*(IFERROR(SUMIFS('03_Base_Vendas'!$I$4:$I$387, '03_Base_Vendas'!$A$4:$A$387, I$7, '03_Base_Vendas'!$B$4:$B$387, "ecommerce")/SUMIFS('03_Base_Vendas'!$I$4:$I$387, '03_Base_Vendas'!$A$4:$A$387, I$7),0)) -> 3144.1212 | ... Y19: =(SUMIFS('04_Base_Despesas'!$D$4:$D$219, '04_Base_Despesas'!$A$4:$A$219, Y$7, '04_Base_Despesas'!$B$4:$B$219, "tecnologia"))*(IFERROR(SUMIFS('03_Base_Vendas'!$I$4:$I$387, '03_Base_Vendas'!$A$4:$A$387, Y$7, '03_Base_Vendas'!$B$4:$B$387, "ecommerce")/SUMIFS('03_Base_Vendas'!$I$4:$I$387, '03_Base_Vendas'!$A$4:$A$387, Y$7),0)) -> 0 | Z19: =SUM(B19:Y19) -> 69563.101
A20: (−) Administrativo | B20: =(SUMIFS('04_Base_Despesas'!$D$4:$D$219, '04_Base_Despesas'!$A$4:$A$219, B$7, '04_Base_Despesas'!$B$4:$B$219, "administrativo"))*(IFERROR(SUMIFS('03_Base_Vendas'!$I$4:$I$387, '03_Base_Vendas'!$A$4:$A$387, B$7, '03_Base_Vendas'!$B$4:$B$387, "ecommerce")/SUMIFS('03_Base_Vendas'!$I$4:$I$387, '03_Base_Vendas'!$A$4:$A$387, B$7),0)) -> 1749.8608 | C20: =(SUMIFS('04_Base_Despesas'!$D$4:$D$219, '04_Base_Despesas'!$A$4:$A$219, C$7, '04_Base_Despesas'!$B$4:$B$219, "administrativo"))*(IFERROR(SUMIFS('03_Base_Vendas'!$I$4:$I$387, '03_Base_Vendas'!$A$4:$A$387, C$7, '03_Base_Vendas'!$B$4:$B$387, "ecommerce")/SUMIFS('03_Base_Vendas'!$I$4:$I$387, '03_Base_Vendas'!$A$4:$A$387, C$7),0)) -> 1200.2345 | D20: =(SUMIFS('04_Base_Despesas'!$D$4:$D$219, '04_Base_Despesas'!$A$4:$A$219, D$7, '04_Base_Despesas'!$B$4:$B$219, "administrativo"))*(IFERROR(SUMIFS('03_Base_Vendas'!$I$4:$I$387, '03_Base_Vendas'!$A$4:$A$387, D$7, '03_Base_Vendas'!$B$4:$B$387, "ecommerce")/SUMIFS('03_Base_Vendas'!$I$4:$I$387, '03_Base_Vendas'!$A$4:$A$387, D$7),0)) -> 1074.6508 | E20: =(SUMIFS('04_Base_Despesas'!$D$4:$D$219, '04_Base_Despesas'!$A$4:$A$219, E$7, '04_Base_Despesas'!$B$4:$B$219, "administrativo"))*(IFERROR(SUMIFS('03_Base_Vendas'!$I$4:$I$387, '03_Base_Vendas'!$A$4:$A$387, E$7, '03_Base_Vendas'!$B$4:$B$387, "ecommerce")/SUMIFS('03_Base_Vendas'!$I$4:$I$387, '03_Base_Vendas'!$A$4:$A$387, E$7),0)) -> 1957.0023 | F20: =(SUMIFS('04_Base_Despesas'!$D$4:$D$219, '04_Base_Despesas'!$A$4:$A$219, F$7, '04_Base_Despesas'!$B$4:$B$219, "administrativo"))*(IFERROR(SUMIFS('03_Base_Vendas'!$I$4:$I$387, '03_Base_Vendas'!$A$4:$A$387, F$7, '03_Base_Vendas'!$B$4:$B$387, "ecommerce")/SUMIFS('03_Base_Vendas'!$I$4:$I$387, '03_Base_Vendas'!$A$4:$A$387, F$7),0)) -> 1217.4957 | G20: =(SUMIFS('04_Base_Despesas'!$D$4:$D$219, '04_Base_Despesas'!$A$4:$A$219, G$7, '04_Base_Despesas'!$B$4:$B$219, "administrativo"))*(IFERROR(SUMIFS('03_Base_Vendas'!$I$4:$I$387, '03_Base_Vendas'!$A$4:$A$387, G$7, '03_Base_Vendas'!$B$4:$B$387, "ecommerce")/SUMIFS('03_Base_Vendas'!$I$4:$I$387, '03_Base_Vendas'!$A$4:$A$387, G$7),0)) -> 1193.8562 | H20: =(SUMIFS('04_Base_Despesas'!$D$4:$D$219, '04_Base_Despesas'!$A$4:$A$219, H$7, '04_Base_Despesas'!$B$4:$B$219, "administrativo"))*(IFERROR(SUMIFS('03_Base_Vendas'!$I$4:$I$387, '03_Base_Vendas'!$A$4:$A$387, H$7, '03_Base_Vendas'!$B$4:$B$387, "ecommerce")/SUMIFS('03_Base_Vendas'!$I$4:$I$387, '03_Base_Vendas'!$A$4:$A$387, H$7),0)) -> 2080.6885 | I20: =(SUMIFS('04_Base_Despesas'!$D$4:$D$219, '04_Base_Despesas'!$A$4:$A$219, I$7, '04_Base_Despesas'!$B$4:$B$219, "administrativo"))*(IFERROR(SUMIFS('03_Base_Vendas'!$I$4:$I$387, '03_Base_Vendas'!$A$4:$A$387, I$7, '03_Base_Vendas'!$B$4:$B$387, "ecommerce")/SUMIFS('03_Base_Vendas'!$I$4:$I$387, '03_Base_Vendas'!$A$4:$A$387, I$7),0)) -> 1156.82 | ... Y20: =(SUMIFS('04_Base_Despesas'!$D$4:$D$219, '04_Base_Despesas'!$A$4:$A$219, Y$7, '04_Base_Despesas'!$B$4:$B$219, "administrativo"))*(IFERROR(SUMIFS('03_Base_Vendas'!$I$4:$I$387, '03_Base_Vendas'!$A$4:$A$387, Y$7, '03_Base_Vendas'!$B$4:$B$387, "ecommerce")/SUMIFS('03_Base_Vendas'!$I$4:$I$387, '03_Base_Vendas'!$A$4:$A$387, Y$7),0)) -> 1273.2419 | Z20: =SUM(B20:Y20) -> 34165.639
A21: (−) Outros | B21: =(SUMIFS('04_Base_Despesas'!$D$4:$D$219, '04_Base_Despesas'!$A$4:$A$219, B$7, '04_Base_Despesas'!$B$4:$B$219, "outros"))*(IFERROR(SUMIFS('03_Base_Vendas'!$I$4:$I$387, '03_Base_Vendas'!$A$4:$A$387, B$7, '03_Base_Vendas'!$B$4:$B$387, "ecommerce")/SUMIFS('03_Base_Vendas'!$I$4:$I$387, '03_Base_Vendas'!$A$4:$A$387, B$7),0)) -> 337.0314 | C21: =(SUMIFS('04_Base_Despesas'!$D$4:$D$219, '04_Base_Despesas'!$A$4:$A$219, C$7, '04_Base_Despesas'!$B$4:$B$219, "outros"))*(IFERROR(SUMIFS('03_Base_Vendas'!$I$4:$I$387, '03_Base_Vendas'!$A$4:$A$387, C$7, '03_Base_Vendas'!$B$4:$B$387, "ecommerce")/SUMIFS('03_Base_Vendas'!$I$4:$I$387, '03_Base_Vendas'!$A$4:$A$387, C$7),0)) -> 421.84403 | D21: =(SUMIFS('04_Base_Despesas'!$D$4:$D$219, '04_Base_Despesas'!$A$4:$A$219, D$7, '04_Base_Despesas'!$B$4:$B$219, "outros"))*(IFERROR(SUMIFS('03_Base_Vendas'!$I$4:$I$387, '03_Base_Vendas'!$A$4:$A$387, D$7, '03_Base_Vendas'!$B$4:$B$387, "ecommerce")/SUMIFS('03_Base_Vendas'!$I$4:$I$387, '03_Base_Vendas'!$A$4:$A$387, D$7),0)) -> 371.74751 | E21: =(SUMIFS('04_Base_Despesas'!$D$4:$D$219, '04_Base_Despesas'!$A$4:$A$219, E$7, '04_Base_Despesas'!$B$4:$B$219, "outros"))*(IFERROR(SUMIFS('03_Base_Vendas'!$I$4:$I$387, '03_Base_Vendas'!$A$4:$A$387, E$7, '03_Base_Vendas'!$B$4:$B$387, "ecommerce")/SUMIFS('03_Base_Vendas'!$I$4:$I$387, '03_Base_Vendas'!$A$4:$A$387, E$7),0)) -> 295.67943 | F21: =(SUMIFS('04_Base_Despesas'!$D$4:$D$219, '04_Base_Despesas'!$A$4:$A$219, F$7, '04_Base_Despesas'!$B$4:$B$219, "outros"))*(IFERROR(SUMIFS('03_Base_Vendas'!$I$4:$I$387, '03_Base_Vendas'!$A$4:$A$387, F$7, '03_Base_Vendas'!$B$4:$B$387, "ecommerce")/SUMIFS('03_Base_Vendas'!$I$4:$I$387, '03_Base_Vendas'!$A$4:$A$387, F$7),0)) -> 376.8003 | G21: =(SUMIFS('04_Base_Despesas'!$D$4:$D$219, '04_Base_Despesas'!$A$4:$A$219, G$7, '04_Base_Despesas'!$B$4:$B$219, "outros"))*(IFERROR(SUMIFS('03_Base_Vendas'!$I$4:$I$387, '03_Base_Vendas'!$A$4:$A$387, G$7, '03_Base_Vendas'!$B$4:$B$387, "ecommerce")/SUMIFS('03_Base_Vendas'!$I$4:$I$387, '03_Base_Vendas'!$A$4:$A$387, G$7),0)) -> 368.0993 | H21: =(SUMIFS('04_Base_Despesas'!$D$4:$D$219, '04_Base_Despesas'!$A$4:$A$219, H$7, '04_Base_Despesas'!$B$4:$B$219, "outros"))*(IFERROR(SUMIFS('03_Base_Vendas'!$I$4:$I$387, '03_Base_Vendas'!$A$4:$A$387, H$7, '03_Base_Vendas'!$B$4:$B$387, "ecommerce")/SUMIFS('03_Base_Vendas'!$I$4:$I$387, '03_Base_Vendas'!$A$4:$A$387, H$7),0)) -> 481.70306 | I21: =(SUMIFS('04_Base_Despesas'!$D$4:$D$219, '04_Base_Despesas'!$A$4:$A$219, I$7, '04_Base_Despesas'!$B$4:$B$219, "outros"))*(IFERROR(SUMIFS('03_Base_Vendas'!$I$4:$I$387, '03_Base_Vendas'!$A$4:$A$387, I$7, '03_Base_Vendas'!$B$4:$B$387, "ecommerce")/SUMIFS('03_Base_Vendas'!$I$4:$I$387, '03_Base_Vendas'!$A$4:$A$387, I$7),0)) -> 404.33637 | ... Y21: =(SUMIFS('04_Base_Despesas'!$D$4:$D$219, '04_Base_Despesas'!$A$4:$A$219, Y$7, '04_Base_Despesas'!$B$4:$B$219, "outros"))*(IFERROR(SUMIFS('03_Base_Vendas'!$I$4:$I$387, '03_Base_Vendas'!$A$4:$A$387, Y$7, '03_Base_Vendas'!$B$4:$B$387, "ecommerce")/SUMIFS('03_Base_Vendas'!$I$4:$I$387, '03_Base_Vendas'!$A$4:$A$387, Y$7),0)) -> 330.26367 | Z21: =SUM(B21:Y21) -> 9289.7811
A22: Total Despesas Operac. | B22: =B15+B16+B17+B18+B19+B20+B21 -> 41992.431 | C22: =C15+C16+C17+C18+C19+C20+C21 -> 44614.509 | D22: =D15+D16+D17+D18+D19+D20+D21 -> 38858.42 | E22: =E15+E16+E17+E18+E19+E20+E21 -> 40381.346 | F22: =F15+F16+F17+F18+F19+F20+F21 -> 47880.872 | G22: =G15+G16+G17+G18+G19+G20+G21 -> 46420.865 | H22: =H15+H16+H17+H18+H19+H20+H21 -> 45957.2 | I22: =I15+I16+I17+I18+I19+I20+I21 -> 44042.365 | ... Y22: =Y15+Y16+Y17+Y18+Y19+Y20+Y21 -> 44406.572 | Z22: =SUM(B22:Y22) -> 1045762.8
A23: EBITDA | B23: =B13-B22 -> -10830.131 | C23: =C13-C22 -> -16350.759 | D23: =D13-D22 -> -7559.8796 | E23: =E13-E22 -> -10961.376 | F23: =F13-F22 -> -1807.0515 | G23: =G13-G22 -> -8526.4046 | H23: =H13-H22 -> -14823.93 | I23: =I13-I22 -> -15114.035 | ... Y23: =Y13-Y22 -> 4182.5575 | Z23: =SUM(B23:Y23) -> -168983.82
A24: % Margem EBITDA | B24: =IFERROR(B23/B11,0) -> -0.16951982 | C24: =IFERROR(C23/C11,0) -> -0.27308968 | D24: =IFERROR(D23/D11,0) -> -0.11562538 | E24: =IFERROR(E23/E11,0) -> -0.18256692 | F24: =IFERROR(F23/F11,0) -> -0.019029137 | G24: =IFERROR(G23/G11,0) -> -0.10519982 | H24: =IFERROR(H23/H11,0) -> -0.23449537 | I24: =IFERROR(I23/I11,0) -> -0.25330927 | ... Y24: =IFERROR(Y23/Y11,0) -> 0.042272078 | Z24: =IFERROR($Z$23/$Z$11,0) -> -0.093470732
A25: (−) Depreciação | B25: =(SUMIFS('04_Base_Despesas'!$D$4:$D$219, '04_Base_Despesas'!$A$4:$A$219, B$7, '04_Base_Despesas'!$B$4:$B$219, "depreciacao"))*(IFERROR(SUMIFS('03_Base_Vendas'!$I$4:$I$387, '03_Base_Vendas'!$A$4:$A$387, B$7, '03_Base_Vendas'!$B$4:$B$387, "ecommerce")/SUMIFS('03_Base_Vendas'!$I$4:$I$387, '03_Base_Vendas'!$A$4:$A$387, B$7),0)) -> 936.86834 | C25: =(SUMIFS('04_Base_Despesas'!$D$4:$D$219, '04_Base_Despesas'!$A$4:$A$219, C$7, '04_Base_Despesas'!$B$4:$B$219, "depreciacao"))*(IFERROR(SUMIFS('03_Base_Vendas'!$I$4:$I$387, '03_Base_Vendas'!$A$4:$A$387, C$7, '03_Base_Vendas'!$B$4:$B$387, "ecommerce")/SUMIFS('03_Base_Vendas'!$I$4:$I$387, '03_Base_Vendas'!$A$4:$A$387, C$7),0)) -> 1056.2064 | D25: =(SUMIFS('04_Base_Despesas'!$D$4:$D$219, '04_Base_Despesas'!$A$4:$A$219, D$7, '04_Base_Despesas'!$B$4:$B$219, "depreciacao"))*(IFERROR(SUMIFS('03_Base_Vendas'!$I$4:$I$387, '03_Base_Vendas'!$A$4:$A$387, D$7, '03_Base_Vendas'!$B$4:$B$387, "ecommerce")/SUMIFS('03_Base_Vendas'!$I$4:$I$387, '03_Base_Vendas'!$A$4:$A$387, D$7),0)) -> 945.68843 | E25: =(SUMIFS('04_Base_Despesas'!$D$4:$D$219, '04_Base_Despesas'!$A$4:$A$219, E$7, '04_Base_Despesas'!$B$4:$B$219, "depreciacao"))*(IFERROR(SUMIFS('03_Base_Vendas'!$I$4:$I$387, '03_Base_Vendas'!$A$4:$A$387, E$7, '03_Base_Vendas'!$B$4:$B$387, "ecommerce")/SUMIFS('03_Base_Vendas'!$I$4:$I$387, '03_Base_Vendas'!$A$4:$A$387, E$7),0)) -> 944.72702 | F25: =(SUMIFS('04_Base_Despesas'!$D$4:$D$219, '04_Base_Despesas'!$A$4:$A$219, F$7, '04_Base_Despesas'!$B$4:$B$219, "depreciacao"))*(IFERROR(SUMIFS('03_Base_Vendas'!$I$4:$I$387, '03_Base_Vendas'!$A$4:$A$387, F$7, '03_Base_Vendas'!$B$4:$B$387, "ecommerce")/SUMIFS('03_Base_Vendas'!$I$4:$I$387, '03_Base_Vendas'!$A$4:$A$387, F$7),0)) -> 1071.3913 | G25: =(SUMIFS('04_Base_Despesas'!$D$4:$D$219, '04_Base_Despesas'!$A$4:$A$219, G$7, '04_Base_Despesas'!$B$4:$B$219, "depreciacao"))*(IFERROR(SUMIFS('03_Base_Vendas'!$I$4:$I$387, '03_Base_Vendas'!$A$4:$A$387, G$7, '03_Base_Vendas'!$B$4:$B$387, "ecommerce")/SUMIFS('03_Base_Vendas'!$I$4:$I$387, '03_Base_Vendas'!$A$4:$A$387, G$7),0)) -> 1050.5887 | H25: =(SUMIFS('04_Base_Despesas'!$D$4:$D$219, '04_Base_Despesas'!$A$4:$A$219, H$7, '04_Base_Despesas'!$B$4:$B$219, "depreciacao"))*(IFERROR(SUMIFS('03_Base_Vendas'!$I$4:$I$387, '03_Base_Vendas'!$A$4:$A$387, H$7, '03_Base_Vendas'!$B$4:$B$387, "ecommerce")/SUMIFS('03_Base_Vendas'!$I$4:$I$387, '03_Base_Vendas'!$A$4:$A$387, H$7),0)) -> 1076.3609 | I25: =(SUMIFS('04_Base_Despesas'!$D$4:$D$219, '04_Base_Despesas'!$A$4:$A$219, I$7, '04_Base_Despesas'!$B$4:$B$219, "depreciacao"))*(IFERROR(SUMIFS('03_Base_Vendas'!$I$4:$I$387, '03_Base_Vendas'!$A$4:$A$387, I$7, '03_Base_Vendas'!$B$4:$B$387, "ecommerce")/SUMIFS('03_Base_Vendas'!$I$4:$I$387, '03_Base_Vendas'!$A$4:$A$387, I$7),0)) -> 1018.0016 | ... Y25: =(SUMIFS('04_Base_Despesas'!$D$4:$D$219, '04_Base_Despesas'!$A$4:$A$219, Y$7, '04_Base_Despesas'!$B$4:$B$219, "depreciacao"))*(IFERROR(SUMIFS('03_Base_Vendas'!$I$4:$I$387, '03_Base_Vendas'!$A$4:$A$387, Y$7, '03_Base_Vendas'!$B$4:$B$387, "ecommerce")/SUMIFS('03_Base_Vendas'!$I$4:$I$387, '03_Base_Vendas'!$A$4:$A$387, Y$7),0)) -> 1120.4529 | Z25: =SUM(B25:Y25) -> 24031.878
A26: EBIT | B26: =B23-B25 -> -11767 | C26: =C23-C25 -> -17406.965 | D26: =D23-D25 -> -8505.568 | E26: =E23-E25 -> -11906.103 | F26: =F23-F25 -> -2878.4429 | G26: =G23-G25 -> -9576.9933 | H26: =H23-H25 -> -15900.291 | I26: =I23-I25 -> -16132.036 | ... Y26: =Y23-Y25 -> 3062.1046 | Z26: =SUM(B26:Y26) -> -193015.69
A27: (−) Despesas Financeiras | B27: =(SUMIFS('04_Base_Despesas'!$D$4:$D$219, '04_Base_Despesas'!$A$4:$A$219, B$7, '04_Base_Despesas'!$B$4:$B$219, "financeiro"))*(IFERROR(SUMIFS('03_Base_Vendas'!$I$4:$I$387, '03_Base_Vendas'!$A$4:$A$387, B$7, '03_Base_Vendas'!$B$4:$B$387, "ecommerce")/SUMIFS('03_Base_Vendas'!$I$4:$I$387, '03_Base_Vendas'!$A$4:$A$387, B$7),0)) -> 581.47424 | C27: =(SUMIFS('04_Base_Despesas'!$D$4:$D$219, '04_Base_Despesas'!$A$4:$A$219, C$7, '04_Base_Despesas'!$B$4:$B$219, "financeiro"))*(IFERROR(SUMIFS('03_Base_Vendas'!$I$4:$I$387, '03_Base_Vendas'!$A$4:$A$387, C$7, '03_Base_Vendas'!$B$4:$B$387, "ecommerce")/SUMIFS('03_Base_Vendas'!$I$4:$I$387, '03_Base_Vendas'!$A$4:$A$387, C$7),0)) -> 648.8804 | D27: =(SUMIFS('04_Base_Despesas'!$D$4:$D$219, '04_Base_Despesas'!$A$4:$A$219, D$7, '04_Base_Despesas'!$B$4:$B$219, "financeiro"))*(IFERROR(SUMIFS('03_Base_Vendas'!$I$4:$I$387, '03_Base_Vendas'!$A$4:$A$387, D$7, '03_Base_Vendas'!$B$4:$B$387, "ecommerce")/SUMIFS('03_Base_Vendas'!$I$4:$I$387, '03_Base_Vendas'!$A$4:$A$387, D$7),0)) -> 578.51033 | E27: =(SUMIFS('04_Base_Despesas'!$D$4:$D$219, '04_Base_Despesas'!$A$4:$A$219, E$7, '04_Base_Despesas'!$B$4:$B$219, "financeiro"))*(IFERROR(SUMIFS('03_Base_Vendas'!$I$4:$I$387, '03_Base_Vendas'!$A$4:$A$387, E$7, '03_Base_Vendas'!$B$4:$B$387, "ecommerce")/SUMIFS('03_Base_Vendas'!$I$4:$I$387, '03_Base_Vendas'!$A$4:$A$387, E$7),0)) -> 557.43442 | F27: =(SUMIFS('04_Base_Despesas'!$D$4:$D$219, '04_Base_Despesas'!$A$4:$A$219, F$7, '04_Base_Despesas'!$B$4:$B$219, "financeiro"))*(IFERROR(SUMIFS('03_Base_Vendas'!$I$4:$I$387, '03_Base_Vendas'!$A$4:$A$387, F$7, '03_Base_Vendas'!$B$4:$B$387, "ecommerce")/SUMIFS('03_Base_Vendas'!$I$4:$I$387, '03_Base_Vendas'!$A$4:$A$387, F$7),0)) -> 658.92327 | G27: =(SUMIFS('04_Base_Despesas'!$D$4:$D$219, '04_Base_Despesas'!$A$4:$A$219, G$7, '04_Base_Despesas'!$B$4:$B$219, "financeiro"))*(IFERROR(SUMIFS('03_Base_Vendas'!$I$4:$I$387, '03_Base_Vendas'!$A$4:$A$387, G$7, '03_Base_Vendas'!$B$4:$B$387, "ecommerce")/SUMIFS('03_Base_Vendas'!$I$4:$I$387, '03_Base_Vendas'!$A$4:$A$387, G$7),0)) -> 610.52375 | H27: =(SUMIFS('04_Base_Despesas'!$D$4:$D$219, '04_Base_Despesas'!$A$4:$A$219, H$7, '04_Base_Despesas'!$B$4:$B$219, "financeiro"))*(IFERROR(SUMIFS('03_Base_Vendas'!$I$4:$I$387, '03_Base_Vendas'!$A$4:$A$387, H$7, '03_Base_Vendas'!$B$4:$B$387, "ecommerce")/SUMIFS('03_Base_Vendas'!$I$4:$I$387, '03_Base_Vendas'!$A$4:$A$387, H$7),0)) -> 2664.4898 | I27: =(SUMIFS('04_Base_Despesas'!$D$4:$D$219, '04_Base_Despesas'!$A$4:$A$219, I$7, '04_Base_Despesas'!$B$4:$B$219, "financeiro"))*(IFERROR(SUMIFS('03_Base_Vendas'!$I$4:$I$387, '03_Base_Vendas'!$A$4:$A$387, I$7, '03_Base_Vendas'!$B$4:$B$387, "ecommerce")/SUMIFS('03_Base_Vendas'!$I$4:$I$387, '03_Base_Vendas'!$A$4:$A$387, I$7),0)) -> 607.87654 | ... Y27: =(SUMIFS('04_Base_Despesas'!$D$4:$D$219, '04_Base_Despesas'!$A$4:$A$219, Y$7, '04_Base_Despesas'!$B$4:$B$219, "financeiro"))*(IFERROR(SUMIFS('03_Base_Vendas'!$I$4:$I$387, '03_Base_Vendas'!$A$4:$A$387, Y$7, '03_Base_Vendas'!$B$4:$B$387, "ecommerce")/SUMIFS('03_Base_Vendas'!$I$4:$I$387, '03_Base_Vendas'!$A$4:$A$387, Y$7),0)) -> 704.79541 | Z27: =SUM(B27:Y27) -> 16355.6
A28: Resultado Operacional | B28: =B26-B27 -> -12348.474 | C28: =C26-C27 -> -18055.845 | D28: =D26-D27 -> -9084.0783 | E28: =E26-E27 -> -12463.537 | F28: =F26-F27 -> -3537.3661 | G28: =G26-G27 -> -10187.517 | H28: =H26-H27 -> -18564.78 | I28: =I26-I27 -> -16739.913 | ... Y28: =Y26-Y27 -> 2357.3092 | Z28: =SUM(B28:Y28) -> -209371.29
A29: % Margem Operacional | B29: =IFERROR(B28/B11,0) -> -0.19328584 | C29: =IFERROR(C28/C11,0) -> -0.30156797 | D29: =IFERROR(D28/D11,0) -> -0.13893739 | E29: =IFERROR(E28/E11,0) -> -0.20758613 | F29: =IFERROR(F28/F11,0) -> -0.037250196 | G29: =IFERROR(G28/G11,0) -> -0.12569483 | H29: =IFERROR(H28/H11,0) -> -0.29367079 | I29: =IFERROR(I28/I11,0) -> -0.28055878 | ... Y29: =IFERROR(Y28/Y11,0) -> 0.023824743 | Z29: =IFERROR($Z$28/$Z$11,0) -> -0.11581043
A32: Canal: Marketplace
A33: Item | B33: 2023-01 | C33: 2023-02 | D33: 2023-03 | E33: 2023-04 | F33: 2023-05 | G33: 2023-06 | H33: 2023-07 | I33: 2023-08 | J33: 2023-09 | K33: 2023-10 | L33: 2023-11 | M33: 2023-12 | N33: 2024-01 | O33: 2024-02 | P33: 2024-03 | Q33: 2024-04 | R33: 2024-05 | S33: 2024-06 | T33: 2024-07 | U33: 2024-08 | V33: 2024-09 | W33: 2024-10 | X33: 2024-11 | Y33: 2024-12 | Z33: Total 24m
A34: Receita Bruta | B34: =SUMIFS('03_Base_Vendas'!$F$4:$F$387, '03_Base_Vendas'!$A$4:$A$387, B$33, '03_Base_Vendas'!$B$4:$B$387, "marketplace") -> 48043.79 | C34: =SUMIFS('03_Base_Vendas'!$F$4:$F$387, '03_Base_Vendas'!$A$4:$A$387, C$33, '03_Base_Vendas'!$B$4:$B$387, "marketplace") -> 38952.35 | D34: =SUMIFS('03_Base_Vendas'!$F$4:$F$387, '03_Base_Vendas'!$A$4:$A$387, D$33, '03_Base_Vendas'!$B$4:$B$387, "marketplace") -> 52271.09 | E34: =SUMIFS('03_Base_Vendas'!$F$4:$F$387, '03_Base_Vendas'!$A$4:$A$387, E$33, '03_Base_Vendas'!$B$4:$B$387, "marketplace") -> 44313.22 | F34: =SUMIFS('03_Base_Vendas'!$F$4:$F$387, '03_Base_Vendas'!$A$4:$A$387, F$33, '03_Base_Vendas'!$B$4:$B$387, "marketplace") -> 57481.92 | G34: =SUMIFS('03_Base_Vendas'!$F$4:$F$387, '03_Base_Vendas'!$A$4:$A$387, G$33, '03_Base_Vendas'!$B$4:$B$387, "marketplace") -> 46196.45 | H34: =SUMIFS('03_Base_Vendas'!$F$4:$F$387, '03_Base_Vendas'!$A$4:$A$387, H$33, '03_Base_Vendas'!$B$4:$B$387, "marketplace") -> 36921.66 | I34: =SUMIFS('03_Base_Vendas'!$F$4:$F$387, '03_Base_Vendas'!$A$4:$A$387, I$33, '03_Base_Vendas'!$B$4:$B$387, "marketplace") -> 35553.54 | ... Y34: =SUMIFS('03_Base_Vendas'!$F$4:$F$387, '03_Base_Vendas'!$A$4:$A$387, Y$33, '03_Base_Vendas'!$B$4:$B$387, "marketplace") -> 40845.7 | Z34: =SUM(B34:Y34) -> 1264470.2
A35: (−) Devoluções | B35: =SUMIFS('03_Base_Vendas'!$G$4:$G$387, '03_Base_Vendas'!$A$4:$A$387, B$33, '03_Base_Vendas'!$B$4:$B$387, "marketplace") -> 1244.69 | C35: =SUMIFS('03_Base_Vendas'!$G$4:$G$387, '03_Base_Vendas'!$A$4:$A$387, C$33, '03_Base_Vendas'!$B$4:$B$387, "marketplace") -> 1951.03 | D35: =SUMIFS('03_Base_Vendas'!$G$4:$G$387, '03_Base_Vendas'!$A$4:$A$387, D$33, '03_Base_Vendas'!$B$4:$B$387, "marketplace") -> 1417.52 | E35: =SUMIFS('03_Base_Vendas'!$G$4:$G$387, '03_Base_Vendas'!$A$4:$A$387, E$33, '03_Base_Vendas'!$B$4:$B$387, "marketplace") -> 2329.43 | F35: =SUMIFS('03_Base_Vendas'!$G$4:$G$387, '03_Base_Vendas'!$A$4:$A$387, F$33, '03_Base_Vendas'!$B$4:$B$387, "marketplace") -> 3542.91 | G35: =SUMIFS('03_Base_Vendas'!$G$4:$G$387, '03_Base_Vendas'!$A$4:$A$387, G$33, '03_Base_Vendas'!$B$4:$B$387, "marketplace") -> 2804.29 | H35: =SUMIFS('03_Base_Vendas'!$G$4:$G$387, '03_Base_Vendas'!$A$4:$A$387, H$33, '03_Base_Vendas'!$B$4:$B$387, "marketplace") -> 3064.76 | I35: =SUMIFS('03_Base_Vendas'!$G$4:$G$387, '03_Base_Vendas'!$A$4:$A$387, I$33, '03_Base_Vendas'!$B$4:$B$387, "marketplace") -> 3716.01 | ... Y35: =SUMIFS('03_Base_Vendas'!$G$4:$G$387, '03_Base_Vendas'!$A$4:$A$387, Y$33, '03_Base_Vendas'!$B$4:$B$387, "marketplace") -> 1637.15 | Z35: =SUM(B35:Y35) -> 72154.77
A36: (−) Comissões de canal | B36: =SUMIFS('03_Base_Vendas'!$H$4:$H$387, '03_Base_Vendas'!$A$4:$A$387, B$33, '03_Base_Vendas'!$B$4:$B$387, "marketplace") -> 8192.53 | C36: =SUMIFS('03_Base_Vendas'!$H$4:$H$387, '03_Base_Vendas'!$A$4:$A$387, C$33, '03_Base_Vendas'!$B$4:$B$387, "marketplace") -> 6562.65 | D36: =SUMIFS('03_Base_Vendas'!$H$4:$H$387, '03_Base_Vendas'!$A$4:$A$387, D$33, '03_Base_Vendas'!$B$4:$B$387, "marketplace") -> 8928.57 | E36: =SUMIFS('03_Base_Vendas'!$H$4:$H$387, '03_Base_Vendas'!$A$4:$A$387, E$33, '03_Base_Vendas'!$B$4:$B$387, "marketplace") -> 7512.39 | F36: =SUMIFS('03_Base_Vendas'!$H$4:$H$387, '03_Base_Vendas'!$A$4:$A$387, F$33, '03_Base_Vendas'!$B$4:$B$387, "marketplace") -> 9811.66 | G36: =SUMIFS('03_Base_Vendas'!$H$4:$H$387, '03_Base_Vendas'!$A$4:$A$387, G$33, '03_Base_Vendas'!$B$4:$B$387, "marketplace") -> 7809.6 | H36: =SUMIFS('03_Base_Vendas'!$H$4:$H$387, '03_Base_Vendas'!$A$4:$A$387, H$33, '03_Base_Vendas'!$B$4:$B$387, "marketplace") -> 6254.67 | I36: =SUMIFS('03_Base_Vendas'!$H$4:$H$387, '03_Base_Vendas'!$A$4:$A$387, I$33, '03_Base_Vendas'!$B$4:$B$387, "marketplace") -> 6032.54 | ... Y36: =SUMIFS('03_Base_Vendas'!$H$4:$H$387, '03_Base_Vendas'!$A$4:$A$387, Y$33, '03_Base_Vendas'!$B$4:$B$387, "marketplace") -> 6910.14 | Z36: =SUM(B36:Y36) -> 214934.81
A37: Receita Líquida | B37: =B34-B35-B36 -> 38606.57 | C37: =C34-C35-C36 -> 30438.67 | D37: =D34-D35-D36 -> 41925 | E37: =E34-E35-E36 -> 34471.4 | F37: =F34-F35-F36 -> 44127.35 | G37: =G34-G35-G36 -> 35582.56 | H37: =H34-H35-H36 -> 27602.23 | I37: =I34-I35-I36 -> 25804.99 | ... Y37: =Y34-Y35-Y36 -> 32298.41 | Z37: =SUM(B37:Y37) -> 977380.67
A38: (−) CMV | B38: =SUMIFS('03_Base_Vendas'!$J$4:$J$387, '03_Base_Vendas'!$A$4:$A$387, B$33, '03_Base_Vendas'!$B$4:$B$387, "marketplace") -> 22515.81 | C38: =SUMIFS('03_Base_Vendas'!$J$4:$J$387, '03_Base_Vendas'!$A$4:$A$387, C$33, '03_Base_Vendas'!$B$4:$B$387, "marketplace") -> 18509.5 | D38: =SUMIFS('03_Base_Vendas'!$J$4:$J$387, '03_Base_Vendas'!$A$4:$A$387, D$33, '03_Base_Vendas'!$B$4:$B$387, "marketplace") -> 25121.66 | E38: =SUMIFS('03_Base_Vendas'!$J$4:$J$387, '03_Base_Vendas'!$A$4:$A$387, E$33, '03_Base_Vendas'!$B$4:$B$387, "marketplace") -> 21232.47 | F38: =SUMIFS('03_Base_Vendas'!$J$4:$J$387, '03_Base_Vendas'!$A$4:$A$387, F$33, '03_Base_Vendas'!$B$4:$B$387, "marketplace") -> 26589.99 | G38: =SUMIFS('03_Base_Vendas'!$J$4:$J$387, '03_Base_Vendas'!$A$4:$A$387, G$33, '03_Base_Vendas'!$B$4:$B$387, "marketplace") -> 22543.46 | H38: =SUMIFS('03_Base_Vendas'!$J$4:$J$387, '03_Base_Vendas'!$A$4:$A$387, H$33, '03_Base_Vendas'!$B$4:$B$387, "marketplace") -> 17743.91 | I38: =SUMIFS('03_Base_Vendas'!$J$4:$J$387, '03_Base_Vendas'!$A$4:$A$387, I$33, '03_Base_Vendas'!$B$4:$B$387, "marketplace") -> 16488.71 | ... Y38: =SUMIFS('03_Base_Vendas'!$J$4:$J$387, '03_Base_Vendas'!$A$4:$A$387, Y$33, '03_Base_Vendas'!$B$4:$B$387, "marketplace") -> 21473.53 | Z38: =SUM(B38:Y38) -> 606905.21
A39: Margem de Contribuição | B39: =B37-B38 -> 16090.76 | C39: =C37-C38 -> 11929.17 | D39: =D37-D38 -> 16803.34 | E39: =E37-E38 -> 13238.93 | F39: =F37-F38 -> 17537.36 | G39: =G37-G38 -> 13039.1 | H39: =H37-H38 -> 9858.32 | I39: =I37-I38 -> 9316.28 | ... Y39: =Y37-Y38 -> 10824.88 | Z39: =SUM(B39:Y39) -> 370475.46
A40: % Margem de Contribuição | B40: =IFERROR(B39/B37,0) -> 0.41678813 | C40: =IFERROR(C39/C37,0) -> 0.39190838 | D40: =IFERROR(D39/D37,0) -> 0.40079523 | E40: =IFERROR(E39/E37,0) -> 0.38405548 | F40: =IFERROR(F39/F37,0) -> 0.39742609 | G40: =IFERROR(G39/G37,0) -> 0.36644637 | H40: =IFERROR(H39/H37,0) -> 0.35715665 | I40: =IFERROR(I39/I37,0) -> 0.3610263 | ... Y40: =IFERROR(Y39/Y37,0) -> 0.3351521 | Z40: =IFERROR($Z$39/$Z$37,0) -> 0.3790493
A41: (−) Pessoal | B41: =(SUMIFS('04_Base_Despesas'!$D$4:$D$219, '04_Base_Despesas'!$A$4:$A$219, B$33, '04_Base_Despesas'!$B$4:$B$219, "pessoal"))*(IFERROR(SUMIFS('03_Base_Vendas'!$I$4:$I$387, '03_Base_Vendas'!$A$4:$A$387, B$33, '03_Base_Vendas'!$B$4:$B$387, "marketplace")/SUMIFS('03_Base_Vendas'!$I$4:$I$387, '03_Base_Vendas'!$A$4:$A$387, B$33),0)) -> 13034.822 | C41: =(SUMIFS('04_Base_Despesas'!$D$4:$D$219, '04_Base_Despesas'!$A$4:$A$219, C$33, '04_Base_Despesas'!$B$4:$B$219, "pessoal"))*(IFERROR(SUMIFS('03_Base_Vendas'!$I$4:$I$387, '03_Base_Vendas'!$A$4:$A$387, C$33, '03_Base_Vendas'!$B$4:$B$387, "marketplace")/SUMIFS('03_Base_Vendas'!$I$4:$I$387, '03_Base_Vendas'!$A$4:$A$387, C$33),0)) -> 12722.074 | D41: =(SUMIFS('04_Base_Despesas'!$D$4:$D$219, '04_Base_Despesas'!$A$4:$A$219, D$33, '04_Base_Despesas'!$B$4:$B$219, "pessoal"))*(IFERROR(SUMIFS('03_Base_Vendas'!$I$4:$I$387, '03_Base_Vendas'!$A$4:$A$387, D$33, '03_Base_Vendas'!$B$4:$B$387, "marketplace")/SUMIFS('03_Base_Vendas'!$I$4:$I$387, '03_Base_Vendas'!$A$4:$A$387, D$33),0)) -> 13816.274 | E41: =(SUMIFS('04_Base_Despesas'!$D$4:$D$219, '04_Base_Despesas'!$A$4:$A$219, E$33, '04_Base_Despesas'!$B$4:$B$219, "pessoal"))*(IFERROR(SUMIFS('03_Base_Vendas'!$I$4:$I$387, '03_Base_Vendas'!$A$4:$A$387, E$33, '03_Base_Vendas'!$B$4:$B$387, "marketplace")/SUMIFS('03_Base_Vendas'!$I$4:$I$387, '03_Base_Vendas'!$A$4:$A$387, E$33),0)) -> 12197.429 | F41: =(SUMIFS('04_Base_Despesas'!$D$4:$D$219, '04_Base_Despesas'!$A$4:$A$219, F$33, '04_Base_Despesas'!$B$4:$B$219, "pessoal"))*(IFERROR(SUMIFS('03_Base_Vendas'!$I$4:$I$387, '03_Base_Vendas'!$A$4:$A$387, F$33, '03_Base_Vendas'!$B$4:$B$387, "marketplace")/SUMIFS('03_Base_Vendas'!$I$4:$I$387, '03_Base_Vendas'!$A$4:$A$387, F$33),0)) -> 11764.158 | G41: =(SUMIFS('04_Base_Despesas'!$D$4:$D$219, '04_Base_Despesas'!$A$4:$A$219, G$33, '04_Base_Despesas'!$B$4:$B$219, "pessoal"))*(IFERROR(SUMIFS('03_Base_Vendas'!$I$4:$I$387, '03_Base_Vendas'!$A$4:$A$387, G$33, '03_Base_Vendas'!$B$4:$B$387, "marketplace")/SUMIFS('03_Base_Vendas'!$I$4:$I$387, '03_Base_Vendas'!$A$4:$A$387, G$33),0)) -> 10604.778 | H41: =(SUMIFS('04_Base_Despesas'!$D$4:$D$219, '04_Base_Despesas'!$A$4:$A$219, H$33, '04_Base_Despesas'!$B$4:$B$219, "pessoal"))*(IFERROR(SUMIFS('03_Base_Vendas'!$I$4:$I$387, '03_Base_Vendas'!$A$4:$A$387, H$33, '03_Base_Vendas'!$B$4:$B$387, "marketplace")/SUMIFS('03_Base_Vendas'!$I$4:$I$387, '03_Base_Vendas'!$A$4:$A$387, H$33),0)) -> 11083.51 | I41: =(SUMIFS('04_Base_Despesas'!$D$4:$D$219, '04_Base_Despesas'!$A$4:$A$219, I$33, '04_Base_Despesas'!$B$4:$B$219, "pessoal"))*(IFERROR(SUMIFS('03_Base_Vendas'!$I$4:$I$387, '03_Base_Vendas'!$A$4:$A$387, I$33, '03_Base_Vendas'!$B$4:$B$387, "marketplace")/SUMIFS('03_Base_Vendas'!$I$4:$I$387, '03_Base_Vendas'!$A$4:$A$387, I$33),0)) -> 10387.36 | ... Y41: =(SUMIFS('04_Base_Despesas'!$D$4:$D$219, '04_Base_Despesas'!$A$4:$A$219, Y$33, '04_Base_Despesas'!$B$4:$B$219, "pessoal"))*(IFERROR(SUMIFS('03_Base_Vendas'!$I$4:$I$387, '03_Base_Vendas'!$A$4:$A$387, Y$33, '03_Base_Vendas'!$B$4:$B$387, "marketplace")/SUMIFS('03_Base_Vendas'!$I$4:$I$387, '03_Base_Vendas'!$A$4:$A$387, Y$33),0)) -> 8496.9651 | Z41: =SUM(B41:Y41) -> 301818.06
A42: (−) Aluguel | B42: =(SUMIFS('04_Base_Despesas'!$D$4:$D$219, '04_Base_Despesas'!$A$4:$A$219, B$33, '04_Base_Despesas'!$B$4:$B$219, "aluguel"))*(IFERROR(SUMIFS('03_Base_Vendas'!$I$4:$I$387, '03_Base_Vendas'!$A$4:$A$387, B$33, '03_Base_Vendas'!$B$4:$B$387, "marketplace")/SUMIFS('03_Base_Vendas'!$I$4:$I$387, '03_Base_Vendas'!$A$4:$A$387, B$33),0)) -> 2444.7243 | C42: =(SUMIFS('04_Base_Despesas'!$D$4:$D$219, '04_Base_Despesas'!$A$4:$A$219, C$33, '04_Base_Despesas'!$B$4:$B$219, "aluguel"))*(IFERROR(SUMIFS('03_Base_Vendas'!$I$4:$I$387, '03_Base_Vendas'!$A$4:$A$387, C$33, '03_Base_Vendas'!$B$4:$B$387, "marketplace")/SUMIFS('03_Base_Vendas'!$I$4:$I$387, '03_Base_Vendas'!$A$4:$A$387, C$33),0)) -> 2318.6905 | D42: =(SUMIFS('04_Base_Despesas'!$D$4:$D$219, '04_Base_Despesas'!$A$4:$A$219, D$33, '04_Base_Despesas'!$B$4:$B$219, "aluguel"))*(IFERROR(SUMIFS('03_Base_Vendas'!$I$4:$I$387, '03_Base_Vendas'!$A$4:$A$387, D$33, '03_Base_Vendas'!$B$4:$B$387, "marketplace")/SUMIFS('03_Base_Vendas'!$I$4:$I$387, '03_Base_Vendas'!$A$4:$A$387, D$33),0)) -> 2618.5588 | E42: =(SUMIFS('04_Base_Despesas'!$D$4:$D$219, '04_Base_Despesas'!$A$4:$A$219, E$33, '04_Base_Despesas'!$B$4:$B$219, "aluguel"))*(IFERROR(SUMIFS('03_Base_Vendas'!$I$4:$I$387, '03_Base_Vendas'!$A$4:$A$387, E$33, '03_Base_Vendas'!$B$4:$B$387, "marketplace")/SUMIFS('03_Base_Vendas'!$I$4:$I$387, '03_Base_Vendas'!$A$4:$A$387, E$33),0)) -> 2342.2064 | F42: =(SUMIFS('04_Base_Despesas'!$D$4:$D$219, '04_Base_Despesas'!$A$4:$A$219, F$33, '04_Base_Despesas'!$B$4:$B$219, "aluguel"))*(IFERROR(SUMIFS('03_Base_Vendas'!$I$4:$I$387, '03_Base_Vendas'!$A$4:$A$387, F$33, '03_Base_Vendas'!$B$4:$B$387, "marketplace")/SUMIFS('03_Base_Vendas'!$I$4:$I$387, '03_Base_Vendas'!$A$4:$A$387, F$33),0)) -> 2149.8463 | G42: =(SUMIFS('04_Base_Despesas'!$D$4:$D$219, '04_Base_Despesas'!$A$4:$A$219, G$33, '04_Base_Despesas'!$B$4:$B$219, "aluguel"))*(IFERROR(SUMIFS('03_Base_Vendas'!$I$4:$I$387, '03_Base_Vendas'!$A$4:$A$387, G$33, '03_Base_Vendas'!$B$4:$B$387, "marketplace")/SUMIFS('03_Base_Vendas'!$I$4:$I$387, '03_Base_Vendas'!$A$4:$A$387, G$33),0)) -> 1991.6907 | H42: =(SUMIFS('04_Base_Despesas'!$D$4:$D$219, '04_Base_Despesas'!$A$4:$A$219, H$33, '04_Base_Despesas'!$B$4:$B$219, "aluguel"))*(IFERROR(SUMIFS('03_Base_Vendas'!$I$4:$I$387, '03_Base_Vendas'!$A$4:$A$387, H$33, '03_Base_Vendas'!$B$4:$B$387, "marketplace")/SUMIFS('03_Base_Vendas'!$I$4:$I$387, '03_Base_Vendas'!$A$4:$A$387, H$33),0)) -> 2029.4386 | I42: =(SUMIFS('04_Base_Despesas'!$D$4:$D$219, '04_Base_Despesas'!$A$4:$A$219, I$33, '04_Base_Despesas'!$B$4:$B$219, "aluguel"))*(IFERROR(SUMIFS('03_Base_Vendas'!$I$4:$I$387, '03_Base_Vendas'!$A$4:$A$387, I$33, '03_Base_Vendas'!$B$4:$B$387, "marketplace")/SUMIFS('03_Base_Vendas'!$I$4:$I$387, '03_Base_Vendas'!$A$4:$A$387, I$33),0)) -> 1901.1823 | ... Y42: =(SUMIFS('04_Base_Despesas'!$D$4:$D$219, '04_Base_Despesas'!$A$4:$A$219, Y$33, '04_Base_Despesas'!$B$4:$B$219, "aluguel"))*(IFERROR(SUMIFS('03_Base_Vendas'!$I$4:$I$387, '03_Base_Vendas'!$A$4:$A$387, Y$33, '03_Base_Vendas'!$B$4:$B$387, "marketplace")/SUMIFS('03_Base_Vendas'!$I$4:$I$387, '03_Base_Vendas'!$A$4:$A$387, Y$33),0)) -> 1579.3842 | Z42: =SUM(B42:Y42) -> 55850.474
A43: (−) Marketing | B43: =(SUMIFS('04_Base_Despesas'!$D$4:$D$219, '04_Base_Despesas'!$A$4:$A$219, B$33, '04_Base_Despesas'!$B$4:$B$219, "marketing"))*(IFERROR(SUMIFS('03_Base_Vendas'!$I$4:$I$387, '03_Base_Vendas'!$A$4:$A$387, B$33, '03_Base_Vendas'!$B$4:$B$387, "marketplace")/SUMIFS('03_Base_Vendas'!$I$4:$I$387, '03_Base_Vendas'!$A$4:$A$387, B$33),0)) -> 4592.5745 | C43: =(SUMIFS('04_Base_Despesas'!$D$4:$D$219, '04_Base_Despesas'!$A$4:$A$219, C$33, '04_Base_Despesas'!$B$4:$B$219, "marketing"))*(IFERROR(SUMIFS('03_Base_Vendas'!$I$4:$I$387, '03_Base_Vendas'!$A$4:$A$387, C$33, '03_Base_Vendas'!$B$4:$B$387, "marketplace")/SUMIFS('03_Base_Vendas'!$I$4:$I$387, '03_Base_Vendas'!$A$4:$A$387, C$33),0)) -> 2965.0511 | D43: =(SUMIFS('04_Base_Despesas'!$D$4:$D$219, '04_Base_Despesas'!$A$4:$A$219, D$33, '04_Base_Despesas'!$B$4:$B$219, "marketing"))*(IFERROR(SUMIFS('03_Base_Vendas'!$I$4:$I$387, '03_Base_Vendas'!$A$4:$A$387, D$33, '03_Base_Vendas'!$B$4:$B$387, "marketplace")/SUMIFS('03_Base_Vendas'!$I$4:$I$387, '03_Base_Vendas'!$A$4:$A$387, D$33),0)) -> 3029.5567 | E43: =(SUMIFS('04_Base_Despesas'!$D$4:$D$219, '04_Base_Despesas'!$A$4:$A$219, E$33, '04_Base_Despesas'!$B$4:$B$219, "marketing"))*(IFERROR(SUMIFS('03_Base_Vendas'!$I$4:$I$387, '03_Base_Vendas'!$A$4:$A$387, E$33, '03_Base_Vendas'!$B$4:$B$387, "marketplace")/SUMIFS('03_Base_Vendas'!$I$4:$I$387, '03_Base_Vendas'!$A$4:$A$387, E$33),0)) -> 3049.9694 | F43: =(SUMIFS('04_Base_Despesas'!$D$4:$D$219, '04_Base_Despesas'!$A$4:$A$219, F$33, '04_Base_Despesas'!$B$4:$B$219, "marketing"))*(IFERROR(SUMIFS('03_Base_Vendas'!$I$4:$I$387, '03_Base_Vendas'!$A$4:$A$387, F$33, '03_Base_Vendas'!$B$4:$B$387, "marketplace")/SUMIFS('03_Base_Vendas'!$I$4:$I$387, '03_Base_Vendas'!$A$4:$A$387, F$33),0)) -> 3870.2982 | G43: =(SUMIFS('04_Base_Despesas'!$D$4:$D$219, '04_Base_Despesas'!$A$4:$A$219, G$33, '04_Base_Despesas'!$B$4:$B$219, "marketing"))*(IFERROR(SUMIFS('03_Base_Vendas'!$I$4:$I$387, '03_Base_Vendas'!$A$4:$A$387, G$33, '03_Base_Vendas'!$B$4:$B$387, "marketplace")/SUMIFS('03_Base_Vendas'!$I$4:$I$387, '03_Base_Vendas'!$A$4:$A$387, G$33),0)) -> 3716.6604 | H43: =(SUMIFS('04_Base_Despesas'!$D$4:$D$219, '04_Base_Despesas'!$A$4:$A$219, H$33, '04_Base_Despesas'!$B$4:$B$219, "marketing"))*(IFERROR(SUMIFS('03_Base_Vendas'!$I$4:$I$387, '03_Base_Vendas'!$A$4:$A$387, H$33, '03_Base_Vendas'!$B$4:$B$387, "marketplace")/SUMIFS('03_Base_Vendas'!$I$4:$I$387, '03_Base_Vendas'!$A$4:$A$387, H$33),0)) -> 2125.2473 | I43: =(SUMIFS('04_Base_Despesas'!$D$4:$D$219, '04_Base_Despesas'!$A$4:$A$219, I$33, '04_Base_Despesas'!$B$4:$B$219, "marketing"))*(IFERROR(SUMIFS('03_Base_Vendas'!$I$4:$I$387, '03_Base_Vendas'!$A$4:$A$387, I$33, '03_Base_Vendas'!$B$4:$B$387, "marketplace")/SUMIFS('03_Base_Vendas'!$I$4:$I$387, '03_Base_Vendas'!$A$4:$A$387, I$33),0)) -> 2571.4912 | ... Y43: =(SUMIFS('04_Base_Despesas'!$D$4:$D$219, '04_Base_Despesas'!$A$4:$A$219, Y$33, '04_Base_Despesas'!$B$4:$B$219, "marketing"))*(IFERROR(SUMIFS('03_Base_Vendas'!$I$4:$I$387, '03_Base_Vendas'!$A$4:$A$387, Y$33, '03_Base_Vendas'!$B$4:$B$387, "marketplace")/SUMIFS('03_Base_Vendas'!$I$4:$I$387, '03_Base_Vendas'!$A$4:$A$387, Y$33),0)) -> 2349.285 | Z43: =SUM(B43:Y43) -> 86159.86
A44: (−) Logística | B44: =(SUMIFS('04_Base_Despesas'!$D$4:$D$219, '04_Base_Despesas'!$A$4:$A$219, B$33, '04_Base_Despesas'!$B$4:$B$219, "logistica"))*(IFERROR(SUMIFS('03_Base_Vendas'!$I$4:$I$387, '03_Base_Vendas'!$A$4:$A$387, B$33, '03_Base_Vendas'!$B$4:$B$387, "marketplace")/SUMIFS('03_Base_Vendas'!$I$4:$I$387, '03_Base_Vendas'!$A$4:$A$387, B$33),0)) -> 2314.4953 | C44: =(SUMIFS('04_Base_Despesas'!$D$4:$D$219, '04_Base_Despesas'!$A$4:$A$219, C$33, '04_Base_Despesas'!$B$4:$B$219, "logistica"))*(IFERROR(SUMIFS('03_Base_Vendas'!$I$4:$I$387, '03_Base_Vendas'!$A$4:$A$387, C$33, '03_Base_Vendas'!$B$4:$B$387, "marketplace")/SUMIFS('03_Base_Vendas'!$I$4:$I$387, '03_Base_Vendas'!$A$4:$A$387, C$33),0)) -> 2235.8473 | D44: =(SUMIFS('04_Base_Despesas'!$D$4:$D$219, '04_Base_Despesas'!$A$4:$A$219, D$33, '04_Base_Despesas'!$B$4:$B$219, "logistica"))*(IFERROR(SUMIFS('03_Base_Vendas'!$I$4:$I$387, '03_Base_Vendas'!$A$4:$A$387, D$33, '03_Base_Vendas'!$B$4:$B$387, "marketplace")/SUMIFS('03_Base_Vendas'!$I$4:$I$387, '03_Base_Vendas'!$A$4:$A$387, D$33),0)) -> 2691.3464 | E44: =(SUMIFS('04_Base_Despesas'!$D$4:$D$219, '04_Base_Despesas'!$A$4:$A$219, E$33, '04_Base_Despesas'!$B$4:$B$219, "logistica"))*(IFERROR(SUMIFS('03_Base_Vendas'!$I$4:$I$387, '03_Base_Vendas'!$A$4:$A$387, E$33, '03_Base_Vendas'!$B$4:$B$387, "marketplace")/SUMIFS('03_Base_Vendas'!$I$4:$I$387, '03_Base_Vendas'!$A$4:$A$387, E$33),0)) -> 2677.0482 | F44: =(SUMIFS('04_Base_Despesas'!$D$4:$D$219, '04_Base_Despesas'!$A$4:$A$219, F$33, '04_Base_Despesas'!$B$4:$B$219, "logistica"))*(IFERROR(SUMIFS('03_Base_Vendas'!$I$4:$I$387, '03_Base_Vendas'!$A$4:$A$387, F$33, '03_Base_Vendas'!$B$4:$B$387, "marketplace")/SUMIFS('03_Base_Vendas'!$I$4:$I$387, '03_Base_Vendas'!$A$4:$A$387, F$33),0)) -> 2232.8802 | G44: =(SUMIFS('04_Base_Despesas'!$D$4:$D$219, '04_Base_Despesas'!$A$4:$A$219, G$33, '04_Base_Despesas'!$B$4:$B$219, "logistica"))*(IFERROR(SUMIFS('03_Base_Vendas'!$I$4:$I$387, '03_Base_Vendas'!$A$4:$A$387, G$33, '03_Base_Vendas'!$B$4:$B$387, "marketplace")/SUMIFS('03_Base_Vendas'!$I$4:$I$387, '03_Base_Vendas'!$A$4:$A$387, G$33),0)) -> 1976.1618 | H44: =(SUMIFS('04_Base_Despesas'!$D$4:$D$219, '04_Base_Despesas'!$A$4:$A$219, H$33, '04_Base_Despesas'!$B$4:$B$219, "logistica"))*(IFERROR(SUMIFS('03_Base_Vendas'!$I$4:$I$387, '03_Base_Vendas'!$A$4:$A$387, H$33, '03_Base_Vendas'!$B$4:$B$387, "marketplace")/SUMIFS('03_Base_Vendas'!$I$4:$I$387, '03_Base_Vendas'!$A$4:$A$387, H$33),0)) -> 2294.2312 | I44: =(SUMIFS('04_Base_Despesas'!$D$4:$D$219, '04_Base_Despesas'!$A$4:$A$219, I$33, '04_Base_Despesas'!$B$4:$B$219, "logistica"))*(IFERROR(SUMIFS('03_Base_Vendas'!$I$4:$I$387, '03_Base_Vendas'!$A$4:$A$387, I$33, '03_Base_Vendas'!$B$4:$B$387, "marketplace")/SUMIFS('03_Base_Vendas'!$I$4:$I$387, '03_Base_Vendas'!$A$4:$A$387, I$33),0)) -> 2152.7968 | ... Y44: =(SUMIFS('04_Base_Despesas'!$D$4:$D$219, '04_Base_Despesas'!$A$4:$A$219, Y$33, '04_Base_Despesas'!$B$4:$B$219, "logistica"))*(IFERROR(SUMIFS('03_Base_Vendas'!$I$4:$I$387, '03_Base_Vendas'!$A$4:$A$387, Y$33, '03_Base_Vendas'!$B$4:$B$387, "marketplace")/SUMIFS('03_Base_Vendas'!$I$4:$I$387, '03_Base_Vendas'!$A$4:$A$387, Y$33),0)) -> 1546.6594 | Z44: =SUM(B44:Y44) -> 58479.427
A45: (−) Tecnologia | B45: =(SUMIFS('04_Base_Despesas'!$D$4:$D$219, '04_Base_Despesas'!$A$4:$A$219, B$33, '04_Base_Despesas'!$B$4:$B$219, "tecnologia"))*(IFERROR(SUMIFS('03_Base_Vendas'!$I$4:$I$387, '03_Base_Vendas'!$A$4:$A$387, B$33, '03_Base_Vendas'!$B$4:$B$387, "marketplace")/SUMIFS('03_Base_Vendas'!$I$4:$I$387, '03_Base_Vendas'!$A$4:$A$387, B$33),0)) -> 1728.0451 | C45: =(SUMIFS('04_Base_Despesas'!$D$4:$D$219, '04_Base_Despesas'!$A$4:$A$219, C$33, '04_Base_Despesas'!$B$4:$B$219, "tecnologia"))*(IFERROR(SUMIFS('03_Base_Vendas'!$I$4:$I$387, '03_Base_Vendas'!$A$4:$A$387, C$33, '03_Base_Vendas'!$B$4:$B$387, "marketplace")/SUMIFS('03_Base_Vendas'!$I$4:$I$387, '03_Base_Vendas'!$A$4:$A$387, C$33),0)) -> 1615.0607 | D45: =(SUMIFS('04_Base_Despesas'!$D$4:$D$219, '04_Base_Despesas'!$A$4:$A$219, D$33, '04_Base_Despesas'!$B$4:$B$219, "tecnologia"))*(IFERROR(SUMIFS('03_Base_Vendas'!$I$4:$I$387, '03_Base_Vendas'!$A$4:$A$387, D$33, '03_Base_Vendas'!$B$4:$B$387, "marketplace")/SUMIFS('03_Base_Vendas'!$I$4:$I$387, '03_Base_Vendas'!$A$4:$A$387, D$33),0)) -> 1833.8373 | E45: =(SUMIFS('04_Base_Despesas'!$D$4:$D$219, '04_Base_Despesas'!$A$4:$A$219, E$33, '04_Base_Despesas'!$B$4:$B$219, "tecnologia"))*(IFERROR(SUMIFS('03_Base_Vendas'!$I$4:$I$387, '03_Base_Vendas'!$A$4:$A$387, E$33, '03_Base_Vendas'!$B$4:$B$387, "marketplace")/SUMIFS('03_Base_Vendas'!$I$4:$I$387, '03_Base_Vendas'!$A$4:$A$387, E$33),0)) -> 1624.4434 | F45: =(SUMIFS('04_Base_Despesas'!$D$4:$D$219, '04_Base_Despesas'!$A$4:$A$219, F$33, '04_Base_Despesas'!$B$4:$B$219, "tecnologia"))*(IFERROR(SUMIFS('03_Base_Vendas'!$I$4:$I$387, '03_Base_Vendas'!$A$4:$A$387, F$33, '03_Base_Vendas'!$B$4:$B$387, "marketplace")/SUMIFS('03_Base_Vendas'!$I$4:$I$387, '03_Base_Vendas'!$A$4:$A$387, F$33),0)) -> 1491.3824 | G45: =(SUMIFS('04_Base_Despesas'!$D$4:$D$219, '04_Base_Despesas'!$A$4:$A$219, G$33, '04_Base_Despesas'!$B$4:$B$219, "tecnologia"))*(IFERROR(SUMIFS('03_Base_Vendas'!$I$4:$I$387, '03_Base_Vendas'!$A$4:$A$387, G$33, '03_Base_Vendas'!$B$4:$B$387, "marketplace")/SUMIFS('03_Base_Vendas'!$I$4:$I$387, '03_Base_Vendas'!$A$4:$A$387, G$33),0)) -> 1404.7562 | H45: =(SUMIFS('04_Base_Despesas'!$D$4:$D$219, '04_Base_Despesas'!$A$4:$A$219, H$33, '04_Base_Despesas'!$B$4:$B$219, "tecnologia"))*(IFERROR(SUMIFS('03_Base_Vendas'!$I$4:$I$387, '03_Base_Vendas'!$A$4:$A$387, H$33, '03_Base_Vendas'!$B$4:$B$387, "marketplace")/SUMIFS('03_Base_Vendas'!$I$4:$I$387, '03_Base_Vendas'!$A$4:$A$387, H$33),0)) -> 1415.1147 | I45: =(SUMIFS('04_Base_Despesas'!$D$4:$D$219, '04_Base_Despesas'!$A$4:$A$219, I$33, '04_Base_Despesas'!$B$4:$B$219, "tecnologia"))*(IFERROR(SUMIFS('03_Base_Vendas'!$I$4:$I$387, '03_Base_Vendas'!$A$4:$A$387, I$33, '03_Base_Vendas'!$B$4:$B$387, "marketplace")/SUMIFS('03_Base_Vendas'!$I$4:$I$387, '03_Base_Vendas'!$A$4:$A$387, I$33),0)) -> 1359.7957 | ... Y45: =(SUMIFS('04_Base_Despesas'!$D$4:$D$219, '04_Base_Despesas'!$A$4:$A$219, Y$33, '04_Base_Despesas'!$B$4:$B$219, "tecnologia"))*(IFERROR(SUMIFS('03_Base_Vendas'!$I$4:$I$387, '03_Base_Vendas'!$A$4:$A$387, Y$33, '03_Base_Vendas'!$B$4:$B$387, "marketplace")/SUMIFS('03_Base_Vendas'!$I$4:$I$387, '03_Base_Vendas'!$A$4:$A$387, Y$33),0)) -> 0 | Z45: =SUM(B45:Y45) -> 38156.121
A46: (−) Administrativo | B46: =(SUMIFS('04_Base_Despesas'!$D$4:$D$219, '04_Base_Despesas'!$A$4:$A$219, B$33, '04_Base_Despesas'!$B$4:$B$219, "administrativo"))*(IFERROR(SUMIFS('03_Base_Vendas'!$I$4:$I$387, '03_Base_Vendas'!$A$4:$A$387, B$33, '03_Base_Vendas'!$B$4:$B$387, "marketplace")/SUMIFS('03_Base_Vendas'!$I$4:$I$387, '03_Base_Vendas'!$A$4:$A$387, B$33),0)) -> 1057.4297 | C46: =(SUMIFS('04_Base_Despesas'!$D$4:$D$219, '04_Base_Despesas'!$A$4:$A$219, C$33, '04_Base_Despesas'!$B$4:$B$219, "administrativo"))*(IFERROR(SUMIFS('03_Base_Vendas'!$I$4:$I$387, '03_Base_Vendas'!$A$4:$A$387, C$33, '03_Base_Vendas'!$B$4:$B$387, "marketplace")/SUMIFS('03_Base_Vendas'!$I$4:$I$387, '03_Base_Vendas'!$A$4:$A$387, C$33),0)) -> 610.1817 | D46: =(SUMIFS('04_Base_Despesas'!$D$4:$D$219, '04_Base_Despesas'!$A$4:$A$219, D$33, '04_Base_Despesas'!$B$4:$B$219, "administrativo"))*(IFERROR(SUMIFS('03_Base_Vendas'!$I$4:$I$387, '03_Base_Vendas'!$A$4:$A$387, D$33, '03_Base_Vendas'!$B$4:$B$387, "marketplace")/SUMIFS('03_Base_Vendas'!$I$4:$I$387, '03_Base_Vendas'!$A$4:$A$387, D$33),0)) -> 689.09441 | E46: =(SUMIFS('04_Base_Despesas'!$D$4:$D$219, '04_Base_Despesas'!$A$4:$A$219, E$33, '04_Base_Despesas'!$B$4:$B$219, "administrativo"))*(IFERROR(SUMIFS('03_Base_Vendas'!$I$4:$I$387, '03_Base_Vendas'!$A$4:$A$387, E$33, '03_Base_Vendas'!$B$4:$B$387, "marketplace")/SUMIFS('03_Base_Vendas'!$I$4:$I$387, '03_Base_Vendas'!$A$4:$A$387, E$33),0)) -> 1123.5884 | F46: =(SUMIFS('04_Base_Despesas'!$D$4:$D$219, '04_Base_Despesas'!$A$4:$A$219, F$33, '04_Base_Despesas'!$B$4:$B$219, "administrativo"))*(IFERROR(SUMIFS('03_Base_Vendas'!$I$4:$I$387, '03_Base_Vendas'!$A$4:$A$387, F$33, '03_Base_Vendas'!$B$4:$B$387, "marketplace")/SUMIFS('03_Base_Vendas'!$I$4:$I$387, '03_Base_Vendas'!$A$4:$A$387, F$33),0)) -> 565.74904 | G46: =(SUMIFS('04_Base_Despesas'!$D$4:$D$219, '04_Base_Despesas'!$A$4:$A$219, G$33, '04_Base_Despesas'!$B$4:$B$219, "administrativo"))*(IFERROR(SUMIFS('03_Base_Vendas'!$I$4:$I$387, '03_Base_Vendas'!$A$4:$A$387, G$33, '03_Base_Vendas'!$B$4:$B$387, "marketplace")/SUMIFS('03_Base_Vendas'!$I$4:$I$387, '03_Base_Vendas'!$A$4:$A$387, G$33),0)) -> 524.12912 | H46: =(SUMIFS('04_Base_Despesas'!$D$4:$D$219, '04_Base_Despesas'!$A$4:$A$219, H$33, '04_Base_Despesas'!$B$4:$B$219, "administrativo"))*(IFERROR(SUMIFS('03_Base_Vendas'!$I$4:$I$387, '03_Base_Vendas'!$A$4:$A$387, H$33, '03_Base_Vendas'!$B$4:$B$387, "marketplace")/SUMIFS('03_Base_Vendas'!$I$4:$I$387, '03_Base_Vendas'!$A$4:$A$387, H$33),0)) -> 908.49421 | I46: =(SUMIFS('04_Base_Despesas'!$D$4:$D$219, '04_Base_Despesas'!$A$4:$A$219, I$33, '04_Base_Despesas'!$B$4:$B$219, "administrativo"))*(IFERROR(SUMIFS('03_Base_Vendas'!$I$4:$I$387, '03_Base_Vendas'!$A$4:$A$387, I$33, '03_Base_Vendas'!$B$4:$B$387, "marketplace")/SUMIFS('03_Base_Vendas'!$I$4:$I$387, '03_Base_Vendas'!$A$4:$A$387, I$33),0)) -> 500.31114 | ... Y46: =(SUMIFS('04_Base_Despesas'!$D$4:$D$219, '04_Base_Despesas'!$A$4:$A$219, Y$33, '04_Base_Despesas'!$B$4:$B$219, "administrativo"))*(IFERROR(SUMIFS('03_Base_Vendas'!$I$4:$I$387, '03_Base_Vendas'!$A$4:$A$387, Y$33, '03_Base_Vendas'!$B$4:$B$387, "marketplace")/SUMIFS('03_Base_Vendas'!$I$4:$I$387, '03_Base_Vendas'!$A$4:$A$387, Y$33),0)) -> 415.62699 | Z46: =SUM(B46:Y46) -> 18478.594
A47: (−) Outros | B47: =(SUMIFS('04_Base_Despesas'!$D$4:$D$219, '04_Base_Despesas'!$A$4:$A$219, B$33, '04_Base_Despesas'!$B$4:$B$219, "outros"))*(IFERROR(SUMIFS('03_Base_Vendas'!$I$4:$I$387, '03_Base_Vendas'!$A$4:$A$387, B$33, '03_Base_Vendas'!$B$4:$B$387, "marketplace")/SUMIFS('03_Base_Vendas'!$I$4:$I$387, '03_Base_Vendas'!$A$4:$A$387, B$33),0)) -> 203.66591 | C47: =(SUMIFS('04_Base_Despesas'!$D$4:$D$219, '04_Base_Despesas'!$A$4:$A$219, C$33, '04_Base_Despesas'!$B$4:$B$219, "outros"))*(IFERROR(SUMIFS('03_Base_Vendas'!$I$4:$I$387, '03_Base_Vendas'!$A$4:$A$387, C$33, '03_Base_Vendas'!$B$4:$B$387, "marketplace")/SUMIFS('03_Base_Vendas'!$I$4:$I$387, '03_Base_Vendas'!$A$4:$A$387, C$33),0)) -> 214.45934 | D47: =(SUMIFS('04_Base_Despesas'!$D$4:$D$219, '04_Base_Despesas'!$A$4:$A$219, D$33, '04_Base_Despesas'!$B$4:$B$219, "outros"))*(IFERROR(SUMIFS('03_Base_Vendas'!$I$4:$I$387, '03_Base_Vendas'!$A$4:$A$387, D$33, '03_Base_Vendas'!$B$4:$B$387, "marketplace")/SUMIFS('03_Base_Vendas'!$I$4:$I$387, '03_Base_Vendas'!$A$4:$A$387, D$33),0)) -> 238.37429 | E47: =(SUMIFS('04_Base_Despesas'!$D$4:$D$219, '04_Base_Despesas'!$A$4:$A$219, E$33, '04_Base_Despesas'!$B$4:$B$219, "outros"))*(IFERROR(SUMIFS('03_Base_Vendas'!$I$4:$I$387, '03_Base_Vendas'!$A$4:$A$387, E$33, '03_Base_Vendas'!$B$4:$B$387, "marketplace")/SUMIFS('03_Base_Vendas'!$I$4:$I$387, '03_Base_Vendas'!$A$4:$A$387, E$33),0)) -> 169.76065 | F47: =(SUMIFS('04_Base_Despesas'!$D$4:$D$219, '04_Base_Despesas'!$A$4:$A$219, F$33, '04_Base_Despesas'!$B$4:$B$219, "outros"))*(IFERROR(SUMIFS('03_Base_Vendas'!$I$4:$I$387, '03_Base_Vendas'!$A$4:$A$387, F$33, '03_Base_Vendas'!$B$4:$B$387, "marketplace")/SUMIFS('03_Base_Vendas'!$I$4:$I$387, '03_Base_Vendas'!$A$4:$A$387, F$33),0)) -> 175.09254 | G47: =(SUMIFS('04_Base_Despesas'!$D$4:$D$219, '04_Base_Despesas'!$A$4:$A$219, G$33, '04_Base_Despesas'!$B$4:$B$219, "outros"))*(IFERROR(SUMIFS('03_Base_Vendas'!$I$4:$I$387, '03_Base_Vendas'!$A$4:$A$387, G$33, '03_Base_Vendas'!$B$4:$B$387, "marketplace")/SUMIFS('03_Base_Vendas'!$I$4:$I$387, '03_Base_Vendas'!$A$4:$A$387, G$33),0)) -> 161.60368 | H47: =(SUMIFS('04_Base_Despesas'!$D$4:$D$219, '04_Base_Despesas'!$A$4:$A$219, H$33, '04_Base_Despesas'!$B$4:$B$219, "outros"))*(IFERROR(SUMIFS('03_Base_Vendas'!$I$4:$I$387, '03_Base_Vendas'!$A$4:$A$387, H$33, '03_Base_Vendas'!$B$4:$B$387, "marketplace")/SUMIFS('03_Base_Vendas'!$I$4:$I$387, '03_Base_Vendas'!$A$4:$A$387, H$33),0)) -> 210.32674 | I47: =(SUMIFS('04_Base_Despesas'!$D$4:$D$219, '04_Base_Despesas'!$A$4:$A$219, I$33, '04_Base_Despesas'!$B$4:$B$219, "outros"))*(IFERROR(SUMIFS('03_Base_Vendas'!$I$4:$I$387, '03_Base_Vendas'!$A$4:$A$387, I$33, '03_Base_Vendas'!$B$4:$B$387, "marketplace")/SUMIFS('03_Base_Vendas'!$I$4:$I$387, '03_Base_Vendas'!$A$4:$A$387, I$33),0)) -> 174.87075 | ... Y47: =(SUMIFS('04_Base_Despesas'!$D$4:$D$219, '04_Base_Despesas'!$A$4:$A$219, Y$33, '04_Base_Despesas'!$B$4:$B$219, "outros"))*(IFERROR(SUMIFS('03_Base_Vendas'!$I$4:$I$387, '03_Base_Vendas'!$A$4:$A$387, Y$33, '03_Base_Vendas'!$B$4:$B$387, "marketplace")/SUMIFS('03_Base_Vendas'!$I$4:$I$387, '03_Base_Vendas'!$A$4:$A$387, Y$33),0)) -> 107.80865 | Z47: =SUM(B47:Y47) -> 4996.8602
A48: Total Despesas Operac. | B48: =B41+B42+B43+B44+B45+B46+B47 -> 25375.756 | C48: =C41+C42+C43+C44+C45+C46+C47 -> 22681.364 | D48: =D41+D42+D43+D44+D45+D46+D47 -> 24917.042 | E48: =E41+E42+E43+E44+E45+E46+E47 -> 23184.446 | F48: =F41+F42+F43+F44+F45+F46+F47 -> 22249.407 | G48: =G41+G42+G43+G44+G45+G46+G47 -> 20379.78 | H48: =H41+H42+H43+H44+H45+H46+H47 -> 20066.363 | I48: =I41+I42+I43+I44+I45+I46+I47 -> 19047.808 | ... Y48: =Y41+Y42+Y43+Y44+Y45+Y46+Y47 -> 14495.729 | Z48: =SUM(B48:Y48) -> 563939.39
A49: EBITDA | B49: =B39-B48 -> -9284.9964 | C49: =C39-C48 -> -10752.194 | D49: =D39-D48 -> -8113.7019 | E49: =E39-E48 -> -9945.5156 | F49: =F39-F48 -> -4712.047 | G49: =G39-G48 -> -7340.6797 | H49: =H39-H48 -> -10208.043 | I49: =I39-I48 -> -9731.5277 | ... Y49: =Y39-Y48 -> -3670.8494 | Z49: =SUM(B49:Y49) -> -193463.93
A50: % Margem EBITDA | B50: =IFERROR(B49/B37,0) -> -0.24050301 | C50: =IFERROR(C49/C37,0) -> -0.35324126 | D50: =IFERROR(D49/D37,0) -> -0.19352897 | E50: =IFERROR(E49/E37,0) -> -0.28851499 | F50: =IFERROR(F49/F37,0) -> -0.10678291 | G50: =IFERROR(G49/G37,0) -> -0.20629993 | H50: =IFERROR(H49/H37,0) -> -0.36982674 | I50: =IFERROR(I49/I37,0) -> -0.37711806 | ... Y50: =IFERROR(Y49/Y37,0) -> -0.11365418 | Z50: =IFERROR($Z$49/$Z$37,0) -> -0.19794123
A51: (−) Depreciação | B51: =(SUMIFS('04_Base_Despesas'!$D$4:$D$219, '04_Base_Despesas'!$A$4:$A$219, B$33, '04_Base_Despesas'!$B$4:$B$219, "depreciacao"))*(IFERROR(SUMIFS('03_Base_Vendas'!$I$4:$I$387, '03_Base_Vendas'!$A$4:$A$387, B$33, '03_Base_Vendas'!$B$4:$B$387, "marketplace")/SUMIFS('03_Base_Vendas'!$I$4:$I$387, '03_Base_Vendas'!$A$4:$A$387, B$33),0)) -> 566.14352 | C51: =(SUMIFS('04_Base_Despesas'!$D$4:$D$219, '04_Base_Despesas'!$A$4:$A$219, C$33, '04_Base_Despesas'!$B$4:$B$219, "depreciacao"))*(IFERROR(SUMIFS('03_Base_Vendas'!$I$4:$I$387, '03_Base_Vendas'!$A$4:$A$387, C$33, '03_Base_Vendas'!$B$4:$B$387, "marketplace")/SUMIFS('03_Base_Vendas'!$I$4:$I$387, '03_Base_Vendas'!$A$4:$A$387, C$33),0)) -> 536.9599 | D51: =(SUMIFS('04_Base_Despesas'!$D$4:$D$219, '04_Base_Despesas'!$A$4:$A$219, D$33, '04_Base_Despesas'!$B$4:$B$219, "depreciacao"))*(IFERROR(SUMIFS('03_Base_Vendas'!$I$4:$I$387, '03_Base_Vendas'!$A$4:$A$387, D$33, '03_Base_Vendas'!$B$4:$B$387, "marketplace")/SUMIFS('03_Base_Vendas'!$I$4:$I$387, '03_Base_Vendas'!$A$4:$A$387, D$33),0)) -> 606.40032 | E51: =(SUMIFS('04_Base_Despesas'!$D$4:$D$219, '04_Base_Despesas'!$A$4:$A$219, E$33, '04_Base_Despesas'!$B$4:$B$219, "depreciacao"))*(IFERROR(SUMIFS('03_Base_Vendas'!$I$4:$I$387, '03_Base_Vendas'!$A$4:$A$387, E$33, '03_Base_Vendas'!$B$4:$B$387, "marketplace")/SUMIFS('03_Base_Vendas'!$I$4:$I$387, '03_Base_Vendas'!$A$4:$A$387, E$33),0)) -> 542.40322 | F51: =(SUMIFS('04_Base_Despesas'!$D$4:$D$219, '04_Base_Despesas'!$A$4:$A$219, F$33, '04_Base_Despesas'!$B$4:$B$219, "depreciacao"))*(IFERROR(SUMIFS('03_Base_Vendas'!$I$4:$I$387, '03_Base_Vendas'!$A$4:$A$387, F$33, '03_Base_Vendas'!$B$4:$B$387, "marketplace")/SUMIFS('03_Base_Vendas'!$I$4:$I$387, '03_Base_Vendas'!$A$4:$A$387, F$33),0)) -> 497.85689 | G51: =(SUMIFS('04_Base_Despesas'!$D$4:$D$219, '04_Base_Despesas'!$A$4:$A$219, G$33, '04_Base_Despesas'!$B$4:$B$219, "depreciacao"))*(IFERROR(SUMIFS('03_Base_Vendas'!$I$4:$I$387, '03_Base_Vendas'!$A$4:$A$387, G$33, '03_Base_Vendas'!$B$4:$B$387, "marketplace")/SUMIFS('03_Base_Vendas'!$I$4:$I$387, '03_Base_Vendas'!$A$4:$A$387, G$33),0)) -> 461.23153 | H51: =(SUMIFS('04_Base_Despesas'!$D$4:$D$219, '04_Base_Despesas'!$A$4:$A$219, H$33, '04_Base_Despesas'!$B$4:$B$219, "depreciacao"))*(IFERROR(SUMIFS('03_Base_Vendas'!$I$4:$I$387, '03_Base_Vendas'!$A$4:$A$387, H$33, '03_Base_Vendas'!$B$4:$B$387, "marketplace")/SUMIFS('03_Base_Vendas'!$I$4:$I$387, '03_Base_Vendas'!$A$4:$A$387, H$33),0)) -> 469.97312 | I51: =(SUMIFS('04_Base_Despesas'!$D$4:$D$219, '04_Base_Despesas'!$A$4:$A$219, I$33, '04_Base_Despesas'!$B$4:$B$219, "depreciacao"))*(IFERROR(SUMIFS('03_Base_Vendas'!$I$4:$I$387, '03_Base_Vendas'!$A$4:$A$387, I$33, '03_Base_Vendas'!$B$4:$B$387, "marketplace")/SUMIFS('03_Base_Vendas'!$I$4:$I$387, '03_Base_Vendas'!$A$4:$A$387, I$33),0)) -> 440.2738 | ... Y51: =(SUMIFS('04_Base_Despesas'!$D$4:$D$219, '04_Base_Despesas'!$A$4:$A$219, Y$33, '04_Base_Despesas'!$B$4:$B$219, "depreciacao"))*(IFERROR(SUMIFS('03_Base_Vendas'!$I$4:$I$387, '03_Base_Vendas'!$A$4:$A$387, Y$33, '03_Base_Vendas'!$B$4:$B$387, "marketplace")/SUMIFS('03_Base_Vendas'!$I$4:$I$387, '03_Base_Vendas'!$A$4:$A$387, Y$33),0)) -> 365.75175 | Z51: =SUM(B51:Y51) -> 12933.768
A52: EBIT | B52: =B49-B51 -> -9851.1399 | C52: =C49-C51 -> -11289.154 | D52: =D49-D51 -> -8720.1022 | E52: =E49-E51 -> -10487.919 | F52: =F49-F51 -> -5209.9039 | G52: =G49-G51 -> -7801.9113 | H52: =H49-H51 -> -10678.016 | I52: =I49-I51 -> -10171.802 | ... Y52: =Y49-Y51 -> -4036.6012 | Z52: =SUM(B52:Y52) -> -206397.7
A53: (−) Despesas Financeiras | B53: =(SUMIFS('04_Base_Despesas'!$D$4:$D$219, '04_Base_Despesas'!$A$4:$A$219, B$33, '04_Base_Despesas'!$B$4:$B$219, "financeiro"))*(IFERROR(SUMIFS('03_Base_Vendas'!$I$4:$I$387, '03_Base_Vendas'!$A$4:$A$387, B$33, '03_Base_Vendas'!$B$4:$B$387, "marketplace")/SUMIFS('03_Base_Vendas'!$I$4:$I$387, '03_Base_Vendas'!$A$4:$A$387, B$33),0)) -> 351.38115 | C53: =(SUMIFS('04_Base_Despesas'!$D$4:$D$219, '04_Base_Despesas'!$A$4:$A$219, C$33, '04_Base_Despesas'!$B$4:$B$219, "financeiro"))*(IFERROR(SUMIFS('03_Base_Vendas'!$I$4:$I$387, '03_Base_Vendas'!$A$4:$A$387, C$33, '03_Base_Vendas'!$B$4:$B$387, "marketplace")/SUMIFS('03_Base_Vendas'!$I$4:$I$387, '03_Base_Vendas'!$A$4:$A$387, C$33),0)) -> 329.88131 | D53: =(SUMIFS('04_Base_Despesas'!$D$4:$D$219, '04_Base_Despesas'!$A$4:$A$219, D$33, '04_Base_Despesas'!$B$4:$B$219, "financeiro"))*(IFERROR(SUMIFS('03_Base_Vendas'!$I$4:$I$387, '03_Base_Vendas'!$A$4:$A$387, D$33, '03_Base_Vendas'!$B$4:$B$387, "marketplace")/SUMIFS('03_Base_Vendas'!$I$4:$I$387, '03_Base_Vendas'!$A$4:$A$387, D$33),0)) -> 370.95606 | E53: =(SUMIFS('04_Base_Despesas'!$D$4:$D$219, '04_Base_Despesas'!$A$4:$A$219, E$33, '04_Base_Despesas'!$B$4:$B$219, "financeiro"))*(IFERROR(SUMIFS('03_Base_Vendas'!$I$4:$I$387, '03_Base_Vendas'!$A$4:$A$387, E$33, '03_Base_Vendas'!$B$4:$B$387, "marketplace")/SUMIFS('03_Base_Vendas'!$I$4:$I$387, '03_Base_Vendas'!$A$4:$A$387, E$33),0)) -> 320.04401 | F53: =(SUMIFS('04_Base_Despesas'!$D$4:$D$219, '04_Base_Despesas'!$A$4:$A$219, F$33, '04_Base_Despesas'!$B$4:$B$219, "financeiro"))*(IFERROR(SUMIFS('03_Base_Vendas'!$I$4:$I$387, '03_Base_Vendas'!$A$4:$A$387, F$33, '03_Base_Vendas'!$B$4:$B$387, "marketplace")/SUMIFS('03_Base_Vendas'!$I$4:$I$387, '03_Base_Vendas'!$A$4:$A$387, F$33),0)) -> 306.19017 | G53: =(SUMIFS('04_Base_Despesas'!$D$4:$D$219, '04_Base_Despesas'!$A$4:$A$219, G$33, '04_Base_Despesas'!$B$4:$B$219, "financeiro"))*(IFERROR(SUMIFS('03_Base_Vendas'!$I$4:$I$387, '03_Base_Vendas'!$A$4:$A$387, G$33, '03_Base_Vendas'!$B$4:$B$387, "marketplace")/SUMIFS('03_Base_Vendas'!$I$4:$I$387, '03_Base_Vendas'!$A$4:$A$387, G$33),0)) -> 268.03334 | H53: =(SUMIFS('04_Base_Despesas'!$D$4:$D$219, '04_Base_Despesas'!$A$4:$A$219, H$33, '04_Base_Despesas'!$B$4:$B$219, "financeiro"))*(IFERROR(SUMIFS('03_Base_Vendas'!$I$4:$I$387, '03_Base_Vendas'!$A$4:$A$387, H$33, '03_Base_Vendas'!$B$4:$B$387, "marketplace")/SUMIFS('03_Base_Vendas'!$I$4:$I$387, '03_Base_Vendas'!$A$4:$A$387, H$33),0)) -> 1163.4002 | I53: =(SUMIFS('04_Base_Despesas'!$D$4:$D$219, '04_Base_Despesas'!$A$4:$A$219, I$33, '04_Base_Despesas'!$B$4:$B$219, "financeiro"))*(IFERROR(SUMIFS('03_Base_Vendas'!$I$4:$I$387, '03_Base_Vendas'!$A$4:$A$387, I$33, '03_Base_Vendas'!$B$4:$B$387, "marketplace")/SUMIFS('03_Base_Vendas'!$I$4:$I$387, '03_Base_Vendas'!$A$4:$A$387, I$33),0)) -> 262.8995 | ... Y53: =(SUMIFS('04_Base_Despesas'!$D$4:$D$219, '04_Base_Despesas'!$A$4:$A$219, Y$33, '04_Base_Despesas'!$B$4:$B$219, "financeiro"))*(IFERROR(SUMIFS('03_Base_Vendas'!$I$4:$I$387, '03_Base_Vendas'!$A$4:$A$387, Y$33, '03_Base_Vendas'!$B$4:$B$387, "marketplace")/SUMIFS('03_Base_Vendas'!$I$4:$I$387, '03_Base_Vendas'!$A$4:$A$387, Y$33),0)) -> 230.06783 | Z53: =SUM(B53:Y53) -> 8589.5035
A54: Resultado Operacional | B54: =B52-B53 -> -10202.521 | C54: =C52-C53 -> -11619.035 | D54: =D52-D53 -> -9091.0583 | E54: =E52-E53 -> -10807.963 | F54: =F52-F53 -> -5516.0941 | G54: =G52-G53 -> -8069.9446 | H54: =H52-H53 -> -11841.416 | I54: =I52-I53 -> -10434.701 | ... Y54: =Y52-Y53 -> -4266.669 | Z54: =SUM(B54:Y54) -> -214987.21
A55: % Margem Operacional | B55: =IFERROR(B54/B37,0) -> -0.26426904 | C55: =IFERROR(C54/C37,0) -> -0.38171955 | D55: =IFERROR(D54/D37,0) -> -0.21684099 | E55: =IFERROR(E54/E37,0) -> -0.3135342 | F55: =IFERROR(F54/F37,0) -> -0.12500397 | G55: =IFERROR(G54/G37,0) -> -0.22679494 | H55: =IFERROR(H54/H37,0) -> -0.42900215 | I55: =IFERROR(I54/I37,0) -> -0.40436757 | ... Y55: =IFERROR(Y54/Y37,0) -> -0.13210152 | Z55: =IFERROR($Z$54/$Z$37,0) -> -0.21996261
A58: Canal: Franquia
A59: Item | B59: 2023-01 | C59: 2023-02 | D59: 2023-03 | E59: 2023-04 | F59: 2023-05 | G59: 2023-06 | H59: 2023-07 | I59: 2023-08 | J59: 2023-09 | K59: 2023-10 | L59: 2023-11 | M59: 2023-12 | N59: 2024-01 | O59: 2024-02 | P59: 2024-03 | Q59: 2024-04 | R59: 2024-05 | S59: 2024-06 | T59: 2024-07 | U59: 2024-08 | V59: 2024-09 | W59: 2024-10 | X59: 2024-11 | Y59: 2024-12 | Z59: Total 24m
A60: Receita Bruta | B60: =SUMIFS('03_Base_Vendas'!$F$4:$F$387, '03_Base_Vendas'!$A$4:$A$387, B$59, '03_Base_Vendas'!$B$4:$B$387, "franquia") -> 39661.72 | C60: =SUMIFS('03_Base_Vendas'!$F$4:$F$387, '03_Base_Vendas'!$A$4:$A$387, C$59, '03_Base_Vendas'!$B$4:$B$387, "franquia") -> 21900.04 | D60: =SUMIFS('03_Base_Vendas'!$F$4:$F$387, '03_Base_Vendas'!$A$4:$A$387, D$59, '03_Base_Vendas'!$B$4:$B$387, "franquia") -> 28169.75 | E60: =SUMIFS('03_Base_Vendas'!$F$4:$F$387, '03_Base_Vendas'!$A$4:$A$387, E$59, '03_Base_Vendas'!$B$4:$B$387, "franquia") -> 26518.34 | F60: =SUMIFS('03_Base_Vendas'!$F$4:$F$387, '03_Base_Vendas'!$A$4:$A$387, F$59, '03_Base_Vendas'!$B$4:$B$387, "franquia") -> 38282.55 | G60: =SUMIFS('03_Base_Vendas'!$F$4:$F$387, '03_Base_Vendas'!$A$4:$A$387, G$59, '03_Base_Vendas'!$B$4:$B$387, "franquia") -> 32940.29 | H60: =SUMIFS('03_Base_Vendas'!$F$4:$F$387, '03_Base_Vendas'!$A$4:$A$387, H$59, '03_Base_Vendas'!$B$4:$B$387, "franquia") -> 25149.64 | I60: =SUMIFS('03_Base_Vendas'!$F$4:$F$387, '03_Base_Vendas'!$A$4:$A$387, I$59, '03_Base_Vendas'!$B$4:$B$387, "franquia") -> 31149.06 | ... Y60: =SUMIFS('03_Base_Vendas'!$F$4:$F$387, '03_Base_Vendas'!$A$4:$A$387, Y$59, '03_Base_Vendas'!$B$4:$B$387, "franquia") -> 45474.45 | Z60: =SUM(B60:Y60) -> 807258.09
A61: (−) Devoluções | B61: =SUMIFS('03_Base_Vendas'!$G$4:$G$387, '03_Base_Vendas'!$A$4:$A$387, B$59, '03_Base_Vendas'!$B$4:$B$387, "franquia") -> 2639.97 | C61: =SUMIFS('03_Base_Vendas'!$G$4:$G$387, '03_Base_Vendas'!$A$4:$A$387, C$59, '03_Base_Vendas'!$B$4:$B$387, "franquia") -> 1461.07 | D61: =SUMIFS('03_Base_Vendas'!$G$4:$G$387, '03_Base_Vendas'!$A$4:$A$387, D$59, '03_Base_Vendas'!$B$4:$B$387, "franquia") -> 2139.37 | E61: =SUMIFS('03_Base_Vendas'!$G$4:$G$387, '03_Base_Vendas'!$A$4:$A$387, E$59, '03_Base_Vendas'!$B$4:$B$387, "franquia") -> 1331.46 | F61: =SUMIFS('03_Base_Vendas'!$G$4:$G$387, '03_Base_Vendas'!$A$4:$A$387, F$59, '03_Base_Vendas'!$B$4:$B$387, "franquia") -> 1669.02 | G61: =SUMIFS('03_Base_Vendas'!$G$4:$G$387, '03_Base_Vendas'!$A$4:$A$387, G$59, '03_Base_Vendas'!$B$4:$B$387, "franquia") -> 435.63 | H61: =SUMIFS('03_Base_Vendas'!$G$4:$G$387, '03_Base_Vendas'!$A$4:$A$387, H$59, '03_Base_Vendas'!$B$4:$B$387, "franquia") -> 0 | I61: =SUMIFS('03_Base_Vendas'!$G$4:$G$387, '03_Base_Vendas'!$A$4:$A$387, I$59, '03_Base_Vendas'!$B$4:$B$387, "franquia") -> 1147.7 | ... Y61: =SUMIFS('03_Base_Vendas'!$G$4:$G$387, '03_Base_Vendas'!$A$4:$A$387, Y$59, '03_Base_Vendas'!$B$4:$B$387, "franquia") -> 1120.94 | Z61: =SUM(B61:Y61) -> 36836.21
A62: (−) Comissões de canal | B62: =SUMIFS('03_Base_Vendas'!$H$4:$H$387, '03_Base_Vendas'!$A$4:$A$387, B$59, '03_Base_Vendas'!$B$4:$B$387, "franquia") -> 4776.3 | C62: =SUMIFS('03_Base_Vendas'!$H$4:$H$387, '03_Base_Vendas'!$A$4:$A$387, C$59, '03_Base_Vendas'!$B$4:$B$387, "franquia") -> 2625.81 | D62: =SUMIFS('03_Base_Vendas'!$H$4:$H$387, '03_Base_Vendas'!$A$4:$A$387, D$59, '03_Base_Vendas'!$B$4:$B$387, "franquia") -> 3363.98 | E62: =SUMIFS('03_Base_Vendas'!$H$4:$H$387, '03_Base_Vendas'!$A$4:$A$387, E$59, '03_Base_Vendas'!$B$4:$B$387, "franquia") -> 3183.4 | F62: =SUMIFS('03_Base_Vendas'!$H$4:$H$387, '03_Base_Vendas'!$A$4:$A$387, F$59, '03_Base_Vendas'!$B$4:$B$387, "franquia") -> 4593.22 | G62: =SUMIFS('03_Base_Vendas'!$H$4:$H$387, '03_Base_Vendas'!$A$4:$A$387, G$59, '03_Base_Vendas'!$B$4:$B$387, "franquia") -> 3952.55 | H62: =SUMIFS('03_Base_Vendas'!$H$4:$H$387, '03_Base_Vendas'!$A$4:$A$387, H$59, '03_Base_Vendas'!$B$4:$B$387, "franquia") -> 3033.1 | I62: =SUMIFS('03_Base_Vendas'!$H$4:$H$387, '03_Base_Vendas'!$A$4:$A$387, I$59, '03_Base_Vendas'!$B$4:$B$387, "franquia") -> 3739.32 | ... Y62: =SUMIFS('03_Base_Vendas'!$H$4:$H$387, '03_Base_Vendas'!$A$4:$A$387, Y$59, '03_Base_Vendas'!$B$4:$B$387, "franquia") -> 5493.28 | Z62: =SUM(B62:Y62) -> 96801.34
A63: Receita Líquida | B63: =B60-B61-B62 -> 32245.45 | C63: =C60-C61-C62 -> 17813.16 | D63: =D60-D61-D62 -> 22666.4 | E63: =E60-E61-E62 -> 22003.48 | F63: =F60-F61-F62 -> 32020.31 | G63: =G60-G61-G62 -> 28552.11 | H63: =H60-H61-H62 -> 22116.54 | I63: =I60-I61-I62 -> 26262.04 | ... Y63: =Y60-Y61-Y62 -> 38860.23 | Z63: =SUM(B63:Y63) -> 673620.54
A64: (−) CMV | B64: =SUMIFS('03_Base_Vendas'!$J$4:$J$387, '03_Base_Vendas'!$A$4:$A$387, B$59, '03_Base_Vendas'!$B$4:$B$387, "franquia") -> 18840.12 | C64: =SUMIFS('03_Base_Vendas'!$J$4:$J$387, '03_Base_Vendas'!$A$4:$A$387, C$59, '03_Base_Vendas'!$B$4:$B$387, "franquia") -> 10527.26 | D64: =SUMIFS('03_Base_Vendas'!$J$4:$J$387, '03_Base_Vendas'!$A$4:$A$387, D$59, '03_Base_Vendas'!$B$4:$B$387, "franquia") -> 13664.45 | E64: =SUMIFS('03_Base_Vendas'!$J$4:$J$387, '03_Base_Vendas'!$A$4:$A$387, E$59, '03_Base_Vendas'!$B$4:$B$387, "franquia") -> 12487.76 | F64: =SUMIFS('03_Base_Vendas'!$J$4:$J$387, '03_Base_Vendas'!$A$4:$A$387, F$59, '03_Base_Vendas'!$B$4:$B$387, "franquia") -> 18045.24 | G64: =SUMIFS('03_Base_Vendas'!$J$4:$J$387, '03_Base_Vendas'!$A$4:$A$387, G$59, '03_Base_Vendas'!$B$4:$B$387, "franquia") -> 16114.41 | H64: =SUMIFS('03_Base_Vendas'!$J$4:$J$387, '03_Base_Vendas'!$A$4:$A$387, H$59, '03_Base_Vendas'!$B$4:$B$387, "franquia") -> 12305.35 | I64: =SUMIFS('03_Base_Vendas'!$J$4:$J$387, '03_Base_Vendas'!$A$4:$A$387, I$59, '03_Base_Vendas'!$B$4:$B$387, "franquia") -> 14445.64 | ... Y64: =SUMIFS('03_Base_Vendas'!$J$4:$J$387, '03_Base_Vendas'!$A$4:$A$387, Y$59, '03_Base_Vendas'!$B$4:$B$387, "franquia") -> 21579.89 | Z64: =SUM(B64:Y64) -> 387974.06
A65: Margem de Contribuição | B65: =B63-B64 -> 13405.33 | C65: =C63-C64 -> 7285.9 | D65: =D63-D64 -> 9001.95 | E65: =E63-E64 -> 9515.72 | F65: =F63-F64 -> 13975.07 | G65: =G63-G64 -> 12437.7 | H65: =H63-H64 -> 9811.19 | I65: =I63-I64 -> 11816.4 | ... Y65: =Y63-Y64 -> 17280.34 | Z65: =SUM(B65:Y65) -> 285646.48
A66: % Margem de Contribuição | B66: =IFERROR(B65/B63,0) -> 0.4157278 | C66: =IFERROR(C65/C63,0) -> 0.40901783 | D66: =IFERROR(D65/D63,0) -> 0.39714953 | E66: =IFERROR(E65/E63,0) -> 0.43246432 | F66: =IFERROR(F65/F63,0) -> 0.43644393 | G66: =IFERROR(G65/G63,0) -> 0.43561404 | H66: =IFERROR(H65/H63,0) -> 0.44361324 | I66: =IFERROR(I65/I63,0) -> 0.4499422 | ... Y66: =IFERROR(Y65/Y63,0) -> 0.4446793 | Z66: =IFERROR($Z$65/$Z$63,0) -> 0.42404657
A67: (−) Pessoal | B67: =(SUMIFS('04_Base_Despesas'!$D$4:$D$219, '04_Base_Despesas'!$A$4:$A$219, B$59, '04_Base_Despesas'!$B$4:$B$219, "pessoal"))*(IFERROR(SUMIFS('03_Base_Vendas'!$I$4:$I$387, '03_Base_Vendas'!$A$4:$A$387, B$59, '03_Base_Vendas'!$B$4:$B$387, "franquia")/SUMIFS('03_Base_Vendas'!$I$4:$I$387, '03_Base_Vendas'!$A$4:$A$387, B$59),0)) -> 10887.103 | C67: =(SUMIFS('04_Base_Despesas'!$D$4:$D$219, '04_Base_Despesas'!$A$4:$A$219, C$59, '04_Base_Despesas'!$B$4:$B$219, "pessoal"))*(IFERROR(SUMIFS('03_Base_Vendas'!$I$4:$I$387, '03_Base_Vendas'!$A$4:$A$387, C$59, '03_Base_Vendas'!$B$4:$B$387, "franquia")/SUMIFS('03_Base_Vendas'!$I$4:$I$387, '03_Base_Vendas'!$A$4:$A$387, C$59),0)) -> 7445.1457 | D67: =(SUMIFS('04_Base_Despesas'!$D$4:$D$219, '04_Base_Despesas'!$A$4:$A$219, D$59, '04_Base_Despesas'!$B$4:$B$219, "pessoal"))*(IFERROR(SUMIFS('03_Base_Vendas'!$I$4:$I$387, '03_Base_Vendas'!$A$4:$A$387, D$59, '03_Base_Vendas'!$B$4:$B$387, "franquia")/SUMIFS('03_Base_Vendas'!$I$4:$I$387, '03_Base_Vendas'!$A$4:$A$387, D$59),0)) -> 7469.6528 | E67: =(SUMIFS('04_Base_Despesas'!$D$4:$D$219, '04_Base_Despesas'!$A$4:$A$219, E$59, '04_Base_Despesas'!$B$4:$B$219, "pessoal"))*(IFERROR(SUMIFS('03_Base_Vendas'!$I$4:$I$387, '03_Base_Vendas'!$A$4:$A$387, E$59, '03_Base_Vendas'!$B$4:$B$387, "franquia")/SUMIFS('03_Base_Vendas'!$I$4:$I$387, '03_Base_Vendas'!$A$4:$A$387, E$59),0)) -> 7785.7554 | F67: =(SUMIFS('04_Base_Despesas'!$D$4:$D$219, '04_Base_Despesas'!$A$4:$A$219, F$59, '04_Base_Despesas'!$B$4:$B$219, "pessoal"))*(IFERROR(SUMIFS('03_Base_Vendas'!$I$4:$I$387, '03_Base_Vendas'!$A$4:$A$387, F$59, '03_Base_Vendas'!$B$4:$B$387, "franquia")/SUMIFS('03_Base_Vendas'!$I$4:$I$387, '03_Base_Vendas'!$A$4:$A$387, F$59),0)) -> 8536.4745 | G67: =(SUMIFS('04_Base_Despesas'!$D$4:$D$219, '04_Base_Despesas'!$A$4:$A$219, G$59, '04_Base_Despesas'!$B$4:$B$219, "pessoal"))*(IFERROR(SUMIFS('03_Base_Vendas'!$I$4:$I$387, '03_Base_Vendas'!$A$4:$A$387, G$59, '03_Base_Vendas'!$B$4:$B$387, "franquia")/SUMIFS('03_Base_Vendas'!$I$4:$I$387, '03_Base_Vendas'!$A$4:$A$387, G$59),0)) -> 8509.4716 | H67: =(SUMIFS('04_Base_Despesas'!$D$4:$D$219, '04_Base_Despesas'!$A$4:$A$219, H$59, '04_Base_Despesas'!$B$4:$B$219, "pessoal"))*(IFERROR(SUMIFS('03_Base_Vendas'!$I$4:$I$387, '03_Base_Vendas'!$A$4:$A$387, H$59, '03_Base_Vendas'!$B$4:$B$387, "franquia")/SUMIFS('03_Base_Vendas'!$I$4:$I$387, '03_Base_Vendas'!$A$4:$A$387, H$59),0)) -> 8880.7639 | I67: =(SUMIFS('04_Base_Despesas'!$D$4:$D$219, '04_Base_Despesas'!$A$4:$A$219, I$59, '04_Base_Despesas'!$B$4:$B$219, "pessoal"))*(IFERROR(SUMIFS('03_Base_Vendas'!$I$4:$I$387, '03_Base_Vendas'!$A$4:$A$387, I$59, '03_Base_Vendas'!$B$4:$B$387, "franquia")/SUMIFS('03_Base_Vendas'!$I$4:$I$387, '03_Base_Vendas'!$A$4:$A$387, I$59),0)) -> 10571.338 | ... Y67: =(SUMIFS('04_Base_Despesas'!$D$4:$D$219, '04_Base_Despesas'!$A$4:$A$219, Y$59, '04_Base_Despesas'!$B$4:$B$219, "pessoal"))*(IFERROR(SUMIFS('03_Base_Vendas'!$I$4:$I$387, '03_Base_Vendas'!$A$4:$A$387, Y$59, '03_Base_Vendas'!$B$4:$B$387, "franquia")/SUMIFS('03_Base_Vendas'!$I$4:$I$387, '03_Base_Vendas'!$A$4:$A$387, Y$59),0)) -> 10223.228 | Z67: =SUM(B67:Y67) -> 209515.29
A68: (−) Aluguel | B68: =(SUMIFS('04_Base_Despesas'!$D$4:$D$219, '04_Base_Despesas'!$A$4:$A$219, B$59, '04_Base_Despesas'!$B$4:$B$219, "aluguel"))*(IFERROR(SUMIFS('03_Base_Vendas'!$I$4:$I$387, '03_Base_Vendas'!$A$4:$A$387, B$59, '03_Base_Vendas'!$B$4:$B$387, "franquia")/SUMIFS('03_Base_Vendas'!$I$4:$I$387, '03_Base_Vendas'!$A$4:$A$387, B$59),0)) -> 2041.9125 | C68: =(SUMIFS('04_Base_Despesas'!$D$4:$D$219, '04_Base_Despesas'!$A$4:$A$219, C$59, '04_Base_Despesas'!$B$4:$B$219, "aluguel"))*(IFERROR(SUMIFS('03_Base_Vendas'!$I$4:$I$387, '03_Base_Vendas'!$A$4:$A$387, C$59, '03_Base_Vendas'!$B$4:$B$387, "franquia")/SUMIFS('03_Base_Vendas'!$I$4:$I$387, '03_Base_Vendas'!$A$4:$A$387, C$59),0)) -> 1356.932 | D68: =(SUMIFS('04_Base_Despesas'!$D$4:$D$219, '04_Base_Despesas'!$A$4:$A$219, D$59, '04_Base_Despesas'!$B$4:$B$219, "aluguel"))*(IFERROR(SUMIFS('03_Base_Vendas'!$I$4:$I$387, '03_Base_Vendas'!$A$4:$A$387, D$59, '03_Base_Vendas'!$B$4:$B$387, "franquia")/SUMIFS('03_Base_Vendas'!$I$4:$I$387, '03_Base_Vendas'!$A$4:$A$387, D$59),0)) -> 1415.7019 | E68: =(SUMIFS('04_Base_Despesas'!$D$4:$D$219, '04_Base_Despesas'!$A$4:$A$219, E$59, '04_Base_Despesas'!$B$4:$B$219, "aluguel"))*(IFERROR(SUMIFS('03_Base_Vendas'!$I$4:$I$387, '03_Base_Vendas'!$A$4:$A$387, E$59, '03_Base_Vendas'!$B$4:$B$387, "franquia")/SUMIFS('03_Base_Vendas'!$I$4:$I$387, '03_Base_Vendas'!$A$4:$A$387, E$59),0)) -> 1495.0565 | F68: =(SUMIFS('04_Base_Despesas'!$D$4:$D$219, '04_Base_Despesas'!$A$4:$A$219, F$59, '04_Base_Despesas'!$B$4:$B$219, "aluguel"))*(IFERROR(SUMIFS('03_Base_Vendas'!$I$4:$I$387, '03_Base_Vendas'!$A$4:$A$387, F$59, '03_Base_Vendas'!$B$4:$B$387, "franquia")/SUMIFS('03_Base_Vendas'!$I$4:$I$387, '03_Base_Vendas'!$A$4:$A$387, F$59),0)) -> 1560.0018 | G68: =(SUMIFS('04_Base_Despesas'!$D$4:$D$219, '04_Base_Despesas'!$A$4:$A$219, G$59, '04_Base_Despesas'!$B$4:$B$219, "aluguel"))*(IFERROR(SUMIFS('03_Base_Vendas'!$I$4:$I$387, '03_Base_Vendas'!$A$4:$A$387, G$59, '03_Base_Vendas'!$B$4:$B$387, "franquia")/SUMIFS('03_Base_Vendas'!$I$4:$I$387, '03_Base_Vendas'!$A$4:$A$387, G$59),0)) -> 1598.1697 | H68: =(SUMIFS('04_Base_Despesas'!$D$4:$D$219, '04_Base_Despesas'!$A$4:$A$219, H$59, '04_Base_Despesas'!$B$4:$B$219, "aluguel"))*(IFERROR(SUMIFS('03_Base_Vendas'!$I$4:$I$387, '03_Base_Vendas'!$A$4:$A$387, H$59, '03_Base_Vendas'!$B$4:$B$387, "franquia")/SUMIFS('03_Base_Vendas'!$I$4:$I$387, '03_Base_Vendas'!$A$4:$A$387, H$59),0)) -> 1626.1063 | I68: =(SUMIFS('04_Base_Despesas'!$D$4:$D$219, '04_Base_Despesas'!$A$4:$A$219, I$59, '04_Base_Despesas'!$B$4:$B$219, "aluguel"))*(IFERROR(SUMIFS('03_Base_Vendas'!$I$4:$I$387, '03_Base_Vendas'!$A$4:$A$387, I$59, '03_Base_Vendas'!$B$4:$B$387, "franquia")/SUMIFS('03_Base_Vendas'!$I$4:$I$387, '03_Base_Vendas'!$A$4:$A$387, I$59),0)) -> 1934.8555 | ... Y68: =(SUMIFS('04_Base_Despesas'!$D$4:$D$219, '04_Base_Despesas'!$A$4:$A$219, Y$59, '04_Base_Despesas'!$B$4:$B$219, "aluguel"))*(IFERROR(SUMIFS('03_Base_Vendas'!$I$4:$I$387, '03_Base_Vendas'!$A$4:$A$387, Y$59, '03_Base_Vendas'!$B$4:$B$387, "franquia")/SUMIFS('03_Base_Vendas'!$I$4:$I$387, '03_Base_Vendas'!$A$4:$A$387, Y$59),0)) -> 1900.2556 | Z68: =SUM(B68:Y68) -> 38767.479
A69: (−) Marketing | B69: =(SUMIFS('04_Base_Despesas'!$D$4:$D$219, '04_Base_Despesas'!$A$4:$A$219, B$59, '04_Base_Despesas'!$B$4:$B$219, "marketing"))*(IFERROR(SUMIFS('03_Base_Vendas'!$I$4:$I$387, '03_Base_Vendas'!$A$4:$A$387, B$59, '03_Base_Vendas'!$B$4:$B$387, "franquia")/SUMIFS('03_Base_Vendas'!$I$4:$I$387, '03_Base_Vendas'!$A$4:$A$387, B$59),0)) -> 3835.8661 | C69: =(SUMIFS('04_Base_Despesas'!$D$4:$D$219, '04_Base_Despesas'!$A$4:$A$219, C$59, '04_Base_Despesas'!$B$4:$B$219, "marketing"))*(IFERROR(SUMIFS('03_Base_Vendas'!$I$4:$I$387, '03_Base_Vendas'!$A$4:$A$387, C$59, '03_Base_Vendas'!$B$4:$B$387, "franquia")/SUMIFS('03_Base_Vendas'!$I$4:$I$387, '03_Base_Vendas'!$A$4:$A$387, C$59),0)) -> 1735.1917 | D69: =(SUMIFS('04_Base_Despesas'!$D$4:$D$219, '04_Base_Despesas'!$A$4:$A$219, D$59, '04_Base_Despesas'!$B$4:$B$219, "marketing"))*(IFERROR(SUMIFS('03_Base_Vendas'!$I$4:$I$387, '03_Base_Vendas'!$A$4:$A$387, D$59, '03_Base_Vendas'!$B$4:$B$387, "franquia")/SUMIFS('03_Base_Vendas'!$I$4:$I$387, '03_Base_Vendas'!$A$4:$A$387, D$59),0)) -> 1637.9045 | E69: =(SUMIFS('04_Base_Despesas'!$D$4:$D$219, '04_Base_Despesas'!$A$4:$A$219, E$59, '04_Base_Despesas'!$B$4:$B$219, "marketing"))*(IFERROR(SUMIFS('03_Base_Vendas'!$I$4:$I$387, '03_Base_Vendas'!$A$4:$A$387, E$59, '03_Base_Vendas'!$B$4:$B$387, "franquia")/SUMIFS('03_Base_Vendas'!$I$4:$I$387, '03_Base_Vendas'!$A$4:$A$387, E$59),0)) -> 1946.8295 | F69: =(SUMIFS('04_Base_Despesas'!$D$4:$D$219, '04_Base_Despesas'!$A$4:$A$219, F$59, '04_Base_Despesas'!$B$4:$B$219, "marketing"))*(IFERROR(SUMIFS('03_Base_Vendas'!$I$4:$I$387, '03_Base_Vendas'!$A$4:$A$387, F$59, '03_Base_Vendas'!$B$4:$B$387, "franquia")/SUMIFS('03_Base_Vendas'!$I$4:$I$387, '03_Base_Vendas'!$A$4:$A$387, F$59),0)) -> 2808.4204 | G69: =(SUMIFS('04_Base_Despesas'!$D$4:$D$219, '04_Base_Despesas'!$A$4:$A$219, G$59, '04_Base_Despesas'!$B$4:$B$219, "marketing"))*(IFERROR(SUMIFS('03_Base_Vendas'!$I$4:$I$387, '03_Base_Vendas'!$A$4:$A$387, G$59, '03_Base_Vendas'!$B$4:$B$387, "franquia")/SUMIFS('03_Base_Vendas'!$I$4:$I$387, '03_Base_Vendas'!$A$4:$A$387, G$59),0)) -> 2982.3176 | H69: =(SUMIFS('04_Base_Despesas'!$D$4:$D$219, '04_Base_Despesas'!$A$4:$A$219, H$59, '04_Base_Despesas'!$B$4:$B$219, "marketing"))*(IFERROR(SUMIFS('03_Base_Vendas'!$I$4:$I$387, '03_Base_Vendas'!$A$4:$A$387, H$59, '03_Base_Vendas'!$B$4:$B$387, "franquia")/SUMIFS('03_Base_Vendas'!$I$4:$I$387, '03_Base_Vendas'!$A$4:$A$387, H$59),0)) -> 1702.8739 | I69: =(SUMIFS('04_Base_Despesas'!$D$4:$D$219, '04_Base_Despesas'!$A$4:$A$219, I$59, '04_Base_Despesas'!$B$4:$B$219, "marketing"))*(IFERROR(SUMIFS('03_Base_Vendas'!$I$4:$I$387, '03_Base_Vendas'!$A$4:$A$387, I$59, '03_Base_Vendas'!$B$4:$B$387, "franquia")/SUMIFS('03_Base_Vendas'!$I$4:$I$387, '03_Base_Vendas'!$A$4:$A$387, I$59),0)) -> 2617.0367 | ... Y69: =(SUMIFS('04_Base_Despesas'!$D$4:$D$219, '04_Base_Despesas'!$A$4:$A$219, Y$59, '04_Base_Despesas'!$B$4:$B$219, "marketing"))*(IFERROR(SUMIFS('03_Base_Vendas'!$I$4:$I$387, '03_Base_Vendas'!$A$4:$A$387, Y$59, '03_Base_Vendas'!$B$4:$B$387, "franquia")/SUMIFS('03_Base_Vendas'!$I$4:$I$387, '03_Base_Vendas'!$A$4:$A$387, Y$59),0)) -> 2826.5712 | Z69: =SUM(B69:Y69) -> 59494.214
A70: (−) Logística | B70: =(SUMIFS('04_Base_Despesas'!$D$4:$D$219, '04_Base_Despesas'!$A$4:$A$219, B$59, '04_Base_Despesas'!$B$4:$B$219, "logistica"))*(IFERROR(SUMIFS('03_Base_Vendas'!$I$4:$I$387, '03_Base_Vendas'!$A$4:$A$387, B$59, '03_Base_Vendas'!$B$4:$B$387, "franquia")/SUMIFS('03_Base_Vendas'!$I$4:$I$387, '03_Base_Vendas'!$A$4:$A$387, B$59),0)) -> 1933.141 | C70: =(SUMIFS('04_Base_Despesas'!$D$4:$D$219, '04_Base_Despesas'!$A$4:$A$219, C$59, '04_Base_Despesas'!$B$4:$B$219, "logistica"))*(IFERROR(SUMIFS('03_Base_Vendas'!$I$4:$I$387, '03_Base_Vendas'!$A$4:$A$387, C$59, '03_Base_Vendas'!$B$4:$B$387, "franquia")/SUMIFS('03_Base_Vendas'!$I$4:$I$387, '03_Base_Vendas'!$A$4:$A$387, C$59),0)) -> 1308.4509 | D70: =(SUMIFS('04_Base_Despesas'!$D$4:$D$219, '04_Base_Despesas'!$A$4:$A$219, D$59, '04_Base_Despesas'!$B$4:$B$219, "logistica"))*(IFERROR(SUMIFS('03_Base_Vendas'!$I$4:$I$387, '03_Base_Vendas'!$A$4:$A$387, D$59, '03_Base_Vendas'!$B$4:$B$387, "franquia")/SUMIFS('03_Base_Vendas'!$I$4:$I$387, '03_Base_Vendas'!$A$4:$A$387, D$59),0)) -> 1455.0539 | E70: =(SUMIFS('04_Base_Despesas'!$D$4:$D$219, '04_Base_Despesas'!$A$4:$A$219, E$59, '04_Base_Despesas'!$B$4:$B$219, "logistica"))*(IFERROR(SUMIFS('03_Base_Vendas'!$I$4:$I$387, '03_Base_Vendas'!$A$4:$A$387, E$59, '03_Base_Vendas'!$B$4:$B$387, "franquia")/SUMIFS('03_Base_Vendas'!$I$4:$I$387, '03_Base_Vendas'!$A$4:$A$387, E$59),0)) -> 1708.7898 | F70: =(SUMIFS('04_Base_Despesas'!$D$4:$D$219, '04_Base_Despesas'!$A$4:$A$219, F$59, '04_Base_Despesas'!$B$4:$B$219, "logistica"))*(IFERROR(SUMIFS('03_Base_Vendas'!$I$4:$I$387, '03_Base_Vendas'!$A$4:$A$387, F$59, '03_Base_Vendas'!$B$4:$B$387, "franquia")/SUMIFS('03_Base_Vendas'!$I$4:$I$387, '03_Base_Vendas'!$A$4:$A$387, F$59),0)) -> 1620.254 | G70: =(SUMIFS('04_Base_Despesas'!$D$4:$D$219, '04_Base_Despesas'!$A$4:$A$219, G$59, '04_Base_Despesas'!$B$4:$B$219, "logistica"))*(IFERROR(SUMIFS('03_Base_Vendas'!$I$4:$I$387, '03_Base_Vendas'!$A$4:$A$387, G$59, '03_Base_Vendas'!$B$4:$B$387, "franquia")/SUMIFS('03_Base_Vendas'!$I$4:$I$387, '03_Base_Vendas'!$A$4:$A$387, G$59),0)) -> 1585.7091 | H70: =(SUMIFS('04_Base_Despesas'!$D$4:$D$219, '04_Base_Despesas'!$A$4:$A$219, H$59, '04_Base_Despesas'!$B$4:$B$219, "logistica"))*(IFERROR(SUMIFS('03_Base_Vendas'!$I$4:$I$387, '03_Base_Vendas'!$A$4:$A$387, H$59, '03_Base_Vendas'!$B$4:$B$387, "franquia")/SUMIFS('03_Base_Vendas'!$I$4:$I$387, '03_Base_Vendas'!$A$4:$A$387, H$59),0)) -> 1838.2738 | I70: =(SUMIFS('04_Base_Despesas'!$D$4:$D$219, '04_Base_Despesas'!$A$4:$A$219, I$59, '04_Base_Despesas'!$B$4:$B$219, "logistica"))*(IFERROR(SUMIFS('03_Base_Vendas'!$I$4:$I$387, '03_Base_Vendas'!$A$4:$A$387, I$59, '03_Base_Vendas'!$B$4:$B$387, "franquia")/SUMIFS('03_Base_Vendas'!$I$4:$I$387, '03_Base_Vendas'!$A$4:$A$387, I$59),0)) -> 2190.9265 | ... Y70: =(SUMIFS('04_Base_Despesas'!$D$4:$D$219, '04_Base_Despesas'!$A$4:$A$219, Y$59, '04_Base_Despesas'!$B$4:$B$219, "logistica"))*(IFERROR(SUMIFS('03_Base_Vendas'!$I$4:$I$387, '03_Base_Vendas'!$A$4:$A$387, Y$59, '03_Base_Vendas'!$B$4:$B$387, "franquia")/SUMIFS('03_Base_Vendas'!$I$4:$I$387, '03_Base_Vendas'!$A$4:$A$387, Y$59),0)) -> 1860.8823 | Z70: =SUM(B70:Y70) -> 40555.139
A71: (−) Tecnologia | B71: =(SUMIFS('04_Base_Despesas'!$D$4:$D$219, '04_Base_Despesas'!$A$4:$A$219, B$59, '04_Base_Despesas'!$B$4:$B$219, "tecnologia"))*(IFERROR(SUMIFS('03_Base_Vendas'!$I$4:$I$387, '03_Base_Vendas'!$A$4:$A$387, B$59, '03_Base_Vendas'!$B$4:$B$387, "franquia")/SUMIFS('03_Base_Vendas'!$I$4:$I$387, '03_Base_Vendas'!$A$4:$A$387, B$59),0)) -> 1443.3189 | C71: =(SUMIFS('04_Base_Despesas'!$D$4:$D$219, '04_Base_Despesas'!$A$4:$A$219, C$59, '04_Base_Despesas'!$B$4:$B$219, "tecnologia"))*(IFERROR(SUMIFS('03_Base_Vendas'!$I$4:$I$387, '03_Base_Vendas'!$A$4:$A$387, C$59, '03_Base_Vendas'!$B$4:$B$387, "franquia")/SUMIFS('03_Base_Vendas'!$I$4:$I$387, '03_Base_Vendas'!$A$4:$A$387, C$59),0)) -> 945.15739 | D71: =(SUMIFS('04_Base_Despesas'!$D$4:$D$219, '04_Base_Despesas'!$A$4:$A$219, D$59, '04_Base_Despesas'!$B$4:$B$219, "tecnologia"))*(IFERROR(SUMIFS('03_Base_Vendas'!$I$4:$I$387, '03_Base_Vendas'!$A$4:$A$387, D$59, '03_Base_Vendas'!$B$4:$B$387, "franquia")/SUMIFS('03_Base_Vendas'!$I$4:$I$387, '03_Base_Vendas'!$A$4:$A$387, D$59),0)) -> 991.44879 | E71: =(SUMIFS('04_Base_Despesas'!$D$4:$D$219, '04_Base_Despesas'!$A$4:$A$219, E$59, '04_Base_Despesas'!$B$4:$B$219, "tecnologia"))*(IFERROR(SUMIFS('03_Base_Vendas'!$I$4:$I$387, '03_Base_Vendas'!$A$4:$A$387, E$59, '03_Base_Vendas'!$B$4:$B$387, "franquia")/SUMIFS('03_Base_Vendas'!$I$4:$I$387, '03_Base_Vendas'!$A$4:$A$387, E$59),0)) -> 1036.9004 | F71: =(SUMIFS('04_Base_Despesas'!$D$4:$D$219, '04_Base_Despesas'!$A$4:$A$219, F$59, '04_Base_Despesas'!$B$4:$B$219, "tecnologia"))*(IFERROR(SUMIFS('03_Base_Vendas'!$I$4:$I$387, '03_Base_Vendas'!$A$4:$A$387, F$59, '03_Base_Vendas'!$B$4:$B$387, "franquia")/SUMIFS('03_Base_Vendas'!$I$4:$I$387, '03_Base_Vendas'!$A$4:$A$387, F$59),0)) -> 1082.1979 | G71: =(SUMIFS('04_Base_Despesas'!$D$4:$D$219, '04_Base_Despesas'!$A$4:$A$219, G$59, '04_Base_Despesas'!$B$4:$B$219, "tecnologia"))*(IFERROR(SUMIFS('03_Base_Vendas'!$I$4:$I$387, '03_Base_Vendas'!$A$4:$A$387, G$59, '03_Base_Vendas'!$B$4:$B$387, "franquia")/SUMIFS('03_Base_Vendas'!$I$4:$I$387, '03_Base_Vendas'!$A$4:$A$387, G$59),0)) -> 1127.2026 | H71: =(SUMIFS('04_Base_Despesas'!$D$4:$D$219, '04_Base_Despesas'!$A$4:$A$219, H$59, '04_Base_Despesas'!$B$4:$B$219, "tecnologia"))*(IFERROR(SUMIFS('03_Base_Vendas'!$I$4:$I$387, '03_Base_Vendas'!$A$4:$A$387, H$59, '03_Base_Vendas'!$B$4:$B$387, "franquia")/SUMIFS('03_Base_Vendas'!$I$4:$I$387, '03_Base_Vendas'!$A$4:$A$387, H$59),0)) -> 1133.8737 | I71: =(SUMIFS('04_Base_Despesas'!$D$4:$D$219, '04_Base_Despesas'!$A$4:$A$219, I$59, '04_Base_Despesas'!$B$4:$B$219, "tecnologia"))*(IFERROR(SUMIFS('03_Base_Vendas'!$I$4:$I$387, '03_Base_Vendas'!$A$4:$A$387, I$59, '03_Base_Vendas'!$B$4:$B$387, "franquia")/SUMIFS('03_Base_Vendas'!$I$4:$I$387, '03_Base_Vendas'!$A$4:$A$387, I$59),0)) -> 1383.8799 | ... Y71: =(SUMIFS('04_Base_Despesas'!$D$4:$D$219, '04_Base_Despesas'!$A$4:$A$219, Y$59, '04_Base_Despesas'!$B$4:$B$219, "tecnologia"))*(IFERROR(SUMIFS('03_Base_Vendas'!$I$4:$I$387, '03_Base_Vendas'!$A$4:$A$387, Y$59, '03_Base_Vendas'!$B$4:$B$387, "franquia")/SUMIFS('03_Base_Vendas'!$I$4:$I$387, '03_Base_Vendas'!$A$4:$A$387, Y$59),0)) -> 0 | Z71: =SUM(B71:Y71) -> 25950.234
A72: (−) Administrativo | B72: =(SUMIFS('04_Base_Despesas'!$D$4:$D$219, '04_Base_Despesas'!$A$4:$A$219, B$59, '04_Base_Despesas'!$B$4:$B$219, "administrativo"))*(IFERROR(SUMIFS('03_Base_Vendas'!$I$4:$I$387, '03_Base_Vendas'!$A$4:$A$387, B$59, '03_Base_Vendas'!$B$4:$B$387, "franquia")/SUMIFS('03_Base_Vendas'!$I$4:$I$387, '03_Base_Vendas'!$A$4:$A$387, B$59),0)) -> 883.19929 | C72: =(SUMIFS('04_Base_Despesas'!$D$4:$D$219, '04_Base_Despesas'!$A$4:$A$219, C$59, '04_Base_Despesas'!$B$4:$B$219, "administrativo"))*(IFERROR(SUMIFS('03_Base_Vendas'!$I$4:$I$387, '03_Base_Vendas'!$A$4:$A$387, C$59, '03_Base_Vendas'!$B$4:$B$387, "franquia")/SUMIFS('03_Base_Vendas'!$I$4:$I$387, '03_Base_Vendas'!$A$4:$A$387, C$59),0)) -> 357.08736 | D72: =(SUMIFS('04_Base_Despesas'!$D$4:$D$219, '04_Base_Despesas'!$A$4:$A$219, D$59, '04_Base_Despesas'!$B$4:$B$219, "administrativo"))*(IFERROR(SUMIFS('03_Base_Vendas'!$I$4:$I$387, '03_Base_Vendas'!$A$4:$A$387, D$59, '03_Base_Vendas'!$B$4:$B$387, "franquia")/SUMIFS('03_Base_Vendas'!$I$4:$I$387, '03_Base_Vendas'!$A$4:$A$387, D$59),0)) -> 372.55312 | E72: =(SUMIFS('04_Base_Despesas'!$D$4:$D$219, '04_Base_Despesas'!$A$4:$A$219, E$59, '04_Base_Despesas'!$B$4:$B$219, "administrativo"))*(IFERROR(SUMIFS('03_Base_Vendas'!$I$4:$I$387, '03_Base_Vendas'!$A$4:$A$387, E$59, '03_Base_Vendas'!$B$4:$B$387, "franquia")/SUMIFS('03_Base_Vendas'!$I$4:$I$387, '03_Base_Vendas'!$A$4:$A$387, E$59),0)) -> 717.19907 | F72: =(SUMIFS('04_Base_Despesas'!$D$4:$D$219, '04_Base_Despesas'!$A$4:$A$219, F$59, '04_Base_Despesas'!$B$4:$B$219, "administrativo"))*(IFERROR(SUMIFS('03_Base_Vendas'!$I$4:$I$387, '03_Base_Vendas'!$A$4:$A$387, F$59, '03_Base_Vendas'!$B$4:$B$387, "franquia")/SUMIFS('03_Base_Vendas'!$I$4:$I$387, '03_Base_Vendas'!$A$4:$A$387, F$59),0)) -> 410.52679 | G72: =(SUMIFS('04_Base_Despesas'!$D$4:$D$219, '04_Base_Despesas'!$A$4:$A$219, G$59, '04_Base_Despesas'!$B$4:$B$219, "administrativo"))*(IFERROR(SUMIFS('03_Base_Vendas'!$I$4:$I$387, '03_Base_Vendas'!$A$4:$A$387, G$59, '03_Base_Vendas'!$B$4:$B$387, "franquia")/SUMIFS('03_Base_Vendas'!$I$4:$I$387, '03_Base_Vendas'!$A$4:$A$387, G$59),0)) -> 420.57099 | H72: =(SUMIFS('04_Base_Despesas'!$D$4:$D$219, '04_Base_Despesas'!$A$4:$A$219, H$59, '04_Base_Despesas'!$B$4:$B$219, "administrativo"))*(IFERROR(SUMIFS('03_Base_Vendas'!$I$4:$I$387, '03_Base_Vendas'!$A$4:$A$387, H$59, '03_Base_Vendas'!$B$4:$B$387, "franquia")/SUMIFS('03_Base_Vendas'!$I$4:$I$387, '03_Base_Vendas'!$A$4:$A$387, H$59),0)) -> 727.93932 | I72: =(SUMIFS('04_Base_Despesas'!$D$4:$D$219, '04_Base_Despesas'!$A$4:$A$219, I$59, '04_Base_Despesas'!$B$4:$B$219, "administrativo"))*(IFERROR(SUMIFS('03_Base_Vendas'!$I$4:$I$387, '03_Base_Vendas'!$A$4:$A$387, I$59, '03_Base_Vendas'!$B$4:$B$387, "franquia")/SUMIFS('03_Base_Vendas'!$I$4:$I$387, '03_Base_Vendas'!$A$4:$A$387, I$59),0)) -> 509.1725 | ... Y72: =(SUMIFS('04_Base_Despesas'!$D$4:$D$219, '04_Base_Despesas'!$A$4:$A$219, Y$59, '04_Base_Despesas'!$B$4:$B$219, "administrativo"))*(IFERROR(SUMIFS('03_Base_Vendas'!$I$4:$I$387, '03_Base_Vendas'!$A$4:$A$387, Y$59, '03_Base_Vendas'!$B$4:$B$387, "franquia")/SUMIFS('03_Base_Vendas'!$I$4:$I$387, '03_Base_Vendas'!$A$4:$A$387, Y$59),0)) -> 500.06674 | Z72: =SUM(B72:Y72) -> 12789.844
A73: (−) Outros | B73: =(SUMIFS('04_Base_Despesas'!$D$4:$D$219, '04_Base_Despesas'!$A$4:$A$219, B$59, '04_Base_Despesas'!$B$4:$B$219, "outros"))*(IFERROR(SUMIFS('03_Base_Vendas'!$I$4:$I$387, '03_Base_Vendas'!$A$4:$A$387, B$59, '03_Base_Vendas'!$B$4:$B$387, "franquia")/SUMIFS('03_Base_Vendas'!$I$4:$I$387, '03_Base_Vendas'!$A$4:$A$387, B$59),0)) -> 170.10832 | C73: =(SUMIFS('04_Base_Despesas'!$D$4:$D$219, '04_Base_Despesas'!$A$4:$A$219, C$59, '04_Base_Despesas'!$B$4:$B$219, "outros"))*(IFERROR(SUMIFS('03_Base_Vendas'!$I$4:$I$387, '03_Base_Vendas'!$A$4:$A$387, C$59, '03_Base_Vendas'!$B$4:$B$387, "franquia")/SUMIFS('03_Base_Vendas'!$I$4:$I$387, '03_Base_Vendas'!$A$4:$A$387, C$59),0)) -> 125.50478 | D73: =(SUMIFS('04_Base_Despesas'!$D$4:$D$219, '04_Base_Despesas'!$A$4:$A$219, D$59, '04_Base_Despesas'!$B$4:$B$219, "outros"))*(IFERROR(SUMIFS('03_Base_Vendas'!$I$4:$I$387, '03_Base_Vendas'!$A$4:$A$387, D$59, '03_Base_Vendas'!$B$4:$B$387, "franquia")/SUMIFS('03_Base_Vendas'!$I$4:$I$387, '03_Base_Vendas'!$A$4:$A$387, D$59),0)) -> 128.87507 | E73: =(SUMIFS('04_Base_Despesas'!$D$4:$D$219, '04_Base_Despesas'!$A$4:$A$219, E$59, '04_Base_Despesas'!$B$4:$B$219, "outros"))*(IFERROR(SUMIFS('03_Base_Vendas'!$I$4:$I$387, '03_Base_Vendas'!$A$4:$A$387, E$59, '03_Base_Vendas'!$B$4:$B$387, "franquia")/SUMIFS('03_Base_Vendas'!$I$4:$I$387, '03_Base_Vendas'!$A$4:$A$387, E$59),0)) -> 108.36012 | F73: =(SUMIFS('04_Base_Despesas'!$D$4:$D$219, '04_Base_Despesas'!$A$4:$A$219, F$59, '04_Base_Despesas'!$B$4:$B$219, "outros"))*(IFERROR(SUMIFS('03_Base_Vendas'!$I$4:$I$387, '03_Base_Vendas'!$A$4:$A$387, F$59, '03_Base_Vendas'!$B$4:$B$387, "franquia")/SUMIFS('03_Base_Vendas'!$I$4:$I$387, '03_Base_Vendas'!$A$4:$A$387, F$59),0)) -> 127.05312 | G73: =(SUMIFS('04_Base_Despesas'!$D$4:$D$219, '04_Base_Despesas'!$A$4:$A$219, G$59, '04_Base_Despesas'!$B$4:$B$219, "outros"))*(IFERROR(SUMIFS('03_Base_Vendas'!$I$4:$I$387, '03_Base_Vendas'!$A$4:$A$387, G$59, '03_Base_Vendas'!$B$4:$B$387, "franquia")/SUMIFS('03_Base_Vendas'!$I$4:$I$387, '03_Base_Vendas'!$A$4:$A$387, G$59),0)) -> 129.67381 | H73: =(SUMIFS('04_Base_Despesas'!$D$4:$D$219, '04_Base_Despesas'!$A$4:$A$219, H$59, '04_Base_Despesas'!$B$4:$B$219, "outros"))*(IFERROR(SUMIFS('03_Base_Vendas'!$I$4:$I$387, '03_Base_Vendas'!$A$4:$A$387, H$59, '03_Base_Vendas'!$B$4:$B$387, "franquia")/SUMIFS('03_Base_Vendas'!$I$4:$I$387, '03_Base_Vendas'!$A$4:$A$387, H$59),0)) -> 168.52623 | I73: =(SUMIFS('04_Base_Despesas'!$D$4:$D$219, '04_Base_Despesas'!$A$4:$A$219, I$59, '04_Base_Despesas'!$B$4:$B$219, "outros"))*(IFERROR(SUMIFS('03_Base_Vendas'!$I$4:$I$387, '03_Base_Vendas'!$A$4:$A$387, I$59, '03_Base_Vendas'!$B$4:$B$387, "franquia")/SUMIFS('03_Base_Vendas'!$I$4:$I$387, '03_Base_Vendas'!$A$4:$A$387, I$59),0)) -> 177.96801 | ... Y73: =(SUMIFS('04_Base_Despesas'!$D$4:$D$219, '04_Base_Despesas'!$A$4:$A$219, Y$59, '04_Base_Despesas'!$B$4:$B$219, "outros"))*(IFERROR(SUMIFS('03_Base_Vendas'!$I$4:$I$387, '03_Base_Vendas'!$A$4:$A$387, Y$59, '03_Base_Vendas'!$B$4:$B$387, "franquia")/SUMIFS('03_Base_Vendas'!$I$4:$I$387, '03_Base_Vendas'!$A$4:$A$387, Y$59),0)) -> 129.71131 | Z73: =SUM(B73:Y73) -> 3482.5069
A74: Total Despesas Operac. | B74: =B67+B68+B69+B70+B71+B72+B73 -> 21194.649 | C74: =C67+C68+C69+C70+C71+C72+C73 -> 13273.47 | D74: =D67+D68+D69+D70+D71+D72+D73 -> 13471.19 | E74: =E67+E68+E69+E70+E71+E72+E73 -> 14798.891 | F74: =F67+F68+F69+F70+F71+F72+F73 -> 16144.928 | G74: =G67+G68+G69+G70+G71+G72+G73 -> 16353.115 | H74: =H67+H68+H69+H70+H71+H72+H73 -> 16078.357 | I74: =I67+I68+I69+I70+I71+I72+I73 -> 19385.177 | ... Y74: =Y67+Y68+Y69+Y70+Y71+Y72+Y73 -> 17440.716 | Z74: =SUM(B74:Y74) -> 390554.71
A75: EBITDA | B75: =B65-B74 -> -7789.3186 | C75: =C65-C74 -> -5987.5699 | D75: =D65-D74 -> -4469.24 | E75: =E65-E74 -> -5283.1708 | F75: =F65-F74 -> -2169.8585 | G75: =G65-G74 -> -3915.4155 | H75: =H65-H74 -> -6267.1671 | I75: =I65-I74 -> -7568.7766 | ... Y75: =Y65-Y74 -> -160.37551 | Z75: =SUM(B75:Y75) -> -104908.23
A76: % Margem EBITDA | B76: =IFERROR(B75/B63,0) -> -0.24156334 | C76: =IFERROR(C75/C63,0) -> -0.33613182 | D76: =IFERROR(D75/D63,0) -> -0.19717467 | E76: =IFERROR(E75/E63,0) -> -0.24010615 | F76: =IFERROR(F75/F63,0) -> -0.067765068 | G76: =IFERROR(G75/G63,0) -> -0.13713226 | H76: =IFERROR(H75/H63,0) -> -0.28337014 | I76: =IFERROR(I75/I63,0) -> -0.28820216 | ... Y76: =IFERROR(Y75/Y63,0) -> -0.004126983 | Z76: =IFERROR($Z$75/$Z$63,0) -> -0.15573787
A77: (−) Depreciação | B77: =(SUMIFS('04_Base_Despesas'!$D$4:$D$219, '04_Base_Despesas'!$A$4:$A$219, B$59, '04_Base_Despesas'!$B$4:$B$219, "depreciacao"))*(IFERROR(SUMIFS('03_Base_Vendas'!$I$4:$I$387, '03_Base_Vendas'!$A$4:$A$387, B$59, '03_Base_Vendas'!$B$4:$B$387, "franquia")/SUMIFS('03_Base_Vendas'!$I$4:$I$387, '03_Base_Vendas'!$A$4:$A$387, B$59),0)) -> 472.86129 | C77: =(SUMIFS('04_Base_Despesas'!$D$4:$D$219, '04_Base_Despesas'!$A$4:$A$219, C$59, '04_Base_Despesas'!$B$4:$B$219, "depreciacao"))*(IFERROR(SUMIFS('03_Base_Vendas'!$I$4:$I$387, '03_Base_Vendas'!$A$4:$A$387, C$59, '03_Base_Vendas'!$B$4:$B$387, "franquia")/SUMIFS('03_Base_Vendas'!$I$4:$I$387, '03_Base_Vendas'!$A$4:$A$387, C$59),0)) -> 314.23687 | D77: =(SUMIFS('04_Base_Despesas'!$D$4:$D$219, '04_Base_Despesas'!$A$4:$A$219, D$59, '04_Base_Despesas'!$B$4:$B$219, "depreciacao"))*(IFERROR(SUMIFS('03_Base_Vendas'!$I$4:$I$387, '03_Base_Vendas'!$A$4:$A$387, D$59, '03_Base_Vendas'!$B$4:$B$387, "franquia")/SUMIFS('03_Base_Vendas'!$I$4:$I$387, '03_Base_Vendas'!$A$4:$A$387, D$59),0)) -> 327.84525 | E77: =(SUMIFS('04_Base_Despesas'!$D$4:$D$219, '04_Base_Despesas'!$A$4:$A$219, E$59, '04_Base_Despesas'!$B$4:$B$219, "depreciacao"))*(IFERROR(SUMIFS('03_Base_Vendas'!$I$4:$I$387, '03_Base_Vendas'!$A$4:$A$387, E$59, '03_Base_Vendas'!$B$4:$B$387, "franquia")/SUMIFS('03_Base_Vendas'!$I$4:$I$387, '03_Base_Vendas'!$A$4:$A$387, E$59),0)) -> 346.22204 | F77: =(SUMIFS('04_Base_Despesas'!$D$4:$D$219, '04_Base_Despesas'!$A$4:$A$219, F$59, '04_Base_Despesas'!$B$4:$B$219, "depreciacao"))*(IFERROR(SUMIFS('03_Base_Vendas'!$I$4:$I$387, '03_Base_Vendas'!$A$4:$A$387, F$59, '03_Base_Vendas'!$B$4:$B$387, "franquia")/SUMIFS('03_Base_Vendas'!$I$4:$I$387, '03_Base_Vendas'!$A$4:$A$387, F$59),0)) -> 361.26194 | G77: =(SUMIFS('04_Base_Despesas'!$D$4:$D$219, '04_Base_Despesas'!$A$4:$A$219, G$59, '04_Base_Despesas'!$B$4:$B$219, "depreciacao"))*(IFERROR(SUMIFS('03_Base_Vendas'!$I$4:$I$387, '03_Base_Vendas'!$A$4:$A$387, G$59, '03_Base_Vendas'!$B$4:$B$387, "franquia")/SUMIFS('03_Base_Vendas'!$I$4:$I$387, '03_Base_Vendas'!$A$4:$A$387, G$59),0)) -> 370.10079 | H77: =(SUMIFS('04_Base_Despesas'!$D$4:$D$219, '04_Base_Despesas'!$A$4:$A$219, H$59, '04_Base_Despesas'!$B$4:$B$219, "depreciacao"))*(IFERROR(SUMIFS('03_Base_Vendas'!$I$4:$I$387, '03_Base_Vendas'!$A$4:$A$387, H$59, '03_Base_Vendas'!$B$4:$B$387, "franquia")/SUMIFS('03_Base_Vendas'!$I$4:$I$387, '03_Base_Vendas'!$A$4:$A$387, H$59),0)) -> 376.57027 | I77: =(SUMIFS('04_Base_Despesas'!$D$4:$D$219, '04_Base_Despesas'!$A$4:$A$219, I$59, '04_Base_Despesas'!$B$4:$B$219, "depreciacao"))*(IFERROR(SUMIFS('03_Base_Vendas'!$I$4:$I$387, '03_Base_Vendas'!$A$4:$A$387, I$59, '03_Base_Vendas'!$B$4:$B$387, "franquia")/SUMIFS('03_Base_Vendas'!$I$4:$I$387, '03_Base_Vendas'!$A$4:$A$387, I$59),0)) -> 448.0718 | ... Y77: =(SUMIFS('04_Base_Despesas'!$D$4:$D$219, '04_Base_Despesas'!$A$4:$A$219, Y$59, '04_Base_Despesas'!$B$4:$B$219, "depreciacao"))*(IFERROR(SUMIFS('03_Base_Vendas'!$I$4:$I$387, '03_Base_Vendas'!$A$4:$A$387, Y$59, '03_Base_Vendas'!$B$4:$B$387, "franquia")/SUMIFS('03_Base_Vendas'!$I$4:$I$387, '03_Base_Vendas'!$A$4:$A$387, Y$59),0)) -> 440.05873 | Z77: =SUM(B77:Y77) -> 8977.7146
A78: EBIT | B78: =B75-B77 -> -8262.1799 | C78: =C75-C77 -> -6301.8067 | D78: =D75-D77 -> -4797.0852 | E78: =E75-E77 -> -5629.3929 | F78: =F75-F77 -> -2531.1204 | G78: =G75-G77 -> -4285.5163 | H78: =H75-H77 -> -6643.7374 | I78: =I75-I77 -> -8016.8484 | ... Y78: =Y75-Y77 -> -600.43424 | Z78: =SUM(B78:Y78) -> -113885.94
A79: (−) Despesas Financeiras | B79: =(SUMIFS('04_Base_Despesas'!$D$4:$D$219, '04_Base_Despesas'!$A$4:$A$219, B$59, '04_Base_Despesas'!$B$4:$B$219, "financeiro"))*(IFERROR(SUMIFS('03_Base_Vendas'!$I$4:$I$387, '03_Base_Vendas'!$A$4:$A$387, B$59, '03_Base_Vendas'!$B$4:$B$387, "franquia")/SUMIFS('03_Base_Vendas'!$I$4:$I$387, '03_Base_Vendas'!$A$4:$A$387, B$59),0)) -> 293.48484 | C79: =(SUMIFS('04_Base_Despesas'!$D$4:$D$219, '04_Base_Despesas'!$A$4:$A$219, C$59, '04_Base_Despesas'!$B$4:$B$219, "financeiro"))*(IFERROR(SUMIFS('03_Base_Vendas'!$I$4:$I$387, '03_Base_Vendas'!$A$4:$A$387, C$59, '03_Base_Vendas'!$B$4:$B$387, "franquia")/SUMIFS('03_Base_Vendas'!$I$4:$I$387, '03_Base_Vendas'!$A$4:$A$387, C$59),0)) -> 193.05142 | D79: =(SUMIFS('04_Base_Despesas'!$D$4:$D$219, '04_Base_Despesas'!$A$4:$A$219, D$59, '04_Base_Despesas'!$B$4:$B$219, "financeiro"))*(IFERROR(SUMIFS('03_Base_Vendas'!$I$4:$I$387, '03_Base_Vendas'!$A$4:$A$387, D$59, '03_Base_Vendas'!$B$4:$B$387, "franquia")/SUMIFS('03_Base_Vendas'!$I$4:$I$387, '03_Base_Vendas'!$A$4:$A$387, D$59),0)) -> 200.55429 | E79: =(SUMIFS('04_Base_Despesas'!$D$4:$D$219, '04_Base_Despesas'!$A$4:$A$219, E$59, '04_Base_Despesas'!$B$4:$B$219, "financeiro"))*(IFERROR(SUMIFS('03_Base_Vendas'!$I$4:$I$387, '03_Base_Vendas'!$A$4:$A$387, E$59, '03_Base_Vendas'!$B$4:$B$387, "franquia")/SUMIFS('03_Base_Vendas'!$I$4:$I$387, '03_Base_Vendas'!$A$4:$A$387, E$59),0)) -> 204.28767 | F79: =(SUMIFS('04_Base_Despesas'!$D$4:$D$219, '04_Base_Despesas'!$A$4:$A$219, F$59, '04_Base_Despesas'!$B$4:$B$219, "financeiro"))*(IFERROR(SUMIFS('03_Base_Vendas'!$I$4:$I$387, '03_Base_Vendas'!$A$4:$A$387, F$59, '03_Base_Vendas'!$B$4:$B$387, "franquia")/SUMIFS('03_Base_Vendas'!$I$4:$I$387, '03_Base_Vendas'!$A$4:$A$387, F$59),0)) -> 222.18203 | G79: =(SUMIFS('04_Base_Despesas'!$D$4:$D$219, '04_Base_Despesas'!$A$4:$A$219, G$59, '04_Base_Despesas'!$B$4:$B$219, "financeiro"))*(IFERROR(SUMIFS('03_Base_Vendas'!$I$4:$I$387, '03_Base_Vendas'!$A$4:$A$387, G$59, '03_Base_Vendas'!$B$4:$B$387, "franquia")/SUMIFS('03_Base_Vendas'!$I$4:$I$387, '03_Base_Vendas'!$A$4:$A$387, G$59),0)) -> 215.07496 | H79: =(SUMIFS('04_Base_Despesas'!$D$4:$D$219, '04_Base_Despesas'!$A$4:$A$219, H$59, '04_Base_Despesas'!$B$4:$B$219, "financeiro"))*(IFERROR(SUMIFS('03_Base_Vendas'!$I$4:$I$387, '03_Base_Vendas'!$A$4:$A$387, H$59, '03_Base_Vendas'!$B$4:$B$387, "franquia")/SUMIFS('03_Base_Vendas'!$I$4:$I$387, '03_Base_Vendas'!$A$4:$A$387, H$59),0)) -> 932.18512 | I79: =(SUMIFS('04_Base_Despesas'!$D$4:$D$219, '04_Base_Despesas'!$A$4:$A$219, I$59, '04_Base_Despesas'!$B$4:$B$219, "financeiro"))*(IFERROR(SUMIFS('03_Base_Vendas'!$I$4:$I$387, '03_Base_Vendas'!$A$4:$A$387, I$59, '03_Base_Vendas'!$B$4:$B$387, "franquia")/SUMIFS('03_Base_Vendas'!$I$4:$I$387, '03_Base_Vendas'!$A$4:$A$387, I$59),0)) -> 267.55589 | ... Y79: =(SUMIFS('04_Base_Despesas'!$D$4:$D$219, '04_Base_Despesas'!$A$4:$A$219, Y$59, '04_Base_Despesas'!$B$4:$B$219, "financeiro"))*(IFERROR(SUMIFS('03_Base_Vendas'!$I$4:$I$387, '03_Base_Vendas'!$A$4:$A$387, Y$59, '03_Base_Vendas'!$B$4:$B$387, "franquia")/SUMIFS('03_Base_Vendas'!$I$4:$I$387, '03_Base_Vendas'!$A$4:$A$387, Y$59),0)) -> 276.80894 | Z79: =SUM(B79:Y79) -> 6064.4823
A80: Resultado Operacional | B80: =B78-B79 -> -8555.6647 | C80: =C78-C79 -> -6494.8582 | D80: =D78-D79 -> -4997.6395 | E80: =E78-E79 -> -5833.6805 | F80: =F78-F79 -> -2753.3024 | G80: =G78-G79 -> -4500.5912 | H80: =H78-H79 -> -7575.9225 | I80: =I78-I79 -> -8284.4043 | ... Y80: =Y78-Y79 -> -877.24318 | Z80: =SUM(B80:Y80) -> -119950.42
A81: % Margem Operacional | B81: =IFERROR(B80/B63,0) -> -0.26532936 | C81: =IFERROR(C80/C63,0) -> -0.36461011 | D81: =IFERROR(D80/D63,0) -> -0.22048669 | E81: =IFERROR(E80/E63,0) -> -0.26512536 | F81: =IFERROR(F80/F63,0) -> -0.085986127 | G81: =IFERROR(G80/G63,0) -> -0.15762727 | H81: =IFERROR(H80/H63,0) -> -0.34254556 | I81: =IFERROR(I80/I63,0) -> -0.31545167 | ... Y81: =IFERROR(Y80/Y63,0) -> -0.022574318 | Z81: =IFERROR($Z$80/$Z$63,0) -> -0.17806824
A84: Canal: Loja Própria
A85: Item | B85: 2023-01 | C85: 2023-02 | D85: 2023-03 | E85: 2023-04 | F85: 2023-05 | G85: 2023-06 | H85: 2023-07 | I85: 2023-08 | J85: 2023-09 | K85: 2023-10 | L85: 2023-11 | M85: 2023-12 | N85: 2024-01 | O85: 2024-02 | P85: 2024-03 | Q85: 2024-04 | R85: 2024-05 | S85: 2024-06 | T85: 2024-07 | U85: 2024-08 | V85: 2024-09 | W85: 2024-10 | X85: 2024-11 | Y85: 2024-12 | Z85: Total 24m
A86: Receita Bruta | B86: =SUMIFS('03_Base_Vendas'!$F$4:$F$387, '03_Base_Vendas'!$A$4:$A$387, B$85, '03_Base_Vendas'!$B$4:$B$387, "loja_propria") -> 15287.18 | C86: =SUMIFS('03_Base_Vendas'!$F$4:$F$387, '03_Base_Vendas'!$A$4:$A$387, C$85, '03_Base_Vendas'!$B$4:$B$387, "loja_propria") -> 17549.15 | D86: =SUMIFS('03_Base_Vendas'!$F$4:$F$387, '03_Base_Vendas'!$A$4:$A$387, D$85, '03_Base_Vendas'!$B$4:$B$387, "loja_propria") -> 22291.13 | E86: =SUMIFS('03_Base_Vendas'!$F$4:$F$387, '03_Base_Vendas'!$A$4:$A$387, E$85, '03_Base_Vendas'!$B$4:$B$387, "loja_propria") -> 23821.55 | F86: =SUMIFS('03_Base_Vendas'!$F$4:$F$387, '03_Base_Vendas'!$A$4:$A$387, F$85, '03_Base_Vendas'!$B$4:$B$387, "loja_propria") -> 24128.79 | G86: =SUMIFS('03_Base_Vendas'!$F$4:$F$387, '03_Base_Vendas'!$A$4:$A$387, G$85, '03_Base_Vendas'!$B$4:$B$387, "loja_propria") -> 24537.92 | H86: =SUMIFS('03_Base_Vendas'!$F$4:$F$387, '03_Base_Vendas'!$A$4:$A$387, H$85, '03_Base_Vendas'!$B$4:$B$387, "loja_propria") -> 16767.53 | I86: =SUMIFS('03_Base_Vendas'!$F$4:$F$387, '03_Base_Vendas'!$A$4:$A$387, I$85, '03_Base_Vendas'!$B$4:$B$387, "loja_propria") -> 18498.78 | ... Y86: =SUMIFS('03_Base_Vendas'!$F$4:$F$387, '03_Base_Vendas'!$A$4:$A$387, Y$85, '03_Base_Vendas'!$B$4:$B$387, "loja_propria") -> 24790.08 | Z86: =SUM(B86:Y86) -> 525862.35
A87: (−) Devoluções | B87: =SUMIFS('03_Base_Vendas'!$G$4:$G$387, '03_Base_Vendas'!$A$4:$A$387, B$85, '03_Base_Vendas'!$B$4:$B$387, "loja_propria") -> 0 | C87: =SUMIFS('03_Base_Vendas'!$G$4:$G$387, '03_Base_Vendas'!$A$4:$A$387, C$85, '03_Base_Vendas'!$B$4:$B$387, "loja_propria") -> 974.25 | D87: =SUMIFS('03_Base_Vendas'!$G$4:$G$387, '03_Base_Vendas'!$A$4:$A$387, D$85, '03_Base_Vendas'!$B$4:$B$387, "loja_propria") -> 156.94 | E87: =SUMIFS('03_Base_Vendas'!$G$4:$G$387, '03_Base_Vendas'!$A$4:$A$387, E$85, '03_Base_Vendas'!$B$4:$B$387, "loja_propria") -> 472.79 | F87: =SUMIFS('03_Base_Vendas'!$G$4:$G$387, '03_Base_Vendas'!$A$4:$A$387, F$85, '03_Base_Vendas'!$B$4:$B$387, "loja_propria") -> 227.72 | G87: =SUMIFS('03_Base_Vendas'!$G$4:$G$387, '03_Base_Vendas'!$A$4:$A$387, G$85, '03_Base_Vendas'!$B$4:$B$387, "loja_propria") -> 0 | H87: =SUMIFS('03_Base_Vendas'!$G$4:$G$387, '03_Base_Vendas'!$A$4:$A$387, H$85, '03_Base_Vendas'!$B$4:$B$387, "loja_propria") -> 498.07 | I87: =SUMIFS('03_Base_Vendas'!$G$4:$G$387, '03_Base_Vendas'!$A$4:$A$387, I$85, '03_Base_Vendas'!$B$4:$B$387, "loja_propria") -> 1312.53 | ... Y87: =SUMIFS('03_Base_Vendas'!$G$4:$G$387, '03_Base_Vendas'!$A$4:$A$387, Y$85, '03_Base_Vendas'!$B$4:$B$387, "loja_propria") -> 650.33 | Z87: =SUM(B87:Y87) -> 9729.44
A88: (−) Comissões de canal | B88: =SUMIFS('03_Base_Vendas'!$H$4:$H$387, '03_Base_Vendas'!$A$4:$A$387, B$85, '03_Base_Vendas'!$B$4:$B$387, "loja_propria") -> 4.16 | C88: =SUMIFS('03_Base_Vendas'!$H$4:$H$387, '03_Base_Vendas'!$A$4:$A$387, C$85, '03_Base_Vendas'!$B$4:$B$387, "loja_propria") -> -11.55 | D88: =SUMIFS('03_Base_Vendas'!$H$4:$H$387, '03_Base_Vendas'!$A$4:$A$387, D$85, '03_Base_Vendas'!$B$4:$B$387, "loja_propria") -> 6.32 | E88: =SUMIFS('03_Base_Vendas'!$H$4:$H$387, '03_Base_Vendas'!$A$4:$A$387, E$85, '03_Base_Vendas'!$B$4:$B$387, "loja_propria") -> 47.8 | F88: =SUMIFS('03_Base_Vendas'!$H$4:$H$387, '03_Base_Vendas'!$A$4:$A$387, F$85, '03_Base_Vendas'!$B$4:$B$387, "loja_propria") -> 15.83 | G88: =SUMIFS('03_Base_Vendas'!$H$4:$H$387, '03_Base_Vendas'!$A$4:$A$387, G$85, '03_Base_Vendas'!$B$4:$B$387, "loja_propria") -> -0.1 | H88: =SUMIFS('03_Base_Vendas'!$H$4:$H$387, '03_Base_Vendas'!$A$4:$A$387, H$85, '03_Base_Vendas'!$B$4:$B$387, "loja_propria") -> -4.2 | I88: =SUMIFS('03_Base_Vendas'!$H$4:$H$387, '03_Base_Vendas'!$A$4:$A$387, I$85, '03_Base_Vendas'!$B$4:$B$387, "loja_propria") -> -25.1 | ... Y88: =SUMIFS('03_Base_Vendas'!$H$4:$H$387, '03_Base_Vendas'!$A$4:$A$387, Y$85, '03_Base_Vendas'!$B$4:$B$387, "loja_propria") -> -33.09 | Z88: =SUM(B88:Y88) -> -40.13
A89: Receita Líquida | B89: =B86-B87-B88 -> 15283.02 | C89: =C86-C87-C88 -> 16586.45 | D89: =D86-D87-D88 -> 22127.87 | E89: =E86-E87-E88 -> 23300.96 | F89: =F86-F87-F88 -> 23885.24 | G89: =G86-G87-G88 -> 24538.02 | H89: =H86-H87-H88 -> 16273.66 | I89: =I86-I87-I88 -> 17211.35 | ... Y89: =Y86-Y87-Y88 -> 24172.84 | Z89: =SUM(B89:Y89) -> 516173.04
A90: (−) CMV | B90: =SUMIFS('03_Base_Vendas'!$J$4:$J$387, '03_Base_Vendas'!$A$4:$A$387, B$85, '03_Base_Vendas'!$B$4:$B$387, "loja_propria") -> 7130.35 | C90: =SUMIFS('03_Base_Vendas'!$J$4:$J$387, '03_Base_Vendas'!$A$4:$A$387, C$85, '03_Base_Vendas'!$B$4:$B$387, "loja_propria") -> 8306.87 | D90: =SUMIFS('03_Base_Vendas'!$J$4:$J$387, '03_Base_Vendas'!$A$4:$A$387, D$85, '03_Base_Vendas'!$B$4:$B$387, "loja_propria") -> 10699.91 | E90: =SUMIFS('03_Base_Vendas'!$J$4:$J$387, '03_Base_Vendas'!$A$4:$A$387, E$85, '03_Base_Vendas'!$B$4:$B$387, "loja_propria") -> 11453.61 | F90: =SUMIFS('03_Base_Vendas'!$J$4:$J$387, '03_Base_Vendas'!$A$4:$A$387, F$85, '03_Base_Vendas'!$B$4:$B$387, "loja_propria") -> 10881.1 | G90: =SUMIFS('03_Base_Vendas'!$J$4:$J$387, '03_Base_Vendas'!$A$4:$A$387, G$85, '03_Base_Vendas'!$B$4:$B$387, "loja_propria") -> 11867.97 | H90: =SUMIFS('03_Base_Vendas'!$J$4:$J$387, '03_Base_Vendas'!$A$4:$A$387, H$85, '03_Base_Vendas'!$B$4:$B$387, "loja_propria") -> 8144.66 | I90: =SUMIFS('03_Base_Vendas'!$J$4:$J$387, '03_Base_Vendas'!$A$4:$A$387, I$85, '03_Base_Vendas'!$B$4:$B$387, "loja_propria") -> 8622.33 | ... Y90: =SUMIFS('03_Base_Vendas'!$J$4:$J$387, '03_Base_Vendas'!$A$4:$A$387, Y$85, '03_Base_Vendas'!$B$4:$B$387, "loja_propria") -> 11700.83 | Z90: =SUM(B90:Y90) -> 253010.33
A91: Margem de Contribuição | B91: =B89-B90 -> 8152.67 | C91: =C89-C90 -> 8279.58 | D91: =D89-D90 -> 11427.96 | E91: =E89-E90 -> 11847.35 | F91: =F89-F90 -> 13004.14 | G91: =G89-G90 -> 12670.05 | H91: =H89-H90 -> 8129 | I91: =I89-I90 -> 8589.02 | ... Y91: =Y89-Y90 -> 12472.01 | Z91: =SUM(B91:Y91) -> 263162.71
A92: % Margem de Contribuição | B92: =IFERROR(B91/B89,0) -> 0.53344627 | C92: =IFERROR(C91/C89,0) -> 0.49917734 | D92: =IFERROR(D91/D89,0) -> 0.51645097 | E92: =IFERROR(E91/E89,0) -> 0.50844901 | F92: =IFERROR(F91/F89,0) -> 0.54444251 | G92: =IFERROR(G91/G89,0) -> 0.51634362 | H92: =IFERROR(H91/H89,0) -> 0.49951885 | I92: =IFERROR(I91/I89,0) -> 0.49903232 | ... Y92: =IFERROR(Y91/Y89,0) -> 0.51595137 | Z92: =IFERROR($Z$91/$Z$89,0) -> 0.50983428
A93: (−) Pessoal | B93: =(SUMIFS('04_Base_Despesas'!$D$4:$D$219, '04_Base_Despesas'!$A$4:$A$219, B$85, '04_Base_Despesas'!$B$4:$B$219, "pessoal"))*(IFERROR(SUMIFS('03_Base_Vendas'!$I$4:$I$387, '03_Base_Vendas'!$A$4:$A$387, B$85, '03_Base_Vendas'!$B$4:$B$387, "loja_propria")/SUMIFS('03_Base_Vendas'!$I$4:$I$387, '03_Base_Vendas'!$A$4:$A$387, B$85),0)) -> 5160.0398 | C93: =(SUMIFS('04_Base_Despesas'!$D$4:$D$219, '04_Base_Despesas'!$A$4:$A$219, C$85, '04_Base_Despesas'!$B$4:$B$219, "pessoal"))*(IFERROR(SUMIFS('03_Base_Vendas'!$I$4:$I$387, '03_Base_Vendas'!$A$4:$A$387, C$85, '03_Base_Vendas'!$B$4:$B$387, "loja_propria")/SUMIFS('03_Base_Vendas'!$I$4:$I$387, '03_Base_Vendas'!$A$4:$A$387, C$85),0)) -> 6932.4329 | D93: =(SUMIFS('04_Base_Despesas'!$D$4:$D$219, '04_Base_Despesas'!$A$4:$A$219, D$85, '04_Base_Despesas'!$B$4:$B$219, "pessoal"))*(IFERROR(SUMIFS('03_Base_Vendas'!$I$4:$I$387, '03_Base_Vendas'!$A$4:$A$387, D$85, '03_Base_Vendas'!$B$4:$B$387, "loja_propria")/SUMIFS('03_Base_Vendas'!$I$4:$I$387, '03_Base_Vendas'!$A$4:$A$387, D$85),0)) -> 7292.1816 | E93: =(SUMIFS('04_Base_Despesas'!$D$4:$D$219, '04_Base_Despesas'!$A$4:$A$219, E$85, '04_Base_Despesas'!$B$4:$B$219, "pessoal"))*(IFERROR(SUMIFS('03_Base_Vendas'!$I$4:$I$387, '03_Base_Vendas'!$A$4:$A$387, E$85, '03_Base_Vendas'!$B$4:$B$387, "loja_propria")/SUMIFS('03_Base_Vendas'!$I$4:$I$387, '03_Base_Vendas'!$A$4:$A$387, E$85),0)) -> 8244.8583 | F93: =(SUMIFS('04_Base_Despesas'!$D$4:$D$219, '04_Base_Despesas'!$A$4:$A$219, F$85, '04_Base_Despesas'!$B$4:$B$219, "pessoal"))*(IFERROR(SUMIFS('03_Base_Vendas'!$I$4:$I$387, '03_Base_Vendas'!$A$4:$A$387, F$85, '03_Base_Vendas'!$B$4:$B$387, "loja_propria")/SUMIFS('03_Base_Vendas'!$I$4:$I$387, '03_Base_Vendas'!$A$4:$A$387, F$85),0)) -> 6367.7004 | G93: =(SUMIFS('04_Base_Despesas'!$D$4:$D$219, '04_Base_Despesas'!$A$4:$A$219, G$85, '04_Base_Despesas'!$B$4:$B$219, "pessoal"))*(IFERROR(SUMIFS('03_Base_Vendas'!$I$4:$I$387, '03_Base_Vendas'!$A$4:$A$387, G$85, '03_Base_Vendas'!$B$4:$B$387, "loja_propria")/SUMIFS('03_Base_Vendas'!$I$4:$I$387, '03_Base_Vendas'!$A$4:$A$387, G$85),0)) -> 7313.1403 | H93: =(SUMIFS('04_Base_Despesas'!$D$4:$D$219, '04_Base_Despesas'!$A$4:$A$219, H$85, '04_Base_Despesas'!$B$4:$B$219, "pessoal"))*(IFERROR(SUMIFS('03_Base_Vendas'!$I$4:$I$387, '03_Base_Vendas'!$A$4:$A$387, H$85, '03_Base_Vendas'!$B$4:$B$387, "loja_propria")/SUMIFS('03_Base_Vendas'!$I$4:$I$387, '03_Base_Vendas'!$A$4:$A$387, H$85),0)) -> 6534.5905 | I93: =(SUMIFS('04_Base_Despesas'!$D$4:$D$219, '04_Base_Despesas'!$A$4:$A$219, I$85, '04_Base_Despesas'!$B$4:$B$219, "pessoal"))*(IFERROR(SUMIFS('03_Base_Vendas'!$I$4:$I$387, '03_Base_Vendas'!$A$4:$A$387, I$85, '03_Base_Vendas'!$B$4:$B$387, "loja_propria")/SUMIFS('03_Base_Vendas'!$I$4:$I$387, '03_Base_Vendas'!$A$4:$A$387, I$85),0)) -> 6928.1362 | ... Y93: =(SUMIFS('04_Base_Despesas'!$D$4:$D$219, '04_Base_Despesas'!$A$4:$A$219, Y$85, '04_Base_Despesas'!$B$4:$B$219, "pessoal"))*(IFERROR(SUMIFS('03_Base_Vendas'!$I$4:$I$387, '03_Base_Vendas'!$A$4:$A$387, Y$85, '03_Base_Vendas'!$B$4:$B$387, "loja_propria")/SUMIFS('03_Base_Vendas'!$I$4:$I$387, '03_Base_Vendas'!$A$4:$A$387, Y$85),0)) -> 6359.3155 | Z93: =SUM(B93:Y93) -> 159918.93
A94: (−) Aluguel | B94: =(SUMIFS('04_Base_Despesas'!$D$4:$D$219, '04_Base_Despesas'!$A$4:$A$219, B$85, '04_Base_Despesas'!$B$4:$B$219, "aluguel"))*(IFERROR(SUMIFS('03_Base_Vendas'!$I$4:$I$387, '03_Base_Vendas'!$A$4:$A$387, B$85, '03_Base_Vendas'!$B$4:$B$387, "loja_propria")/SUMIFS('03_Base_Vendas'!$I$4:$I$387, '03_Base_Vendas'!$A$4:$A$387, B$85),0)) -> 967.78271 | C94: =(SUMIFS('04_Base_Despesas'!$D$4:$D$219, '04_Base_Despesas'!$A$4:$A$219, C$85, '04_Base_Despesas'!$B$4:$B$219, "aluguel"))*(IFERROR(SUMIFS('03_Base_Vendas'!$I$4:$I$387, '03_Base_Vendas'!$A$4:$A$387, C$85, '03_Base_Vendas'!$B$4:$B$387, "loja_propria")/SUMIFS('03_Base_Vendas'!$I$4:$I$387, '03_Base_Vendas'!$A$4:$A$387, C$85),0)) -> 1263.4863 | D94: =(SUMIFS('04_Base_Despesas'!$D$4:$D$219, '04_Base_Despesas'!$A$4:$A$219, D$85, '04_Base_Despesas'!$B$4:$B$219, "aluguel"))*(IFERROR(SUMIFS('03_Base_Vendas'!$I$4:$I$387, '03_Base_Vendas'!$A$4:$A$387, D$85, '03_Base_Vendas'!$B$4:$B$387, "loja_propria")/SUMIFS('03_Base_Vendas'!$I$4:$I$387, '03_Base_Vendas'!$A$4:$A$387, D$85),0)) -> 1382.0663 | E94: =(SUMIFS('04_Base_Despesas'!$D$4:$D$219, '04_Base_Despesas'!$A$4:$A$219, E$85, '04_Base_Despesas'!$B$4:$B$219, "aluguel"))*(IFERROR(SUMIFS('03_Base_Vendas'!$I$4:$I$387, '03_Base_Vendas'!$A$4:$A$387, E$85, '03_Base_Vendas'!$B$4:$B$387, "loja_propria")/SUMIFS('03_Base_Vendas'!$I$4:$I$387, '03_Base_Vendas'!$A$4:$A$387, E$85),0)) -> 1583.2156 | F94: =(SUMIFS('04_Base_Despesas'!$D$4:$D$219, '04_Base_Despesas'!$A$4:$A$219, F$85, '04_Base_Despesas'!$B$4:$B$219, "aluguel"))*(IFERROR(SUMIFS('03_Base_Vendas'!$I$4:$I$387, '03_Base_Vendas'!$A$4:$A$387, F$85, '03_Base_Vendas'!$B$4:$B$387, "loja_propria")/SUMIFS('03_Base_Vendas'!$I$4:$I$387, '03_Base_Vendas'!$A$4:$A$387, F$85),0)) -> 1163.6682 | G94: =(SUMIFS('04_Base_Despesas'!$D$4:$D$219, '04_Base_Despesas'!$A$4:$A$219, G$85, '04_Base_Despesas'!$B$4:$B$219, "aluguel"))*(IFERROR(SUMIFS('03_Base_Vendas'!$I$4:$I$387, '03_Base_Vendas'!$A$4:$A$387, G$85, '03_Base_Vendas'!$B$4:$B$387, "loja_propria")/SUMIFS('03_Base_Vendas'!$I$4:$I$387, '03_Base_Vendas'!$A$4:$A$387, G$85),0)) -> 1373.4859 | H94: =(SUMIFS('04_Base_Despesas'!$D$4:$D$219, '04_Base_Despesas'!$A$4:$A$219, H$85, '04_Base_Despesas'!$B$4:$B$219, "aluguel"))*(IFERROR(SUMIFS('03_Base_Vendas'!$I$4:$I$387, '03_Base_Vendas'!$A$4:$A$387, H$85, '03_Base_Vendas'!$B$4:$B$387, "loja_propria")/SUMIFS('03_Base_Vendas'!$I$4:$I$387, '03_Base_Vendas'!$A$4:$A$387, H$85),0)) -> 1196.5118 | I94: =(SUMIFS('04_Base_Despesas'!$D$4:$D$219, '04_Base_Despesas'!$A$4:$A$219, I$85, '04_Base_Despesas'!$B$4:$B$219, "aluguel"))*(IFERROR(SUMIFS('03_Base_Vendas'!$I$4:$I$387, '03_Base_Vendas'!$A$4:$A$387, I$85, '03_Base_Vendas'!$B$4:$B$387, "loja_propria")/SUMIFS('03_Base_Vendas'!$I$4:$I$387, '03_Base_Vendas'!$A$4:$A$387, I$85),0)) -> 1268.046 | ... Y94: =(SUMIFS('04_Base_Despesas'!$D$4:$D$219, '04_Base_Despesas'!$A$4:$A$219, Y$85, '04_Base_Despesas'!$B$4:$B$219, "aluguel"))*(IFERROR(SUMIFS('03_Base_Vendas'!$I$4:$I$387, '03_Base_Vendas'!$A$4:$A$387, Y$85, '03_Base_Vendas'!$B$4:$B$387, "loja_propria")/SUMIFS('03_Base_Vendas'!$I$4:$I$387, '03_Base_Vendas'!$A$4:$A$387, Y$85),0)) -> 1182.0459 | Z94: =SUM(B94:Y94) -> 29607.886
A95: (−) Marketing | B95: =(SUMIFS('04_Base_Despesas'!$D$4:$D$219, '04_Base_Despesas'!$A$4:$A$219, B$85, '04_Base_Despesas'!$B$4:$B$219, "marketing"))*(IFERROR(SUMIFS('03_Base_Vendas'!$I$4:$I$387, '03_Base_Vendas'!$A$4:$A$387, B$85, '03_Base_Vendas'!$B$4:$B$387, "loja_propria")/SUMIFS('03_Base_Vendas'!$I$4:$I$387, '03_Base_Vendas'!$A$4:$A$387, B$85),0)) -> 1818.0431 | C95: =(SUMIFS('04_Base_Despesas'!$D$4:$D$219, '04_Base_Despesas'!$A$4:$A$219, C$85, '04_Base_Despesas'!$B$4:$B$219, "marketing"))*(IFERROR(SUMIFS('03_Base_Vendas'!$I$4:$I$387, '03_Base_Vendas'!$A$4:$A$387, C$85, '03_Base_Vendas'!$B$4:$B$387, "loja_propria")/SUMIFS('03_Base_Vendas'!$I$4:$I$387, '03_Base_Vendas'!$A$4:$A$387, C$85),0)) -> 1615.6971 | D95: =(SUMIFS('04_Base_Despesas'!$D$4:$D$219, '04_Base_Despesas'!$A$4:$A$219, D$85, '04_Base_Despesas'!$B$4:$B$219, "marketing"))*(IFERROR(SUMIFS('03_Base_Vendas'!$I$4:$I$387, '03_Base_Vendas'!$A$4:$A$387, D$85, '03_Base_Vendas'!$B$4:$B$387, "loja_propria")/SUMIFS('03_Base_Vendas'!$I$4:$I$387, '03_Base_Vendas'!$A$4:$A$387, D$85),0)) -> 1598.9896 | E95: =(SUMIFS('04_Base_Despesas'!$D$4:$D$219, '04_Base_Despesas'!$A$4:$A$219, E$85, '04_Base_Despesas'!$B$4:$B$219, "marketing"))*(IFERROR(SUMIFS('03_Base_Vendas'!$I$4:$I$387, '03_Base_Vendas'!$A$4:$A$387, E$85, '03_Base_Vendas'!$B$4:$B$387, "loja_propria")/SUMIFS('03_Base_Vendas'!$I$4:$I$387, '03_Base_Vendas'!$A$4:$A$387, E$85),0)) -> 2061.6283 | F95: =(SUMIFS('04_Base_Despesas'!$D$4:$D$219, '04_Base_Despesas'!$A$4:$A$219, F$85, '04_Base_Despesas'!$B$4:$B$219, "marketing"))*(IFERROR(SUMIFS('03_Base_Vendas'!$I$4:$I$387, '03_Base_Vendas'!$A$4:$A$387, F$85, '03_Base_Vendas'!$B$4:$B$387, "loja_propria")/SUMIFS('03_Base_Vendas'!$I$4:$I$387, '03_Base_Vendas'!$A$4:$A$387, F$85),0)) -> 2094.914 | G95: =(SUMIFS('04_Base_Despesas'!$D$4:$D$219, '04_Base_Despesas'!$A$4:$A$219, G$85, '04_Base_Despesas'!$B$4:$B$219, "marketing"))*(IFERROR(SUMIFS('03_Base_Vendas'!$I$4:$I$387, '03_Base_Vendas'!$A$4:$A$387, G$85, '03_Base_Vendas'!$B$4:$B$387, "loja_propria")/SUMIFS('03_Base_Vendas'!$I$4:$I$387, '03_Base_Vendas'!$A$4:$A$387, G$85),0)) -> 2563.0389 | H95: =(SUMIFS('04_Base_Despesas'!$D$4:$D$219, '04_Base_Despesas'!$A$4:$A$219, H$85, '04_Base_Despesas'!$B$4:$B$219, "marketing"))*(IFERROR(SUMIFS('03_Base_Vendas'!$I$4:$I$387, '03_Base_Vendas'!$A$4:$A$387, H$85, '03_Base_Vendas'!$B$4:$B$387, "loja_propria")/SUMIFS('03_Base_Vendas'!$I$4:$I$387, '03_Base_Vendas'!$A$4:$A$387, H$85),0)) -> 1252.9985 | I95: =(SUMIFS('04_Base_Despesas'!$D$4:$D$219, '04_Base_Despesas'!$A$4:$A$219, I$85, '04_Base_Despesas'!$B$4:$B$219, "marketing"))*(IFERROR(SUMIFS('03_Base_Vendas'!$I$4:$I$387, '03_Base_Vendas'!$A$4:$A$387, I$85, '03_Base_Vendas'!$B$4:$B$387, "loja_propria")/SUMIFS('03_Base_Vendas'!$I$4:$I$387, '03_Base_Vendas'!$A$4:$A$387, I$85),0)) -> 1715.127 | ... Y95: =(SUMIFS('04_Base_Despesas'!$D$4:$D$219, '04_Base_Despesas'!$A$4:$A$219, Y$85, '04_Base_Despesas'!$B$4:$B$219, "marketing"))*(IFERROR(SUMIFS('03_Base_Vendas'!$I$4:$I$387, '03_Base_Vendas'!$A$4:$A$387, Y$85, '03_Base_Vendas'!$B$4:$B$387, "loja_propria")/SUMIFS('03_Base_Vendas'!$I$4:$I$387, '03_Base_Vendas'!$A$4:$A$387, Y$85),0)) -> 1758.2565 | Z95: =SUM(B95:Y95) -> 45350.039
A96: (−) Logística | B96: =(SUMIFS('04_Base_Despesas'!$D$4:$D$219, '04_Base_Despesas'!$A$4:$A$219, B$85, '04_Base_Despesas'!$B$4:$B$219, "logistica"))*(IFERROR(SUMIFS('03_Base_Vendas'!$I$4:$I$387, '03_Base_Vendas'!$A$4:$A$387, B$85, '03_Base_Vendas'!$B$4:$B$387, "loja_propria")/SUMIFS('03_Base_Vendas'!$I$4:$I$387, '03_Base_Vendas'!$A$4:$A$387, B$85),0)) -> 916.22949 | C96: =(SUMIFS('04_Base_Despesas'!$D$4:$D$219, '04_Base_Despesas'!$A$4:$A$219, C$85, '04_Base_Despesas'!$B$4:$B$219, "logistica"))*(IFERROR(SUMIFS('03_Base_Vendas'!$I$4:$I$387, '03_Base_Vendas'!$A$4:$A$387, C$85, '03_Base_Vendas'!$B$4:$B$387, "loja_propria")/SUMIFS('03_Base_Vendas'!$I$4:$I$387, '03_Base_Vendas'!$A$4:$A$387, C$85),0)) -> 1218.344 | D96: =(SUMIFS('04_Base_Despesas'!$D$4:$D$219, '04_Base_Despesas'!$A$4:$A$219, D$85, '04_Base_Despesas'!$B$4:$B$219, "logistica"))*(IFERROR(SUMIFS('03_Base_Vendas'!$I$4:$I$387, '03_Base_Vendas'!$A$4:$A$387, D$85, '03_Base_Vendas'!$B$4:$B$387, "loja_propria")/SUMIFS('03_Base_Vendas'!$I$4:$I$387, '03_Base_Vendas'!$A$4:$A$387, D$85),0)) -> 1420.4833 | E96: =(SUMIFS('04_Base_Despesas'!$D$4:$D$219, '04_Base_Despesas'!$A$4:$A$219, E$85, '04_Base_Despesas'!$B$4:$B$219, "logistica"))*(IFERROR(SUMIFS('03_Base_Vendas'!$I$4:$I$387, '03_Base_Vendas'!$A$4:$A$387, E$85, '03_Base_Vendas'!$B$4:$B$387, "loja_propria")/SUMIFS('03_Base_Vendas'!$I$4:$I$387, '03_Base_Vendas'!$A$4:$A$387, E$85),0)) -> 1809.5521 | F96: =(SUMIFS('04_Base_Despesas'!$D$4:$D$219, '04_Base_Despesas'!$A$4:$A$219, F$85, '04_Base_Despesas'!$B$4:$B$219, "logistica"))*(IFERROR(SUMIFS('03_Base_Vendas'!$I$4:$I$387, '03_Base_Vendas'!$A$4:$A$387, F$85, '03_Base_Vendas'!$B$4:$B$387, "loja_propria")/SUMIFS('03_Base_Vendas'!$I$4:$I$387, '03_Base_Vendas'!$A$4:$A$387, F$85),0)) -> 1208.6128 | G96: =(SUMIFS('04_Base_Despesas'!$D$4:$D$219, '04_Base_Despesas'!$A$4:$A$219, G$85, '04_Base_Despesas'!$B$4:$B$219, "logistica"))*(IFERROR(SUMIFS('03_Base_Vendas'!$I$4:$I$387, '03_Base_Vendas'!$A$4:$A$387, G$85, '03_Base_Vendas'!$B$4:$B$387, "loja_propria")/SUMIFS('03_Base_Vendas'!$I$4:$I$387, '03_Base_Vendas'!$A$4:$A$387, G$85),0)) -> 1362.7771 | H96: =(SUMIFS('04_Base_Despesas'!$D$4:$D$219, '04_Base_Despesas'!$A$4:$A$219, H$85, '04_Base_Despesas'!$B$4:$B$219, "logistica"))*(IFERROR(SUMIFS('03_Base_Vendas'!$I$4:$I$387, '03_Base_Vendas'!$A$4:$A$387, H$85, '03_Base_Vendas'!$B$4:$B$387, "loja_propria")/SUMIFS('03_Base_Vendas'!$I$4:$I$387, '03_Base_Vendas'!$A$4:$A$387, H$85),0)) -> 1352.6276 | I96: =(SUMIFS('04_Base_Despesas'!$D$4:$D$219, '04_Base_Despesas'!$A$4:$A$219, I$85, '04_Base_Despesas'!$B$4:$B$219, "logistica"))*(IFERROR(SUMIFS('03_Base_Vendas'!$I$4:$I$387, '03_Base_Vendas'!$A$4:$A$387, I$85, '03_Base_Vendas'!$B$4:$B$387, "loja_propria")/SUMIFS('03_Base_Vendas'!$I$4:$I$387, '03_Base_Vendas'!$A$4:$A$387, I$85),0)) -> 1435.8672 | ... Y96: =(SUMIFS('04_Base_Despesas'!$D$4:$D$219, '04_Base_Despesas'!$A$4:$A$219, Y$85, '04_Base_Despesas'!$B$4:$B$219, "logistica"))*(IFERROR(SUMIFS('03_Base_Vendas'!$I$4:$I$387, '03_Base_Vendas'!$A$4:$A$387, Y$85, '03_Base_Vendas'!$B$4:$B$387, "loja_propria")/SUMIFS('03_Base_Vendas'!$I$4:$I$387, '03_Base_Vendas'!$A$4:$A$387, Y$85),0)) -> 1157.5539 | Z96: =SUM(B96:Y96) -> 31077.157
A97: (−) Tecnologia | B97: =(SUMIFS('04_Base_Despesas'!$D$4:$D$219, '04_Base_Despesas'!$A$4:$A$219, B$85, '04_Base_Despesas'!$B$4:$B$219, "tecnologia"))*(IFERROR(SUMIFS('03_Base_Vendas'!$I$4:$I$387, '03_Base_Vendas'!$A$4:$A$387, B$85, '03_Base_Vendas'!$B$4:$B$387, "loja_propria")/SUMIFS('03_Base_Vendas'!$I$4:$I$387, '03_Base_Vendas'!$A$4:$A$387, B$85),0)) -> 684.07394 | C97: =(SUMIFS('04_Base_Despesas'!$D$4:$D$219, '04_Base_Despesas'!$A$4:$A$219, C$85, '04_Base_Despesas'!$B$4:$B$219, "tecnologia"))*(IFERROR(SUMIFS('03_Base_Vendas'!$I$4:$I$387, '03_Base_Vendas'!$A$4:$A$387, C$85, '03_Base_Vendas'!$B$4:$B$387, "loja_propria")/SUMIFS('03_Base_Vendas'!$I$4:$I$387, '03_Base_Vendas'!$A$4:$A$387, C$85),0)) -> 880.06877 | D97: =(SUMIFS('04_Base_Despesas'!$D$4:$D$219, '04_Base_Despesas'!$A$4:$A$219, D$85, '04_Base_Despesas'!$B$4:$B$219, "tecnologia"))*(IFERROR(SUMIFS('03_Base_Vendas'!$I$4:$I$387, '03_Base_Vendas'!$A$4:$A$387, D$85, '03_Base_Vendas'!$B$4:$B$387, "loja_propria")/SUMIFS('03_Base_Vendas'!$I$4:$I$387, '03_Base_Vendas'!$A$4:$A$387, D$85),0)) -> 967.893 | E97: =(SUMIFS('04_Base_Despesas'!$D$4:$D$219, '04_Base_Despesas'!$A$4:$A$219, E$85, '04_Base_Despesas'!$B$4:$B$219, "tecnologia"))*(IFERROR(SUMIFS('03_Base_Vendas'!$I$4:$I$387, '03_Base_Vendas'!$A$4:$A$387, E$85, '03_Base_Vendas'!$B$4:$B$387, "loja_propria")/SUMIFS('03_Base_Vendas'!$I$4:$I$387, '03_Base_Vendas'!$A$4:$A$387, E$85),0)) -> 1098.0433 | F97: =(SUMIFS('04_Base_Despesas'!$D$4:$D$219, '04_Base_Despesas'!$A$4:$A$219, F$85, '04_Base_Despesas'!$B$4:$B$219, "tecnologia"))*(IFERROR(SUMIFS('03_Base_Vendas'!$I$4:$I$387, '03_Base_Vendas'!$A$4:$A$387, F$85, '03_Base_Vendas'!$B$4:$B$387, "loja_propria")/SUMIFS('03_Base_Vendas'!$I$4:$I$387, '03_Base_Vendas'!$A$4:$A$387, F$85),0)) -> 807.25503 | G97: =(SUMIFS('04_Base_Despesas'!$D$4:$D$219, '04_Base_Despesas'!$A$4:$A$219, G$85, '04_Base_Despesas'!$B$4:$B$219, "tecnologia"))*(IFERROR(SUMIFS('03_Base_Vendas'!$I$4:$I$387, '03_Base_Vendas'!$A$4:$A$387, G$85, '03_Base_Vendas'!$B$4:$B$387, "loja_propria")/SUMIFS('03_Base_Vendas'!$I$4:$I$387, '03_Base_Vendas'!$A$4:$A$387, G$85),0)) -> 968.73119 | H97: =(SUMIFS('04_Base_Despesas'!$D$4:$D$219, '04_Base_Despesas'!$A$4:$A$219, H$85, '04_Base_Despesas'!$B$4:$B$219, "tecnologia"))*(IFERROR(SUMIFS('03_Base_Vendas'!$I$4:$I$387, '03_Base_Vendas'!$A$4:$A$387, H$85, '03_Base_Vendas'!$B$4:$B$387, "loja_propria")/SUMIFS('03_Base_Vendas'!$I$4:$I$387, '03_Base_Vendas'!$A$4:$A$387, H$85),0)) -> 834.32012 | I97: =(SUMIFS('04_Base_Despesas'!$D$4:$D$219, '04_Base_Despesas'!$A$4:$A$219, I$85, '04_Base_Despesas'!$B$4:$B$219, "tecnologia"))*(IFERROR(SUMIFS('03_Base_Vendas'!$I$4:$I$387, '03_Base_Vendas'!$A$4:$A$387, I$85, '03_Base_Vendas'!$B$4:$B$387, "loja_propria")/SUMIFS('03_Base_Vendas'!$I$4:$I$387, '03_Base_Vendas'!$A$4:$A$387, I$85),0)) -> 906.95322 | ... Y97: =(SUMIFS('04_Base_Despesas'!$D$4:$D$219, '04_Base_Despesas'!$A$4:$A$219, Y$85, '04_Base_Despesas'!$B$4:$B$219, "tecnologia"))*(IFERROR(SUMIFS('03_Base_Vendas'!$I$4:$I$387, '03_Base_Vendas'!$A$4:$A$387, Y$85, '03_Base_Vendas'!$B$4:$B$387, "loja_propria")/SUMIFS('03_Base_Vendas'!$I$4:$I$387, '03_Base_Vendas'!$A$4:$A$387, Y$85),0)) -> 0 | Z97: =SUM(B97:Y97) -> 20000.024
A98: (−) Administrativo | B98: =(SUMIFS('04_Base_Despesas'!$D$4:$D$219, '04_Base_Despesas'!$A$4:$A$219, B$85, '04_Base_Despesas'!$B$4:$B$219, "administrativo"))*(IFERROR(SUMIFS('03_Base_Vendas'!$I$4:$I$387, '03_Base_Vendas'!$A$4:$A$387, B$85, '03_Base_Vendas'!$B$4:$B$387, "loja_propria")/SUMIFS('03_Base_Vendas'!$I$4:$I$387, '03_Base_Vendas'!$A$4:$A$387, B$85),0)) -> 418.60022 | C98: =(SUMIFS('04_Base_Despesas'!$D$4:$D$219, '04_Base_Despesas'!$A$4:$A$219, C$85, '04_Base_Despesas'!$B$4:$B$219, "administrativo"))*(IFERROR(SUMIFS('03_Base_Vendas'!$I$4:$I$387, '03_Base_Vendas'!$A$4:$A$387, C$85, '03_Base_Vendas'!$B$4:$B$387, "loja_propria")/SUMIFS('03_Base_Vendas'!$I$4:$I$387, '03_Base_Vendas'!$A$4:$A$387, C$85),0)) -> 332.4964 | D98: =(SUMIFS('04_Base_Despesas'!$D$4:$D$219, '04_Base_Despesas'!$A$4:$A$219, D$85, '04_Base_Despesas'!$B$4:$B$219, "administrativo"))*(IFERROR(SUMIFS('03_Base_Vendas'!$I$4:$I$387, '03_Base_Vendas'!$A$4:$A$387, D$85, '03_Base_Vendas'!$B$4:$B$387, "loja_propria")/SUMIFS('03_Base_Vendas'!$I$4:$I$387, '03_Base_Vendas'!$A$4:$A$387, D$85),0)) -> 363.70165 | E98: =(SUMIFS('04_Base_Despesas'!$D$4:$D$219, '04_Base_Despesas'!$A$4:$A$219, E$85, '04_Base_Despesas'!$B$4:$B$219, "administrativo"))*(IFERROR(SUMIFS('03_Base_Vendas'!$I$4:$I$387, '03_Base_Vendas'!$A$4:$A$387, E$85, '03_Base_Vendas'!$B$4:$B$387, "loja_propria")/SUMIFS('03_Base_Vendas'!$I$4:$I$387, '03_Base_Vendas'!$A$4:$A$387, E$85),0)) -> 759.49017 | F98: =(SUMIFS('04_Base_Despesas'!$D$4:$D$219, '04_Base_Despesas'!$A$4:$A$219, F$85, '04_Base_Despesas'!$B$4:$B$219, "administrativo"))*(IFERROR(SUMIFS('03_Base_Vendas'!$I$4:$I$387, '03_Base_Vendas'!$A$4:$A$387, F$85, '03_Base_Vendas'!$B$4:$B$387, "loja_propria")/SUMIFS('03_Base_Vendas'!$I$4:$I$387, '03_Base_Vendas'!$A$4:$A$387, F$85),0)) -> 306.22849 | G98: =(SUMIFS('04_Base_Despesas'!$D$4:$D$219, '04_Base_Despesas'!$A$4:$A$219, G$85, '04_Base_Despesas'!$B$4:$B$219, "administrativo"))*(IFERROR(SUMIFS('03_Base_Vendas'!$I$4:$I$387, '03_Base_Vendas'!$A$4:$A$387, G$85, '03_Base_Vendas'!$B$4:$B$387, "loja_propria")/SUMIFS('03_Base_Vendas'!$I$4:$I$387, '03_Base_Vendas'!$A$4:$A$387, G$85),0)) -> 361.44366 | H98: =(SUMIFS('04_Base_Despesas'!$D$4:$D$219, '04_Base_Despesas'!$A$4:$A$219, H$85, '04_Base_Despesas'!$B$4:$B$219, "administrativo"))*(IFERROR(SUMIFS('03_Base_Vendas'!$I$4:$I$387, '03_Base_Vendas'!$A$4:$A$387, H$85, '03_Base_Vendas'!$B$4:$B$387, "loja_propria")/SUMIFS('03_Base_Vendas'!$I$4:$I$387, '03_Base_Vendas'!$A$4:$A$387, H$85),0)) -> 535.62795 | I98: =(SUMIFS('04_Base_Despesas'!$D$4:$D$219, '04_Base_Despesas'!$A$4:$A$219, I$85, '04_Base_Despesas'!$B$4:$B$219, "administrativo"))*(IFERROR(SUMIFS('03_Base_Vendas'!$I$4:$I$387, '03_Base_Vendas'!$A$4:$A$387, I$85, '03_Base_Vendas'!$B$4:$B$387, "loja_propria")/SUMIFS('03_Base_Vendas'!$I$4:$I$387, '03_Base_Vendas'!$A$4:$A$387, I$85),0)) -> 333.69632 | ... Y98: =(SUMIFS('04_Base_Despesas'!$D$4:$D$219, '04_Base_Despesas'!$A$4:$A$219, Y$85, '04_Base_Despesas'!$B$4:$B$219, "administrativo"))*(IFERROR(SUMIFS('03_Base_Vendas'!$I$4:$I$387, '03_Base_Vendas'!$A$4:$A$387, Y$85, '03_Base_Vendas'!$B$4:$B$387, "loja_propria")/SUMIFS('03_Base_Vendas'!$I$4:$I$387, '03_Base_Vendas'!$A$4:$A$387, Y$85),0)) -> 311.06438 | Z98: =SUM(B98:Y98) -> 9698.1432
A99: (−) Outros | B99: =(SUMIFS('04_Base_Despesas'!$D$4:$D$219, '04_Base_Despesas'!$A$4:$A$219, B$85, '04_Base_Despesas'!$B$4:$B$219, "outros"))*(IFERROR(SUMIFS('03_Base_Vendas'!$I$4:$I$387, '03_Base_Vendas'!$A$4:$A$387, B$85, '03_Base_Vendas'!$B$4:$B$387, "loja_propria")/SUMIFS('03_Base_Vendas'!$I$4:$I$387, '03_Base_Vendas'!$A$4:$A$387, B$85),0)) -> 80.624365 | C99: =(SUMIFS('04_Base_Despesas'!$D$4:$D$219, '04_Base_Despesas'!$A$4:$A$219, C$85, '04_Base_Despesas'!$B$4:$B$219, "outros"))*(IFERROR(SUMIFS('03_Base_Vendas'!$I$4:$I$387, '03_Base_Vendas'!$A$4:$A$387, C$85, '03_Base_Vendas'!$B$4:$B$387, "loja_propria")/SUMIFS('03_Base_Vendas'!$I$4:$I$387, '03_Base_Vendas'!$A$4:$A$387, C$85),0)) -> 116.86185 | D99: =(SUMIFS('04_Base_Despesas'!$D$4:$D$219, '04_Base_Despesas'!$A$4:$A$219, D$85, '04_Base_Despesas'!$B$4:$B$219, "outros"))*(IFERROR(SUMIFS('03_Base_Vendas'!$I$4:$I$387, '03_Base_Vendas'!$A$4:$A$387, D$85, '03_Base_Vendas'!$B$4:$B$387, "loja_propria")/SUMIFS('03_Base_Vendas'!$I$4:$I$387, '03_Base_Vendas'!$A$4:$A$387, D$85),0)) -> 125.81313 | E99: =(SUMIFS('04_Base_Despesas'!$D$4:$D$219, '04_Base_Despesas'!$A$4:$A$219, E$85, '04_Base_Despesas'!$B$4:$B$219, "outros"))*(IFERROR(SUMIFS('03_Base_Vendas'!$I$4:$I$387, '03_Base_Vendas'!$A$4:$A$387, E$85, '03_Base_Vendas'!$B$4:$B$387, "loja_propria")/SUMIFS('03_Base_Vendas'!$I$4:$I$387, '03_Base_Vendas'!$A$4:$A$387, E$85),0)) -> 114.7498 | F99: =(SUMIFS('04_Base_Despesas'!$D$4:$D$219, '04_Base_Despesas'!$A$4:$A$219, F$85, '04_Base_Despesas'!$B$4:$B$219, "outros"))*(IFERROR(SUMIFS('03_Base_Vendas'!$I$4:$I$387, '03_Base_Vendas'!$A$4:$A$387, F$85, '03_Base_Vendas'!$B$4:$B$387, "loja_propria")/SUMIFS('03_Base_Vendas'!$I$4:$I$387, '03_Base_Vendas'!$A$4:$A$387, F$85),0)) -> 94.774041 | G99: =(SUMIFS('04_Base_Despesas'!$D$4:$D$219, '04_Base_Despesas'!$A$4:$A$219, G$85, '04_Base_Despesas'!$B$4:$B$219, "outros"))*(IFERROR(SUMIFS('03_Base_Vendas'!$I$4:$I$387, '03_Base_Vendas'!$A$4:$A$387, G$85, '03_Base_Vendas'!$B$4:$B$387, "loja_propria")/SUMIFS('03_Base_Vendas'!$I$4:$I$387, '03_Base_Vendas'!$A$4:$A$387, G$85),0)) -> 111.4432 | H99: =(SUMIFS('04_Base_Despesas'!$D$4:$D$219, '04_Base_Despesas'!$A$4:$A$219, H$85, '04_Base_Despesas'!$B$4:$B$219, "outros"))*(IFERROR(SUMIFS('03_Base_Vendas'!$I$4:$I$387, '03_Base_Vendas'!$A$4:$A$387, H$85, '03_Base_Vendas'!$B$4:$B$387, "loja_propria")/SUMIFS('03_Base_Vendas'!$I$4:$I$387, '03_Base_Vendas'!$A$4:$A$387, H$85),0)) -> 124.00396 | I99: =(SUMIFS('04_Base_Despesas'!$D$4:$D$219, '04_Base_Despesas'!$A$4:$A$219, I$85, '04_Base_Despesas'!$B$4:$B$219, "outros"))*(IFERROR(SUMIFS('03_Base_Vendas'!$I$4:$I$387, '03_Base_Vendas'!$A$4:$A$387, I$85, '03_Base_Vendas'!$B$4:$B$387, "loja_propria")/SUMIFS('03_Base_Vendas'!$I$4:$I$387, '03_Base_Vendas'!$A$4:$A$387, I$85),0)) -> 116.63487 | ... Y99: =(SUMIFS('04_Base_Despesas'!$D$4:$D$219, '04_Base_Despesas'!$A$4:$A$219, Y$85, '04_Base_Despesas'!$B$4:$B$219, "outros"))*(IFERROR(SUMIFS('03_Base_Vendas'!$I$4:$I$387, '03_Base_Vendas'!$A$4:$A$387, Y$85, '03_Base_Vendas'!$B$4:$B$387, "loja_propria")/SUMIFS('03_Base_Vendas'!$I$4:$I$387, '03_Base_Vendas'!$A$4:$A$387, Y$85),0)) -> 80.686366 | Z99: =SUM(B99:Y99) -> 2658.6518
A100: Total Despesas Operac. | B100: =B93+B94+B95+B96+B97+B98+B99 -> 10045.394 | C100: =C93+C94+C95+C96+C97+C98+C99 -> 12359.387 | D100: =D93+D94+D95+D96+D97+D98+D99 -> 13151.129 | E100: =E93+E94+E95+E96+E97+E98+E99 -> 15671.538 | F100: =F93+F94+F95+F96+F97+F98+F99 -> 12043.153 | G100: =G93+G94+G95+G96+G97+G98+G99 -> 14054.06 | H100: =H93+H94+H95+H96+H97+H98+H99 -> 11830.68 | I100: =I93+I94+I95+I96+I97+I98+I99 -> 12704.461 | ... Y100: =Y93+Y94+Y95+Y96+Y97+Y98+Y99 -> 10848.923 | Z100: =SUM(B100:Y100) -> 298310.83
A101: EBITDA | B101: =B91-B100 -> -1892.7236 | C101: =C91-C100 -> -4079.8073 | D101: =D91-D100 -> -1723.1685 | E101: =E91-E100 -> -3824.1875 | F101: =F91-F100 -> 960.98703 | G101: =G91-G100 -> -1384.0103 | H101: =H91-H100 -> -3701.6804 | I101: =I91-I100 -> -4115.4409 | ... Y101: =Y91-Y100 -> 1623.0875 | Z101: =SUM(B101:Y101) -> -35148.125
A102: % Margem EBITDA | B102: =IFERROR(B101/B89,0) -> -0.12384487 | C102: =IFERROR(C101/C89,0) -> -0.2459723 | D102: =IFERROR(D101/D89,0) -> -0.077873223 | E102: =IFERROR(E101/E89,0) -> -0.16412146 | F102: =IFERROR(F101/F89,0) -> 0.040233509 | G102: =IFERROR(G101/G89,0) -> -0.056402687 | H102: =IFERROR(H101/H89,0) -> -0.22746453 | I102: =IFERROR(I101/I89,0) -> -0.23911203 | ... Y102: =IFERROR(Y101/Y89,0) -> 0.067145087 | Z102: =IFERROR($Z$101/$Z$89,0) -> -0.068093686
A103: (−) Depreciação | B103: =(SUMIFS('04_Base_Despesas'!$D$4:$D$219, '04_Base_Despesas'!$A$4:$A$219, B$85, '04_Base_Despesas'!$B$4:$B$219, "depreciacao"))*(IFERROR(SUMIFS('03_Base_Vendas'!$I$4:$I$387, '03_Base_Vendas'!$A$4:$A$387, B$85, '03_Base_Vendas'!$B$4:$B$387, "loja_propria")/SUMIFS('03_Base_Vendas'!$I$4:$I$387, '03_Base_Vendas'!$A$4:$A$387, B$85),0)) -> 224.11685 | C103: =(SUMIFS('04_Base_Despesas'!$D$4:$D$219, '04_Base_Despesas'!$A$4:$A$219, C$85, '04_Base_Despesas'!$B$4:$B$219, "depreciacao"))*(IFERROR(SUMIFS('03_Base_Vendas'!$I$4:$I$387, '03_Base_Vendas'!$A$4:$A$387, C$85, '03_Base_Vendas'!$B$4:$B$387, "loja_propria")/SUMIFS('03_Base_Vendas'!$I$4:$I$387, '03_Base_Vendas'!$A$4:$A$387, C$85),0)) -> 292.59683 | D103: =(SUMIFS('04_Base_Despesas'!$D$4:$D$219, '04_Base_Despesas'!$A$4:$A$219, D$85, '04_Base_Despesas'!$B$4:$B$219, "depreciacao"))*(IFERROR(SUMIFS('03_Base_Vendas'!$I$4:$I$387, '03_Base_Vendas'!$A$4:$A$387, D$85, '03_Base_Vendas'!$B$4:$B$387, "loja_propria")/SUMIFS('03_Base_Vendas'!$I$4:$I$387, '03_Base_Vendas'!$A$4:$A$387, D$85),0)) -> 320.05599 | E103: =(SUMIFS('04_Base_Despesas'!$D$4:$D$219, '04_Base_Despesas'!$A$4:$A$219, E$85, '04_Base_Despesas'!$B$4:$B$219, "depreciacao"))*(IFERROR(SUMIFS('03_Base_Vendas'!$I$4:$I$387, '03_Base_Vendas'!$A$4:$A$387, E$85, '03_Base_Vendas'!$B$4:$B$387, "loja_propria")/SUMIFS('03_Base_Vendas'!$I$4:$I$387, '03_Base_Vendas'!$A$4:$A$387, E$85),0)) -> 366.63773 | F103: =(SUMIFS('04_Base_Despesas'!$D$4:$D$219, '04_Base_Despesas'!$A$4:$A$219, F$85, '04_Base_Despesas'!$B$4:$B$219, "depreciacao"))*(IFERROR(SUMIFS('03_Base_Vendas'!$I$4:$I$387, '03_Base_Vendas'!$A$4:$A$387, F$85, '03_Base_Vendas'!$B$4:$B$387, "loja_propria")/SUMIFS('03_Base_Vendas'!$I$4:$I$387, '03_Base_Vendas'!$A$4:$A$387, F$85),0)) -> 269.47984 | G103: =(SUMIFS('04_Base_Despesas'!$D$4:$D$219, '04_Base_Despesas'!$A$4:$A$219, G$85, '04_Base_Despesas'!$B$4:$B$219, "depreciacao"))*(IFERROR(SUMIFS('03_Base_Vendas'!$I$4:$I$387, '03_Base_Vendas'!$A$4:$A$387, G$85, '03_Base_Vendas'!$B$4:$B$387, "loja_propria")/SUMIFS('03_Base_Vendas'!$I$4:$I$387, '03_Base_Vendas'!$A$4:$A$387, G$85),0)) -> 318.06898 | H103: =(SUMIFS('04_Base_Despesas'!$D$4:$D$219, '04_Base_Despesas'!$A$4:$A$219, H$85, '04_Base_Despesas'!$B$4:$B$219, "depreciacao"))*(IFERROR(SUMIFS('03_Base_Vendas'!$I$4:$I$387, '03_Base_Vendas'!$A$4:$A$387, H$85, '03_Base_Vendas'!$B$4:$B$387, "loja_propria")/SUMIFS('03_Base_Vendas'!$I$4:$I$387, '03_Base_Vendas'!$A$4:$A$387, H$85),0)) -> 277.08568 | I103: =(SUMIFS('04_Base_Despesas'!$D$4:$D$219, '04_Base_Despesas'!$A$4:$A$219, I$85, '04_Base_Despesas'!$B$4:$B$219, "depreciacao"))*(IFERROR(SUMIFS('03_Base_Vendas'!$I$4:$I$387, '03_Base_Vendas'!$A$4:$A$387, I$85, '03_Base_Vendas'!$B$4:$B$387, "loja_propria")/SUMIFS('03_Base_Vendas'!$I$4:$I$387, '03_Base_Vendas'!$A$4:$A$387, I$85),0)) -> 293.65276 | ... Y103: =(SUMIFS('04_Base_Despesas'!$D$4:$D$219, '04_Base_Despesas'!$A$4:$A$219, Y$85, '04_Base_Despesas'!$B$4:$B$219, "depreciacao"))*(IFERROR(SUMIFS('03_Base_Vendas'!$I$4:$I$387, '03_Base_Vendas'!$A$4:$A$387, Y$85, '03_Base_Vendas'!$B$4:$B$387, "loja_propria")/SUMIFS('03_Base_Vendas'!$I$4:$I$387, '03_Base_Vendas'!$A$4:$A$387, Y$85),0)) -> 273.73665 | Z103: =SUM(B103:Y103) -> 6856.5492
A104: EBIT | B104: =B101-B103 -> -2116.8405 | C104: =C101-C103 -> -4372.4042 | D104: =D101-D103 -> -2043.2245 | E104: =E101-E103 -> -4190.8253 | F104: =F101-F103 -> 691.50718 | G104: =G101-G103 -> -1702.0792 | H104: =H101-H103 -> -3978.7661 | I104: =I101-I103 -> -4409.0936 | ... Y104: =Y101-Y103 -> 1349.3508 | Z104: =SUM(B104:Y104) -> -42004.674
A105: (−) Despesas Financeiras | B105: =(SUMIFS('04_Base_Despesas'!$D$4:$D$219, '04_Base_Despesas'!$A$4:$A$219, B$85, '04_Base_Despesas'!$B$4:$B$219, "financeiro"))*(IFERROR(SUMIFS('03_Base_Vendas'!$I$4:$I$387, '03_Base_Vendas'!$A$4:$A$387, B$85, '03_Base_Vendas'!$B$4:$B$387, "loja_propria")/SUMIFS('03_Base_Vendas'!$I$4:$I$387, '03_Base_Vendas'!$A$4:$A$387, B$85),0)) -> 139.09977 | C105: =(SUMIFS('04_Base_Despesas'!$D$4:$D$219, '04_Base_Despesas'!$A$4:$A$219, C$85, '04_Base_Despesas'!$B$4:$B$219, "financeiro"))*(IFERROR(SUMIFS('03_Base_Vendas'!$I$4:$I$387, '03_Base_Vendas'!$A$4:$A$387, C$85, '03_Base_Vendas'!$B$4:$B$387, "loja_propria")/SUMIFS('03_Base_Vendas'!$I$4:$I$387, '03_Base_Vendas'!$A$4:$A$387, C$85),0)) -> 179.75686 | D105: =(SUMIFS('04_Base_Despesas'!$D$4:$D$219, '04_Base_Despesas'!$A$4:$A$219, D$85, '04_Base_Despesas'!$B$4:$B$219, "financeiro"))*(IFERROR(SUMIFS('03_Base_Vendas'!$I$4:$I$387, '03_Base_Vendas'!$A$4:$A$387, D$85, '03_Base_Vendas'!$B$4:$B$387, "loja_propria")/SUMIFS('03_Base_Vendas'!$I$4:$I$387, '03_Base_Vendas'!$A$4:$A$387, D$85),0)) -> 195.78932 | E105: =(SUMIFS('04_Base_Despesas'!$D$4:$D$219, '04_Base_Despesas'!$A$4:$A$219, E$85, '04_Base_Despesas'!$B$4:$B$219, "financeiro"))*(IFERROR(SUMIFS('03_Base_Vendas'!$I$4:$I$387, '03_Base_Vendas'!$A$4:$A$387, E$85, '03_Base_Vendas'!$B$4:$B$387, "loja_propria")/SUMIFS('03_Base_Vendas'!$I$4:$I$387, '03_Base_Vendas'!$A$4:$A$387, E$85),0)) -> 216.33391 | F105: =(SUMIFS('04_Base_Despesas'!$D$4:$D$219, '04_Base_Despesas'!$A$4:$A$219, F$85, '04_Base_Despesas'!$B$4:$B$219, "financeiro"))*(IFERROR(SUMIFS('03_Base_Vendas'!$I$4:$I$387, '03_Base_Vendas'!$A$4:$A$387, F$85, '03_Base_Vendas'!$B$4:$B$387, "loja_propria")/SUMIFS('03_Base_Vendas'!$I$4:$I$387, '03_Base_Vendas'!$A$4:$A$387, F$85),0)) -> 165.73453 | G105: =(SUMIFS('04_Base_Despesas'!$D$4:$D$219, '04_Base_Despesas'!$A$4:$A$219, G$85, '04_Base_Despesas'!$B$4:$B$219, "financeiro"))*(IFERROR(SUMIFS('03_Base_Vendas'!$I$4:$I$387, '03_Base_Vendas'!$A$4:$A$387, G$85, '03_Base_Vendas'!$B$4:$B$387, "loja_propria")/SUMIFS('03_Base_Vendas'!$I$4:$I$387, '03_Base_Vendas'!$A$4:$A$387, G$85),0)) -> 184.83795 | H105: =(SUMIFS('04_Base_Despesas'!$D$4:$D$219, '04_Base_Despesas'!$A$4:$A$219, H$85, '04_Base_Despesas'!$B$4:$B$219, "financeiro"))*(IFERROR(SUMIFS('03_Base_Vendas'!$I$4:$I$387, '03_Base_Vendas'!$A$4:$A$387, H$85, '03_Base_Vendas'!$B$4:$B$387, "loja_propria")/SUMIFS('03_Base_Vendas'!$I$4:$I$387, '03_Base_Vendas'!$A$4:$A$387, H$85),0)) -> 685.91487 | I105: =(SUMIFS('04_Base_Despesas'!$D$4:$D$219, '04_Base_Despesas'!$A$4:$A$219, I$85, '04_Base_Despesas'!$B$4:$B$219, "financeiro"))*(IFERROR(SUMIFS('03_Base_Vendas'!$I$4:$I$387, '03_Base_Vendas'!$A$4:$A$387, I$85, '03_Base_Vendas'!$B$4:$B$387, "loja_propria")/SUMIFS('03_Base_Vendas'!$I$4:$I$387, '03_Base_Vendas'!$A$4:$A$387, I$85),0)) -> 175.34807 | ... Y105: =(SUMIFS('04_Base_Despesas'!$D$4:$D$219, '04_Base_Despesas'!$A$4:$A$219, Y$85, '04_Base_Despesas'!$B$4:$B$219, "financeiro"))*(IFERROR(SUMIFS('03_Base_Vendas'!$I$4:$I$387, '03_Base_Vendas'!$A$4:$A$387, Y$85, '03_Base_Vendas'!$B$4:$B$387, "loja_propria")/SUMIFS('03_Base_Vendas'!$I$4:$I$387, '03_Base_Vendas'!$A$4:$A$387, Y$85),0)) -> 172.18782 | Z105: =SUM(B105:Y105) -> 4618.9744
A106: Resultado Operacional | B106: =B104-B105 -> -2255.9403 | C106: =C104-C105 -> -4552.161 | D106: =D104-D105 -> -2239.0139 | E106: =E104-E105 -> -4407.1592 | F106: =F104-F105 -> 525.77265 | G106: =G104-G105 -> -1886.9172 | H106: =H104-H105 -> -4664.681 | I106: =I104-I105 -> -4584.4417 | ... Y106: =Y104-Y105 -> 1177.163 | Z106: =SUM(B106:Y106) -> -46623.648
A107: % Margem Operacional | B107: =IFERROR(B106/B89,0) -> -0.14761089 | C107: =IFERROR(C106/C89,0) -> -0.27445059 | D107: =IFERROR(D106/D89,0) -> -0.10118524 | E107: =IFERROR(E106/E89,0) -> -0.18914067 | F107: =IFERROR(F106/F89,0) -> 0.02201245 | G107: =IFERROR(G106/G89,0) -> -0.076897695 | H107: =IFERROR(H106/H89,0) -> -0.28663994 | I107: =IFERROR(I106/I89,0) -> -0.26636154 | ... Y107: =IFERROR(Y106/Y89,0) -> 0.048697753 | Z107: =IFERROR($Z$106/$Z$89,0) -> -0.090325617

Sheet 08_DRE_por_Categoria
A1: 08 — DRE POR CATEGORIA
A2: DREs replicadas por categoria de produto. Despesas centrais rateadas pelo share de receita líquida.
A4: Rateio: despesas operacionais distribuídas por categoria proporcionalmente à receita líquida do mês. Receita, devoluções, comissões, CMV e margem de contribuição são alocação direta pela categoria.
A6: Categoria: Skincare
A7: Item | B7: 2023-01 | C7: 2023-02 | D7: 2023-03 | E7: 2023-04 | F7: 2023-05 | G7: 2023-06 | H7: 2023-07 | I7: 2023-08 | J7: 2023-09 | K7: 2023-10 | L7: 2023-11 | M7: 2023-12 | N7: 2024-01 | O7: 2024-02 | P7: 2024-03 | Q7: 2024-04 | R7: 2024-05 | S7: 2024-06 | T7: 2024-07 | U7: 2024-08 | V7: 2024-09 | W7: 2024-10 | X7: 2024-11 | Y7: 2024-12 | Z7: Total 24m
A8: Receita Bruta | B8: =SUMIFS('03_Base_Vendas'!$F$4:$F$387, '03_Base_Vendas'!$A$4:$A$387, B$7, '03_Base_Vendas'!$C$4:$C$387, "skincare") -> 60014.81 | C8: =SUMIFS('03_Base_Vendas'!$F$4:$F$387, '03_Base_Vendas'!$A$4:$A$387, C$7, '03_Base_Vendas'!$C$4:$C$387, "skincare") -> 49445.6 | D8: =SUMIFS('03_Base_Vendas'!$F$4:$F$387, '03_Base_Vendas'!$A$4:$A$387, D$7, '03_Base_Vendas'!$C$4:$C$387, "skincare") -> 57384.22 | E8: =SUMIFS('03_Base_Vendas'!$F$4:$F$387, '03_Base_Vendas'!$A$4:$A$387, E$7, '03_Base_Vendas'!$C$4:$C$387, "skincare") -> 59605.86 | F8: =SUMIFS('03_Base_Vendas'!$F$4:$F$387, '03_Base_Vendas'!$A$4:$A$387, F$7, '03_Base_Vendas'!$C$4:$C$387, "skincare") -> 84801.17 | G8: =SUMIFS('03_Base_Vendas'!$F$4:$F$387, '03_Base_Vendas'!$A$4:$A$387, G$7, '03_Base_Vendas'!$C$4:$C$387, "skincare") -> 54393.6 | H8: =SUMIFS('03_Base_Vendas'!$F$4:$F$387, '03_Base_Vendas'!$A$4:$A$387, H$7, '03_Base_Vendas'!$C$4:$C$387, "skincare") -> 44403 | I8: =SUMIFS('03_Base_Vendas'!$F$4:$F$387, '03_Base_Vendas'!$A$4:$A$387, I$7, '03_Base_Vendas'!$C$4:$C$387, "skincare") -> 55761.17 | ... Y8: =SUMIFS('03_Base_Vendas'!$F$4:$F$387, '03_Base_Vendas'!$A$4:$A$387, Y$7, '03_Base_Vendas'!$C$4:$C$387, "skincare") -> 61483.62 | Z8: =SUM(B8:Y8) -> 1492530.5
A9: (−) Devoluções | B9: =SUMIFS('03_Base_Vendas'!$G$4:$G$387, '03_Base_Vendas'!$A$4:$A$387, B$7, '03_Base_Vendas'!$C$4:$C$387, "skincare") -> 1779.65 | C9: =SUMIFS('03_Base_Vendas'!$G$4:$G$387, '03_Base_Vendas'!$A$4:$A$387, C$7, '03_Base_Vendas'!$C$4:$C$387, "skincare") -> 3278.9 | D9: =SUMIFS('03_Base_Vendas'!$G$4:$G$387, '03_Base_Vendas'!$A$4:$A$387, D$7, '03_Base_Vendas'!$C$4:$C$387, "skincare") -> 1006.94 | E9: =SUMIFS('03_Base_Vendas'!$G$4:$G$387, '03_Base_Vendas'!$A$4:$A$387, E$7, '03_Base_Vendas'!$C$4:$C$387, "skincare") -> 3242.52 | F9: =SUMIFS('03_Base_Vendas'!$G$4:$G$387, '03_Base_Vendas'!$A$4:$A$387, F$7, '03_Base_Vendas'!$C$4:$C$387, "skincare") -> 3735.79 | G9: =SUMIFS('03_Base_Vendas'!$G$4:$G$387, '03_Base_Vendas'!$A$4:$A$387, G$7, '03_Base_Vendas'!$C$4:$C$387, "skincare") -> 1450.84 | H9: =SUMIFS('03_Base_Vendas'!$G$4:$G$387, '03_Base_Vendas'!$A$4:$A$387, H$7, '03_Base_Vendas'!$C$4:$C$387, "skincare") -> 2014.88 | I9: =SUMIFS('03_Base_Vendas'!$G$4:$G$387, '03_Base_Vendas'!$A$4:$A$387, I$7, '03_Base_Vendas'!$C$4:$C$387, "skincare") -> 1421.26 | ... Y9: =SUMIFS('03_Base_Vendas'!$G$4:$G$387, '03_Base_Vendas'!$A$4:$A$387, Y$7, '03_Base_Vendas'!$C$4:$C$387, "skincare") -> 2186.36 | Z9: =SUM(B9:Y9) -> 64711.02
A10: (−) Comissões de canal | B10: =SUMIFS('03_Base_Vendas'!$H$4:$H$387, '03_Base_Vendas'!$A$4:$A$387, B$7, '03_Base_Vendas'!$C$4:$C$387, "skincare") -> 5631.96 | C10: =SUMIFS('03_Base_Vendas'!$H$4:$H$387, '03_Base_Vendas'!$A$4:$A$387, C$7, '03_Base_Vendas'!$C$4:$C$387, "skincare") -> 3991.73 | D10: =SUMIFS('03_Base_Vendas'!$H$4:$H$387, '03_Base_Vendas'!$A$4:$A$387, D$7, '03_Base_Vendas'!$C$4:$C$387, "skincare") -> 4974.29 | E10: =SUMIFS('03_Base_Vendas'!$H$4:$H$387, '03_Base_Vendas'!$A$4:$A$387, E$7, '03_Base_Vendas'!$C$4:$C$387, "skincare") -> 4630.95 | F10: =SUMIFS('03_Base_Vendas'!$H$4:$H$387, '03_Base_Vendas'!$A$4:$A$387, F$7, '03_Base_Vendas'!$C$4:$C$387, "skincare") -> 7414.25 | G10: =SUMIFS('03_Base_Vendas'!$H$4:$H$387, '03_Base_Vendas'!$A$4:$A$387, G$7, '03_Base_Vendas'!$C$4:$C$387, "skincare") -> 4187.12 | H10: =SUMIFS('03_Base_Vendas'!$H$4:$H$387, '03_Base_Vendas'!$A$4:$A$387, H$7, '03_Base_Vendas'!$C$4:$C$387, "skincare") -> 3720.68 | I10: =SUMIFS('03_Base_Vendas'!$H$4:$H$387, '03_Base_Vendas'!$A$4:$A$387, I$7, '03_Base_Vendas'!$C$4:$C$387, "skincare") -> 4804.86 | ... Y10: =SUMIFS('03_Base_Vendas'!$H$4:$H$387, '03_Base_Vendas'!$A$4:$A$387, Y$7, '03_Base_Vendas'!$C$4:$C$387, "skincare") -> 3341.39 | Z10: =SUM(B10:Y10) -> 127687.21
A11: Receita Líquida | B11: =B8-B9-B10 -> 52603.2 | C11: =C8-C9-C10 -> 42174.97 | D11: =D8-D9-D10 -> 51402.99 | E11: =E8-E9-E10 -> 51732.39 | F11: =F8-F9-F10 -> 73651.13 | G11: =G8-G9-G10 -> 48755.64 | H11: =H8-H9-H10 -> 38667.44 | I11: =I8-I9-I10 -> 49535.05 | ... Y11: =Y8-Y9-Y10 -> 55955.87 | Z11: =SUM(B11:Y11) -> 1300132.3
A12: (−) CMV | B12: =SUMIFS('03_Base_Vendas'!$J$4:$J$387, '03_Base_Vendas'!$A$4:$A$387, B$7, '03_Base_Vendas'!$C$4:$C$387, "skincare") -> 23607.89 | C12: =SUMIFS('03_Base_Vendas'!$J$4:$J$387, '03_Base_Vendas'!$A$4:$A$387, C$7, '03_Base_Vendas'!$C$4:$C$387, "skincare") -> 19397.76 | D12: =SUMIFS('03_Base_Vendas'!$J$4:$J$387, '03_Base_Vendas'!$A$4:$A$387, D$7, '03_Base_Vendas'!$C$4:$C$387, "skincare") -> 22710.23 | E12: =SUMIFS('03_Base_Vendas'!$J$4:$J$387, '03_Base_Vendas'!$A$4:$A$387, E$7, '03_Base_Vendas'!$C$4:$C$387, "skincare") -> 23611.18 | F12: =SUMIFS('03_Base_Vendas'!$J$4:$J$387, '03_Base_Vendas'!$A$4:$A$387, F$7, '03_Base_Vendas'!$C$4:$C$387, "skincare") -> 33428.84 | G12: =SUMIFS('03_Base_Vendas'!$J$4:$J$387, '03_Base_Vendas'!$A$4:$A$387, G$7, '03_Base_Vendas'!$C$4:$C$387, "skincare") -> 21791.18 | H12: =SUMIFS('03_Base_Vendas'!$J$4:$J$387, '03_Base_Vendas'!$A$4:$A$387, H$7, '03_Base_Vendas'!$C$4:$C$387, "skincare") -> 17376.13 | I12: =SUMIFS('03_Base_Vendas'!$J$4:$J$387, '03_Base_Vendas'!$A$4:$A$387, I$7, '03_Base_Vendas'!$C$4:$C$387, "skincare") -> 22007.06 | ... Y12: =SUMIFS('03_Base_Vendas'!$J$4:$J$387, '03_Base_Vendas'!$A$4:$A$387, Y$7, '03_Base_Vendas'!$C$4:$C$387, "skincare") -> 24417.66 | Z12: =SUM(B12:Y12) -> 589985.8
A13: Margem de Contribuição | B13: =B11-B12 -> 28995.31 | C13: =C11-C12 -> 22777.21 | D13: =D11-D12 -> 28692.76 | E13: =E11-E12 -> 28121.21 | F13: =F11-F12 -> 40222.29 | G13: =G11-G12 -> 26964.46 | H13: =H11-H12 -> 21291.31 | I13: =I11-I12 -> 27527.99 | ... Y13: =Y11-Y12 -> 31538.21 | Z13: =SUM(B13:Y13) -> 710146.48
A14: % Margem de Contribuição | B14: =IFERROR(B13/B11,0) -> 0.5512081 | C14: =IFERROR(C13/C11,0) -> 0.54006464 | D14: =IFERROR(D13/D11,0) -> 0.55819243 | E14: =IFERROR(E13/E11,0) -> 0.54359 | F14: =IFERROR(F13/F11,0) -> 0.54611912 | G14: =IFERROR(G13/G11,0) -> 0.55305314 | H14: =IFERROR(H13/H11,0) -> 0.55062632 | I14: =IFERROR(I13/I11,0) -> 0.55572751 | ... Y14: =IFERROR(Y13/Y11,0) -> 0.56362648 | Z14: =IFERROR($Z$13/$Z$11,0) -> 0.54621094
A15: (−) Pessoal | B15: =(SUMIFS('04_Base_Despesas'!$D$4:$D$219, '04_Base_Despesas'!$A$4:$A$219, B$7, '04_Base_Despesas'!$B$4:$B$219, "pessoal"))*(IFERROR(SUMIFS('03_Base_Vendas'!$I$4:$I$387, '03_Base_Vendas'!$A$4:$A$387, B$7, '03_Base_Vendas'!$C$4:$C$387, "skincare")/SUMIFS('03_Base_Vendas'!$I$4:$I$387, '03_Base_Vendas'!$A$4:$A$387, B$7),0)) -> 17760.535 | C15: =(SUMIFS('04_Base_Despesas'!$D$4:$D$219, '04_Base_Despesas'!$A$4:$A$219, C$7, '04_Base_Despesas'!$B$4:$B$219, "pessoal"))*(IFERROR(SUMIFS('03_Base_Vendas'!$I$4:$I$387, '03_Base_Vendas'!$A$4:$A$387, C$7, '03_Base_Vendas'!$C$4:$C$387, "skincare")/SUMIFS('03_Base_Vendas'!$I$4:$I$387, '03_Base_Vendas'!$A$4:$A$387, C$7),0)) -> 17627.35 | D15: =(SUMIFS('04_Base_Despesas'!$D$4:$D$219, '04_Base_Despesas'!$A$4:$A$219, D$7, '04_Base_Despesas'!$B$4:$B$219, "pessoal"))*(IFERROR(SUMIFS('03_Base_Vendas'!$I$4:$I$387, '03_Base_Vendas'!$A$4:$A$387, D$7, '03_Base_Vendas'!$C$4:$C$387, "skincare")/SUMIFS('03_Base_Vendas'!$I$4:$I$387, '03_Base_Vendas'!$A$4:$A$387, D$7),0)) -> 16939.721 | E15: =(SUMIFS('04_Base_Despesas'!$D$4:$D$219, '04_Base_Despesas'!$A$4:$A$219, E$7, '04_Base_Despesas'!$B$4:$B$219, "pessoal"))*(IFERROR(SUMIFS('03_Base_Vendas'!$I$4:$I$387, '03_Base_Vendas'!$A$4:$A$387, E$7, '03_Base_Vendas'!$C$4:$C$387, "skincare")/SUMIFS('03_Base_Vendas'!$I$4:$I$387, '03_Base_Vendas'!$A$4:$A$387, E$7),0)) -> 18305.092 | F15: =(SUMIFS('04_Base_Despesas'!$D$4:$D$219, '04_Base_Despesas'!$A$4:$A$219, F$7, '04_Base_Despesas'!$B$4:$B$219, "pessoal"))*(IFERROR(SUMIFS('03_Base_Vendas'!$I$4:$I$387, '03_Base_Vendas'!$A$4:$A$387, F$7, '03_Base_Vendas'!$C$4:$C$387, "skincare")/SUMIFS('03_Base_Vendas'!$I$4:$I$387, '03_Base_Vendas'!$A$4:$A$387, F$7),0)) -> 19635.069 | G15: =(SUMIFS('04_Base_Despesas'!$D$4:$D$219, '04_Base_Despesas'!$A$4:$A$219, G$7, '04_Base_Despesas'!$B$4:$B$219, "pessoal"))*(IFERROR(SUMIFS('03_Base_Vendas'!$I$4:$I$387, '03_Base_Vendas'!$A$4:$A$387, G$7, '03_Base_Vendas'!$C$4:$C$387, "skincare")/SUMIFS('03_Base_Vendas'!$I$4:$I$387, '03_Base_Vendas'!$A$4:$A$387, G$7),0)) -> 14530.791 | H15: =(SUMIFS('04_Base_Despesas'!$D$4:$D$219, '04_Base_Despesas'!$A$4:$A$219, H$7, '04_Base_Despesas'!$B$4:$B$219, "pessoal"))*(IFERROR(SUMIFS('03_Base_Vendas'!$I$4:$I$387, '03_Base_Vendas'!$A$4:$A$387, H$7, '03_Base_Vendas'!$C$4:$C$387, "skincare")/SUMIFS('03_Base_Vendas'!$I$4:$I$387, '03_Base_Vendas'!$A$4:$A$387, H$7),0)) -> 15526.678 | I15: =(SUMIFS('04_Base_Despesas'!$D$4:$D$219, '04_Base_Despesas'!$A$4:$A$219, I$7, '04_Base_Despesas'!$B$4:$B$219, "pessoal"))*(IFERROR(SUMIFS('03_Base_Vendas'!$I$4:$I$387, '03_Base_Vendas'!$A$4:$A$387, I$7, '03_Base_Vendas'!$C$4:$C$387, "skincare")/SUMIFS('03_Base_Vendas'!$I$4:$I$387, '03_Base_Vendas'!$A$4:$A$387, I$7),0)) -> 19939.492 | ... Y15: =(SUMIFS('04_Base_Despesas'!$D$4:$D$219, '04_Base_Despesas'!$A$4:$A$219, Y$7, '04_Base_Despesas'!$B$4:$B$219, "pessoal"))*(IFERROR(SUMIFS('03_Base_Vendas'!$I$4:$I$387, '03_Base_Vendas'!$A$4:$A$387, Y$7, '03_Base_Vendas'!$C$4:$C$387, "skincare")/SUMIFS('03_Base_Vendas'!$I$4:$I$387, '03_Base_Vendas'!$A$4:$A$387, Y$7),0)) -> 14720.696 | Z15: =SUM(B15:Y15) -> 403607.6
